Workbook

Sheet Controls
B2: PO SPEND TRACKER — CONTROLS
B3: Central assumptions. Blue cells on a cream fill are the only ones you edit. Everything else calculates.
B5: FY Start | C5: 45931 | D5: First day of the fiscal year (Oct 1). Drives every PO, vendor and monthly figure.
B6: FY End | C6: 46295 | D6: Last day of the fiscal year (Sep 30).
B7: Last Closed Month | C7: 46204 | D7: First day of the most recent CLOSED invoice month. Drives months elapsed, run-rate and projections.
B8: Watch Threshold | C8: 0.8 | D8: A PO at or above this % of its funds is flagged Watch.
B9: Trend Window (months) | C9: 3 | D9: How many trailing closed months feed the run-rate.
B10: Months Elapsed | C10: =(YEAR(Controls!$C$7)-YEAR(Controls!$C$5))*12+(MONTH(Controls!$C$7)-MONTH(Controls!$C$5))+1 -> 10 | D10: Closed months from FY Start through Last Closed Month.
B11: Months Remaining | C11: =12-Controls!$C$10 -> 2 | D11: Remaining months in the fiscal year.
B12: Trend Start | C12: =EDATE(Controls!$C$7,-(Controls!$C$9-1)) -> 46143 | D12: First month included in the trailing run-rate window.
B14: DATA COVERAGE (read-only)
B15: Latest invoice date in data | C15: =IFERROR(MAX(_MainTable!$G$2:$G$2001),0) -> 46252 | D15: Newest Invoice Date present on the Invoices tab. Keep Last Closed Month at or before this.
B16: Invoice rows loaded | C16: =COUNT(_MainTable!$G$2:$G$2001) -> 328 | D16: Rows on the Invoices tab with a usable Invoice Date.
B17: Change-order rows loaded | C17: =COUNT('SC Change Orders'!$C$2:$C$501) -> 36 | D17: Rows on the Change Orders tab with a usable Date Submitted.
B18: POs in this fiscal year | C18: =COUNT('PO Index'!$B$5:$B$84) -> 43 | D18: Distinct POs with activity between FY Start and FY End. The tracker sizes itself to this.
B19: Total invoiced this FY | C19: =SUMIFS(_MainTable!$K$2:$K$2001,_MainTable!$G$2:$G$2001,">="&Controls!$C$5,_MainTable!$G$2:$G$2001,"<="&Controls!$C$6) -> 13750125 | D19: Every FY invoice dollar, whether or not the PO carries a funding record.
B21: RANGE CAPACITY
B22: Wired range status | C22: =IF(OR(COUNT(_MainTable!$G$2:$G$2001)>=1979,COUNT('SC Change Orders'!$C$2:$C$501)>=479),"EXTEND RANGES","OK") -> OK | D22: Formulas read 2,000 invoice rows and 500 change-order rows. If a refresh ever pushes past that, this says EXTEND RANGES and the ranges need widening.
B24: HOW THE FUNDING NUMBERS ARE BUILT
B25: Starting Funds = smallest "Original Amount" on the PO's change orders inside the FY window (MINIFS).
B26: Total Funds Added = sum of "Amount Added" on the PO's change orders inside the FY window (SUMIFS).
B27: Total Available = Starting Funds + Total Funds Added.
B28: Spend to Date = sum of "Invoice $" on _MainTable for that PO, invoice-dated inside the FY window.
B29: Same definitions as the Data tab of Vendor_PO_Spending, so the figures tie to what you have today.
B30: Rows the change-order log records ambiguously are listed on the Data Quality tab.
B32: HOW TO CONNECT THIS TO YOUR LIVE POWER QUERIES
B33: This file is a working snapshot. To drive it from the live SharePoint queries instead:
B35: 1. Open Vendor_PO_Spending.xlsx (the workbook that holds the queries) alongside this one.
B36: 2. Here, click the "Controls" tab, then SHIFT-click "Data Quality" so all five tabs are selected together.
B37: Copying them in one go is what keeps the formulas between them intact.
... B47: full ownership detail. Nothing else needs changing — the PO list is driven by the data, not by a list.

Sheet PO Tracker
A1: PO SPEND TRACKER
A2: One row per PO with change-order or invoice activity between FY Start and FY End — the list builds itself, nothing here is typed. Funding comes from the Change Orders tab, spend from the Invoices tab. Run-rate is the trailing window from Controls, falling back to cumulative early in the year.
A4: Vendor | B4: PO | C4: Service | D4: Sr Leader | E4: Primary Owner | F4: Starting Funds | G4: Total Funds Added | H4: Total Available Funding | I4: Spend to Date | J4: Actual % of Funds | K4: Total Remaining | L4: Run-Rate / Mo | M4: Projected Add'l Spend | N4: Projected Total Spend | O4: Projected % of Funds | P4: Projected Over/(Under) | Q4: Mos to Depletion | R4: Status
A5: =IF($B5="","",IF((IFERROR(INDEX(_RefTable!$A$2:$A$501,MATCH($B5,_RefTable!$C$2:$C$501,0)),IFERROR(INDEX(_MainTable!$A$2:$A$2001,MATCH($B5,_MainTable!$F$2:$F$2001,0)),IFERROR(INDEX('SC Change Orders'!$A$2:$A$501,MATCH($B5,'SC Change Orders'!$B$2:$B$501,0)),"(unknown vendor)"))))&""="","—",(IFERROR(INDEX(_RefTable!$A$2:$A$501,MATCH($B5,_RefTable!$C$2:$C$501,0)),IFERROR(INDEX(_MainTable!$A$2:$A$2001,MATCH($B5,_MainTable!$F$2:$F$2001,0)),IFERROR(INDEX('SC Change Orders'!$A$2:$A$501,MATCH($B5,'SC Change Orders'!$B$2:$B$501,0)),"(unknown vendor)")))))) -> FMS INC | B5: =IFERROR(INDEX('PO Index'!$B$5:$B$84,1),"") -> 7892 | C5: =IF($B5="","",IF((IFERROR(INDEX(_RefTable!$B$2:$B$501,MATCH($B5,_RefTable!$C$2:$C$501,0))&IF(COUNTIF(_RefTable!$C$2:$C$501,$B5)>1," (+"&COUNTIF(_RefTable!$C$2:$C$501,$B5)-1&" more)",""),IFERROR(INDEX(_MainTable!$B$2:$B$2001,MATCH($B5,_MainTable!$F$2:$F$2001,0)),"")))&""="","—",(IFERROR(INDEX(_RefTable!$B$2:$B$501,MATCH($B5,_RefTable!$C$2:$C$501,0))&IF(COUNTIF(_RefTable!$C$2:$C$501,$B5)>1," (+"&COUNTIF(_RefTable!$C$2:$C$501,$B5)-1&" more)",""),IFERROR(INDEX(_MainTable!$B$2:$B$2001,MATCH($B5,_MainTable!$F$2:$F$2001,0)),""))))) -> McCall BD | D5: =IF($B5="","",IF((IFERROR(INDEX(_RefTable!$E$2:$E$501,MATCH($B5,_RefTable!$C$2:$C$501,0)),IFERROR(INDEX(_MainTable!$C$2:$C$2001,MATCH($B5,_MainTable!$F$2:$F$2001,0)),"")))&""="","—",(IFERROR(INDEX(_RefTable!$E$2:$E$501,MATCH($B5,_RefTable!$C$2:$C$501,0)),IFERROR(INDEX(_MainTable!$C$2:$C$2001,MATCH($B5,_MainTable!$F$2:$F$2001,0)),""))))) -> Jake Reid | E5: =IF($B5="","",IF((IFERROR(INDEX(_RefTable!$F$2:$F$501,MATCH($B5,_RefTable!$C$2:$C$501,0)),IFERROR(INDEX(_MainTable!$D$2:$D$2001,MATCH($B5,_MainTable!$F$2:$F$2001,0)),"")))&""="","—",(IFERROR(INDEX(_RefTable!$F$2:$F$501,MATCH($B5,_RefTable!$C$2:$C$501,0)),IFERROR(INDEX(_MainTable!$D$2:$D$2001,MATCH($B5,_MainTable!$F$2:$F$2001,0)),""))))) -> Letisia Speelman | F5: =IF($B5="","",IFERROR(_xlfn.MINIFS('SC Change Orders'!$E$2:$E$501,'SC Change Orders'!$B$2:$B$501,$B5,'SC Change Orders'!$C$2:$C$501,">="&Controls!$C$5,'SC Change Orders'!$C$2:$C$501,"<="&Controls!$C$6),0)) -> 0 | G5: =IF($B5="","",SUMIFS('SC Change Orders'!$F$2:$F$501,'SC Change Orders'!$B$2:$B$501,$B5,'SC Change Orders'!$C$2:$C$501,">="&Controls!$C$5,'SC Change Orders'!$C$2:$C$501,"<="&Controls!$C$6)) -> 0 | H5: =IF($B5="","",$F5+$G5) -> 0 | I5: =IF($B5="","",SUMIFS(_MainTable!$K$2:$K$2001,_MainTable!$F$2:$F$2001,$B5,_MainTable!$G$2:$G$2001,">="&Controls!$C$5,_MainTable!$G$2:$G$2001,"<="&Controls!$C$6)) -> 20.4 | J5: =IF($B5="","",IFERROR($I5/$H5,0)) -> 0 | K5: =IF($B5="","",$H5-$I5) -> -20.4 | L5: =IF($B5="","",IFERROR(SUMIFS(_MainTable!$K$2:$K$2001,_MainTable!$F$2:$F$2001,$B5,_MainTable!$G$2:$G$2001,">="&Controls!$C$12,_MainTable!$G$2:$G$2001,"<="&EOMONTH(Controls!$C$7,0))/MIN(Controls!$C$9,Controls!$C$10),0)) -> 3.4 | M5: =IF($B5="","",$L5*Controls!$C$11) -> 6.8 | N5: =IF($B5="","",$I5+$M5) -> 27.2 | O5: =IF($B5="","",IFERROR($N5/$H5,0)) -> 0 | P5: =IF($B5="","",$H5-$N5) -> -27.2 | Q5: =IF($B5="","",IF($L5<=0,"n/a",IFERROR($K5/$L5,"n/a"))) -> -6 | R5: =IF($B5="","",IF(AND($H5=0,$I5=0),"⚪ No Activity",IF(AND($H5=0,COUNTIFS('SC Change Orders'!$B$2:$B$501,$B5,'SC Change Orders'!$C$2:$C$501,">="&Controls!$C$5,'SC Change Orders'!$C$2:$C$501,"<="&Controls!$C$6)=0),"⚪ No Funding on File",IF($H5=0,"🔴 Unfunded Spend",IF($I5>=$H5,"🔴 Over Budget",IF($N5>$H5,"🔴 Projected Shortfall",IF($J5>=Controls!$C$8,"🟡 Watch","🟢 On Track"))))))) -> ⚪ No Funding on File
A6: =IF($B6="","",IF((IFERROR(INDEX(_RefTable!$A$2:$A$501,MATCH($B6,_RefTable!$C$2:$C$501,0)),IFERROR(INDEX(_MainTable!$A$2:$A$2001,MATCH($B6,_MainTable!$F$2:$F$2001,0)),IFERROR(INDEX('SC Change Orders'!$A$2:$A$501,MATCH($B6,'SC Change Orders'!$B$2:$B$501,0)),"(unknown vendor)"))))&""="","—",(IFERROR(INDEX(_RefTable!$A$2:$A$501,MATCH($B6,_RefTable!$C$2:$C$501,0)),IFERROR(INDEX(_MainTable!$A$2:$A$2001,MATCH($B6,_MainTable!$F$2:$F$2001,0)),IFERROR(INDEX('SC Change Orders'!$A$2:$A$501,MATCH($B6,'SC Change Orders'!$B$2:$B$501,0)),"(unknown vendor)")))))) -> FMS INC | B6: =IFERROR(INDEX('PO Index'!$B$5:$B$84,2),"") -> 7893 | C6: =IF($B6="","",IF((IFERROR(INDEX(_RefTable!$B$2:$B$501,MATCH($B6,_RefTable!$C$2:$C$501,0))&IF(COUNTIF(_RefTable!$C$2:$C$501,$B6)>1," (+"&COUNTIF(_RefTable!$C$2:$C$501,$B6)-1&" more)",""),IFERROR(INDEX(_MainTable!$B$2:$B$2001,MATCH($B6,_MainTable!$F$2:$F$2001,0)),"")))&""="","—",(IFERROR(INDEX(_RefTable!$B$2:$B$501,MATCH($B6,_RefTable!$C$2:$C$501,0))&IF(COUNTIF(_RefTable!$C$2:$C$501,$B6)>1," (+"&COUNTIF(_RefTable!$C$2:$C$501,$B6)-1&" more)",""),IFERROR(INDEX(_MainTable!$B$2:$B$2001,MATCH($B6,_MainTable!$F$2:$F$2001,0)),""))))) -> Base Recover | D6: =IF($B6="","",IF((IFERROR(INDEX(_RefTable!$E$2:$E$501,MATCH($B6,_RefTable!$C$2:$C$501,0)),IFERROR(INDEX(_MainTable!$C$2:$C$2001,MATCH($B6,_MainTable!$F$2:$F$2001,0)),"")))&""="","—",(IFERROR(INDEX(_RefTable!$E$2:$E$501,MATCH($B6,_RefTable!$C$2:$C$501,0)),IFERROR(INDEX(_MainTable!$C$2:$C$2001,MATCH($B6,_MainTable!$F$2:$F$2001,0)),""))))) -> Jake Reid | E6: =IF($B6="","",IF((IFERROR(INDEX(_RefTable!$F$2:$F$501,MATCH($B6,_RefTable!$C$2:$C$501,0)),IFERROR(INDEX(_MainTable!$D$2:$D$2001,MATCH($B6,_MainTable!$F$2:$F$2001,0)),"")))&""="","—",(IFERROR(INDEX(_RefTable!$F$2:$F$501,MATCH($B6,_RefTable!$C$2:$C$501,0)),IFERROR(INDEX(_MainTable!$D$2:$D$2001,MATCH($B6,_MainTable!$F$2:$F$2001,0)),""))))) -> Letisia Speelman | F6: =IF($B6="","",IFERROR(_xlfn.MINIFS('SC Change Orders'!$E$2:$E$501,'SC Change Orders'!$B$2:$B$501,$B6,'SC Change Orders'!$C$2:$C$501,">="&Controls!$C$5,'SC Change Orders'!$C$2:$C$501,"<="&Controls!$C$6),0)) -> 0 | G6: =IF($B6="","",SUMIFS('SC Change Orders'!$F$2:$F$501,'SC Change Orders'!$B$2:$B$501,$B6,'SC Change Orders'!$C$2:$C$501,">="&Controls!$C$5,'SC Change Orders'!$C$2:$C$501,"<="&Controls!$C$6)) -> 0 | H6: =IF($B6="","",$F6+$G6) -> 0 | I6: =IF($B6="","",SUMIFS(_MainTable!$K$2:$K$2001,_MainTable!$F$2:$F$2001,$B6,_MainTable!$G$2:$G$2001,">="&Controls!$C$5,_MainTable!$G$2:$G$2001,"<="&Controls!$C$6)) -> 219.85 | J6: =IF($B6="","",IFERROR($I6/$H6,0)) -> 0 | K6: =IF($B6="","",$H6-$I6) -> -219.85 | L6: =IF($B6="","",IFERROR(SUMIFS(_MainTable!$K$2:$K$2001,_MainTable!$F$2:$F$2001,$B6,_MainTable!$G$2:$G$2001,">="&Controls!$C$12,_MainTable!$G$2:$G$2001,"<="&EOMONTH(Controls!$C$7,0))/MIN(Controls!$C$9,Controls!$C$10),0)) -> 29.546667 | M6: =IF($B6="","",$L6*Controls!$C$11) -> 59.093333 | N6: =IF($B6="","",$I6+$M6) -> 278.94333 | O6: =IF($B6="","",IFERROR($N6/$H6,0)) -> 0 | P6: =IF($B6="","",$H6-$N6) -> -278.94333 | Q6: =IF($B6="","",IF($L6<=0,"n/a",IFERROR($K6/$L6,"n/a"))) -> -7.4407717 | R6: =IF($B6="","",IF(AND($H6=0,$I6=0),"⚪ No Activity",IF(AND($H6=0,COUNTIFS('SC Change Orders'!$B$2:$B$501,$B6,'SC Change Orders'!$C$2:$C$501,">="&Controls!$C$5,'SC Change Orders'!$C$2:$C$501,"<="&Controls!$C$6)=0),"⚪ No Funding on File",IF($H6=0,"🔴 Unfunded Spend",IF($I6>=$H6,"🔴 Over Budget",IF($N6>$H6,"🔴 Projected Shortfall",IF($J6>=Controls!$C$8,"🟡 Watch","🟢 On Track"))))))) -> ⚪ No Funding on File
A7: =IF($B7="","",IF((IFERROR(INDEX(_RefTable!$A$2:$A$501,MATCH($B7,_RefTable!$C$2:$C$501,0)),IFERROR(INDEX(_MainTable!$A$2:$A$2001,MATCH($B7,_MainTable!$F$2:$F$2001,0)),IFERROR(INDEX('SC Change Orders'!$A$2:$A$501,MATCH($B7,'SC Change Orders'!$B$2:$B$501,0)),"(unknown vendor)"))))&""="","—",(IFERROR(INDEX(_RefTable!$A$2:$A$501,MATCH($B7,_RefTable!$C$2:$C$501,0)),IFERROR(INDEX(_MainTable!$A$2:$A$2001,MATCH($B7,_MainTable!$F$2:$F$2001,0)),IFERROR(INDEX('SC Change Orders'!$A$2:$A$501,MATCH($B7,'SC Change Orders'!$B$2:$B$501,0)),"(unknown vendor)")))))) -> FMS INC | B7: =IFERROR(INDEX('PO Index'!$B$5:$B$84,3),"") -> 7894 | C7: =IF($B7="","",IF((IFERROR(INDEX(_RefTable!$B$2:$B$501,MATCH($B7,_RefTable!$C$2:$C$501,0))&IF(COUNTIF(_RefTable!$C$2:$C$501,$B7)>1," (+"&COUNTIF(_RefTable!$C$2:$C$501,$B7)-1&" more)",""),IFERROR(INDEX(_MainTable!$B$2:$B$2001,MATCH($B7,_MainTable!$F$2:$F$2001,0)),"")))&""="","—",(IFERROR(INDEX(_RefTable!$B$2:$B$501,MATCH($B7,_RefTable!$C$2:$C$501,0))&IF(COUNTIF(_RefTable!$C$2:$C$501,$B7)>1," (+"&COUNTIF(_RefTable!$C$2:$C$501,$B7)-1&" more)",""),IFERROR(INDEX(_MainTable!$B$2:$B$2001,MATCH($B7,_MainTable!$F$2:$F$2001,0)),""))))) -> Skim Overflow | D7: =IF($B7="","",IF((IFERROR(INDEX(_RefTable!$E$2:$E$501,MATCH($B7,_RefTable!$C$2:$C$501,0)),IFERROR(INDEX(_MainTable!$C$2:$C$2001,MATCH($B7,_MainTable!$F$2:$F$2001,0)),"")))&""="","—",(IFERROR(INDEX(_RefTable!$E$2:$E$501,MATCH($B7,_RefTable!$C$2:$C$501,0)),IFERROR(INDEX(_MainTable!$C$2:$C$2001,MATCH($B7,_MainTable!$F$2:$F$2001,0)),""))))) -> Jake Reid | E7: =IF($B7="","",IF((IFERROR(INDEX(_RefTable!$F$2:$F$501,MATCH($B7,_RefTable!$C$2:$C$501,0)),IFERROR(INDEX(_MainTable!$D$2:$D$2001,MATCH($B7,_MainTable!$F$2:$F$2001,0)),"")))&""="","—",(IFERROR(INDEX(_RefTable!$F$2:$F$501,MATCH($B7,_RefTable!$C$2:$C$501,0)),IFERROR(INDEX(_MainTable!$D$2:$D$2001,MATCH($B7,_MainTable!$F$2:$F$2001,0)),""))))) -> Letisia Speelman | F7: =IF($B7="","",IFERROR(_xlfn.MINIFS('SC Change Orders'!$E$2:$E$501,'SC Change Orders'!$B$2:$B$501,$B7,'SC Change Orders'!$C$2:$C$501,">="&Controls!$C$5,'SC Change Orders'!$C$2:$C$501,"<="&Controls!$C$6),0)) -> 0 | G7: =IF($B7="","",SUMIFS('SC Change Orders'!$F$2:$F$501,'SC Change Orders'!$B$2:$B$501,$B7,'SC Change Orders'!$C$2:$C$501,">="&Controls!$C$5,'SC Change Orders'!$C$2:$C$501,"<="&Controls!$C$6)) -> 0 | H7: =IF($B7="","",$F7+$G7) -> 0 | I7: =IF($B7="","",SUMIFS(_MainTable!$K$2:$K$2001,_MainTable!$F$2:$F$2001,$B7,_MainTable!$G$2:$G$2001,">="&Controls!$C$5,_MainTable!$G$2:$G$2001,"<="&Controls!$C$6)) -> 50650.61 | J7: =IF($B7="","",IFERROR($I7/$H7,0)) -> 0 | K7: =IF($B7="","",$H7-$I7) -> -50650.61 | L7: =IF($B7="","",IFERROR(SUMIFS(_MainTable!$K$2:$K$2001,_MainTable!$F$2:$F$2001,$B7,_MainTable!$G$2:$G$2001,">="&Controls!$C$12,_MainTable!$G$2:$G$2001,"<="&EOMONTH(Controls!$C$7,0))/MIN(Controls!$C$9,Controls!$C$10),0)) -> 9042.36 | M7: =IF($B7="","",$L7*Controls!$C$11) -> 18084.72 | N7: =IF($B7="","",$I7+$M7) -> 68735.33 | O7: =IF($B7="","",IFERROR($N7/$H7,0)) -> 0 | P7: =IF($B7="","",$H7-$N7) -> -68735.33 | Q7: =IF($B7="","",IF($L7<=0,"n/a",IFERROR($K7/$L7,"n/a"))) -> -5.6014813 | R7: =IF($B7="","",IF(AND($H7=0,$I7=0),"⚪ No Activity",IF(AND($H7=0,COUNTIFS('SC Change Orders'!$B$2:$B$501,$B7,'SC Change Orders'!$C$2:$C$501,">="&Controls!$C$5,'SC Change Orders'!$C$2:$C$501,"<="&Controls!$C$6)=0),"⚪ No Funding on File",IF($H7=0,"🔴 Unfunded Spend",IF($I7>=$H7,"🔴 Over Budget",IF($N7>$H7,"🔴 Projected Shortfall",IF($J7>=Controls!$C$8,"🟡 Watch","🟢 On Track"))))))) -> ⚪ No Funding on File
A8: =IF($B8="","",IF((IFERROR(INDEX(_RefTable!$A$2:$A$501,MATCH($B8,_RefTable!$C$2:$C$501,0)),IFERROR(INDEX(_MainTable!$A$2:$A$2001,MATCH($B8,_MainTable!$F$2:$F$2001,0)),IFERROR(INDEX('SC Change Orders'!$A$2:$A$501,MATCH($B8,'SC Change Orders'!$B$2:$B$501,0)),"(unknown vendor)"))))&""="","—",(IFERROR(INDEX(_RefTable!$A$2:$A$501,MATCH($B8,_RefTable!$C$2:$C$501,0)),IFERROR(INDEX(_MainTable!$A$2:$A$2001,MATCH($B8,_MainTable!$F$2:$F$2001,0)),IFERROR(INDEX('SC Change Orders'!$A$2:$A$501,MATCH($B8,'SC Change Orders'!$B$2:$B$501,0)),"(unknown vendor)")))))) -> FMS INC | B8: =IFERROR(INDEX('PO Index'!$B$5:$B$84,4),"") -> 7896 | C8: =IF($B8="","",IF((IFERROR(INDEX(_RefTable!$B$2:$B$501,MATCH($B8,_RefTable!$C$2:$C$501,0))&IF(COUNTIF(_RefTable!$C$2:$C$501,$B8)>1," (+"&COUNTIF(_RefTable!$C$2:$C$501,$B8)-1&" more)",""),IFERROR(INDEX(_MainTable!$B$2:$B$2001,MATCH($B8,_MainTable!$F$2:$F$2001,0)),"")))&""="","—",(IFERROR(INDEX(_RefTable!$B$2:$B$501,MATCH($B8,_RefTable!$C$2:$C$501,0))&IF(COUNTIF(_RefTable!$C$2:$C$501,$B8)>1," (+"&COUNTIF(_RefTable!$C$2:$C$501,$B8)-1&" more)",""),IFERROR(INDEX(_MainTable!$B$2:$B$2001,MATCH($B8,_MainTable!$F$2:$F$2001,0)),""))))) -> MV EBO | D8: =IF($B8="","",IF((IFERROR(INDEX(_RefTable!$E$2:$E$501,MATCH($B8,_RefTable!$C$2:$C$501,0)),IFERROR(INDEX(_MainTable!$C$2:$C$2001,MATCH($B8,_MainTable!$F$2:$F$2001,0)),"")))&""="","—",(IFERROR(INDEX(_RefTable!$E$2:$E$501,MATCH($B8,_RefTable!$C$2:$C$501,0)),IFERROR(INDEX(_MainTable!$C$2:$C$2001,MATCH($B8,_MainTable!$F$2:$F$2001,0)),""))))) -> Jake Reid | E8: =IF($B8="","",IF((IFERROR(INDEX(_RefTable!$F$2:$F$501,MATCH($B8,_RefTable!$C$2:$C$501,0)),IFERROR(INDEX(_MainTable!$D$2:$D$2001,MATCH($B8,_MainTable!$F$2:$F$2001,0)),"")))&""="","—",(IFERROR(INDEX(_RefTable!$F$2:$F$501,MATCH($B8,_RefTable!$C$2:$C$501,0)),IFERROR(INDEX(_MainTable!$D$2:$D$2001,MATCH($B8,_MainTable!$F$2:$F$2001,0)),""))))) -> Letisia Speelman | F8: =IF($B8="","",IFERROR(_xlfn.MINIFS('SC Change Orders'!$E$2:$E$501,'SC Change Orders'!$B$2:$B$501,$B8,'SC Change Orders'!$C$2:$C$501,">="&Controls!$C$5,'SC Change Orders'!$C$2:$C$501,"<="&Controls!$C$6),0)) -> 0 | G8: =IF($B8="","",SUMIFS('SC Change Orders'!$F$2:$F$501,'SC Change Orders'!$B$2:$B$501,$B8,'SC Change Orders'!$C$2:$C$501,">="&Controls!$C$5,'SC Change Orders'!$C$2:$C$501,"<="&Controls!$C$6)) -> 0 | H8: =IF($B8="","",$F8+$G8) -> 0 | I8: =IF($B8="","",SUMIFS(_MainTable!$K$2:$K$2001,_MainTable!$F$2:$F$2001,$B8,_MainTable!$G$2:$G$2001,">="&Controls!$C$5,_MainTable!$G$2:$G$2001,"<="&Controls!$C$6)) -> 462.43 | J8: =IF($B8="","",IFERROR($I8/$H8,0)) -> 0 | K8: =IF($B8="","",$H8-$I8) -> -462.43 | L8: =IF($B8="","",IFERROR(SUMIFS(_MainTable!$K$2:$K$2001,_MainTable!$F$2:$F$2001,$B8,_MainTable!$G$2:$G$2001,">="&Controls!$C$12,_MainTable!$G$2:$G$2001,"<="&EOMONTH(Controls!$C$7,0))/MIN(Controls!$C$9,Controls!$C$10),0)) -> 89.68 | M8: =IF($B8="","",$L8*Controls!$C$11) -> 179.36 | N8: =IF($B8="","",$I8+$M8) -> 641.79 | O8: =IF($B8="","",IFERROR($N8/$H8,0)) -> 0 | P8: =IF($B8="","",$H8-$N8) -> -641.79 | Q8: =IF($B8="","",IF($L8<=0,"n/a",IFERROR($K8/$L8,"n/a"))) -> -5.1564451 | R8: =IF($B8="","",IF(AND($H8=0,$I8=0),"⚪ No Activity",IF(AND($H8=0,COUNTIFS('SC Change Orders'!$B$2:$B$501,$B8,'SC Change Orders'!$C$2:$C$501,">="&Controls!$C$5,'SC Change Orders'!$C$2:$C$501,"<="&Controls!$C$6)=0),"⚪ No Funding on File",IF($H8=0,"🔴 Unfunded Spend",IF($I8>=$H8,"🔴 Over Budget",IF($N8>$H8,"🔴 Projected Shortfall",IF($J8>=Controls!$C$8,"🟡 Watch","🟢 On Track"))))))) -> ⚪ No Funding on File
A9: =IF($B9="","",IF((IFERROR(INDEX(_RefTable!$A$2:$A$501,MATCH($B9,_RefTable!$C$2:$C$501,0)),IFERROR(INDEX(_MainTable!$A$2:$A$2001,MATCH($B9,_MainTable!$F$2:$F$2001,0)),IFERROR(INDEX('SC Change Orders'!$A$2:$A$501,MATCH($B9,'SC Change Orders'!$B$2:$B$501,0)),"(unknown vendor)"))))&""="","—",(IFERROR(INDEX(_RefTable!$A$2:$A$501,MATCH($B9,_RefTable!$C$2:$C$501,0)),IFERROR(INDEX(_MainTable!$A$2:$A$2001,MATCH($B9,_MainTable!$F$2:$F$2001,0)),IFERROR(INDEX('SC Change Orders'!$A$2:$A$501,MATCH($B9,'SC Change Orders'!$B$2:$B$501,0)),"(unknown vendor)")))))) -> FORTE LLC | B9: =IFERROR(INDEX('PO Index'!$B$5:$B$84,5),"") -> 7910 | C9: =IF($B9="","",IF((IFERROR(INDEX(_RefTable!$B$2:$B$501,MATCH($B9,_RefTable!$C$2:$C$501,0))&IF(COUNTIF(_RefTable!$C$2:$C$501,$B9)>1," (+"&COUNTIF(_RefTable!$C$2:$C$501,$B9)-1&" more)",""),IFERROR(INDEX(_MainTable!$B$2:$B$2001,MATCH($B9,_MainTable!$F$2:$F$2001,0)),"")))&""="","—",(IFERROR(INDEX(_RefTable!$B$2:$B$501,MATCH($B9,_RefTable!$C$2:$C$501,0))&IF(COUNTIF(_RefTable!$C$2:$C$501,$B9)>1," (+"&COUNTIF(_RefTable!$C$2:$C$501,$B9)-1&" more)",""),IFERROR(INDEX(_MainTable!$B$2:$B$2001,MATCH($B9,_MainTable!$F$2:$F$2001,0)),""))))) -> Probate Finder | D9: =IF($B9="","",IF((IFERROR(INDEX(_RefTable!$E$2:$E$501,MATCH($B9,_RefTable!$C$2:$C$501,0)),IFERROR(INDEX(_MainTable!$C$2:$C$2001,MATCH($B9,_MainTable!$F$2:$F$2001,0)),"")))&""="","—",(IFERROR(INDEX(_RefTable!$E$2:$E$501,MATCH($B9,_RefTable!$C$2:$C$501,0)),IFERROR(INDEX(_MainTable!$C$2:$C$2001,MATCH($B9,_MainTable!$F$2:$F$2001,0)),""))))) -> Jake Reid | E9: =IF($B9="","",IF((IFERROR(INDEX(_RefTable!$F$2:$F$501,MATCH($B9,_RefTable!$C$2:$C$501,0)),IFERROR(INDEX(_MainTable!$D$2:$D$2001,MATCH($B9,_MainTable!$F$2:$F$2001,0)),"")))&""="","—",(IFERROR(INDEX(_RefTable!$F$2:$F$501,MATCH($B9,_RefTable!$C$2:$C$501,0)),IFERROR(INDEX(_MainTable!$D$2:$D$2001,MATCH($B9,_MainTable!$F$2:$F$2001,0)),""))))) -> Letisia Speelman | F9: =IF($B9="","",IFERROR(_xlfn.MINIFS('SC Change Orders'!$E$2:$E$501,'SC Change Orders'!$B$2:$B$501,$B9,'SC Change Orders'!$C$2:$C$501,">="&Controls!$C$5,'SC Change Orders'!$C$2:$C$501,"<="&Controls!$C$6),0)) -> 0 | G9: =IF($B9="","",SUMIFS('SC Change Orders'!$F$2:$F$501,'SC Change Orders'!$B$2:$B$501,$B9,'SC Change Orders'!$C$2:$C$501,">="&Controls!$C$5,'SC Change Orders'!$C$2:$C$501,"<="&Controls!$C$6)) -> 0 | H9: =IF($B9="","",$F9+$G9) -> 0 | I9: =IF($B9="","",SUMIFS(_MainTable!$K$2:$K$2001,_MainTable!$F$2:$F$2001,$B9,_MainTable!$G$2:$G$2001,">="&Controls!$C$5,_MainTable!$G$2:$G$2001,"<="&Controls!$C$6)) -> 18414.44 | J9: =IF($B9="","",IFERROR($I9/$H9,0)) -> 0 | K9: =IF($B9="","",$H9-$I9) -> -18414.44 | L9: =IF($B9="","",IFERROR(SUMIFS(_MainTable!$K$2:$K$2001,_MainTable!$F$2:$F$2001,$B9,_MainTable!$G$2:$G$2001,">="&Controls!$C$12,_MainTable!$G$2:$G$2001,"<="&EOMONTH(Controls!$C$7,0))/MIN(Controls!$C$9,Controls!$C$10),0)) -> 2274.2833 | M9: =IF($B9="","",$L9*Controls!$C$11) -> 4548.5667 | N9: =IF($B9="","",$I9+$M9) -> 22963.007 | O9: =IF($B9="","",IFERROR($N9/$H9,0)) -> 0 | P9: =IF($B9="","",$H9-$N9) -> -22963.007 | Q9: =IF($B9="","",IF($L9<=0,"n/a",IFERROR($K9/$L9,"n/a"))) -> -8.09681 | R9: =IF($B9="","",IF(AND($H9=0,$I9=0),"⚪ No Activity",IF(AND($H9=0,COUNTIFS('SC Change Orders'!$B$2:$B$501,$B9,'SC Change Orders'!$C$2:$C$501,">="&Controls!$C$5,'SC Change Orders'!$C$2:$C$501,"<="&Controls!$C$6)=0),"⚪ No Funding on File",IF($H9=0,"🔴 Unfunded Spend",IF($I9>=$H9,"🔴 Over Budget",IF($N9>$H9,"🔴 Projected Shortfall",IF($J9>=Controls!$C$8,"🟡 Watch","🟢 On Track"))))))) -> ⚪ No Funding on File
A10: =IF($B10="","",IF((IFERROR(INDEX(_RefTable!$A$2:$A$501,MATCH($B10,_RefTable!$C$2:$C$501,0)),IFERROR(INDEX(_MainTable!$A$2:$A$2001,MATCH($B10,_MainTable!$F$2:$F$2001,0)),IFERROR(INDEX('SC Change Orders'!$A$2:$A$501,MATCH($B10,'SC Change Orders'!$B$2:$B$501,0)),"(unknown vendor)"))))&""="","—",(IFERROR(INDEX(_RefTable!$A$2:$A$501,MATCH($B10,_RefTable!$C$2:$C$501,0)),IFERROR(INDEX(_MainTable!$A$2:$A$2001,MATCH($B10,_MainTable!$F$2:$F$2001,0)),IFERROR(INDEX('SC Change Orders'!$A$2:$A$501,MATCH($B10,'SC Change Orders'!$B$2:$B$501,0)),"(unknown vendor)")))))) -> HAWLEY TROXELL ENNIS HAWLEY | B10: =IFERROR(INDEX('PO Index'!$B$5:$B$84,6),"") -> 7911 | C10: =IF($B10="","",IF((IFERROR(INDEX(_RefTable!$B$2:$B$501,MATCH($B10,_RefTable!$C$2:$C$501,0))&IF(COUNTIF(_RefTable!$C$2:$C$501,$B10)>1," (+"&COUNTIF(_RefTable!$C$2:$C$501,$B10)-1&" more)",""),IFERROR(INDEX(_MainTable!$B$2:$B$2001,MATCH($B10,_MainTable!$F$2:$F$2001,0)),"")))&""="","—",(IFERROR(INDEX(_RefTable!$B$2:$B$501,MATCH($B10,_RefTable!$C$2:$C$501,0))&IF(COUNTIF(_RefTable!$C$2:$C$501,$B10)>1," (+"&COUNTIF(_RefTable!$C$2:$C$501,$B10)-1&" more)",""),IFERROR(INDEX(_MainTable!$B$2:$B$2001,MATCH($B10,_MainTable!$F$2:$F$2001,0)),""))))) -> Estate/Probate (+1 more) | D10: =IF($B10="","",IF((IFERROR(INDEX(_RefTable!$E$2:$E$501,MATCH($B10,_RefTable!$C$2:$C$501,0)),IFERROR(INDEX(_MainTable!$C$2:$C$2001,MATCH($B10,_MainTable!$F$2:$F$2001,0)),"")))&""="","—",(IFERROR(INDEX(_RefTable!$E$2:$E$501,MATCH($B10,_RefTable!$C$2:$C$501,0)),IFERROR(INDEX(_MainTable!$C$2:$C$2001,MATCH($B10,_MainTable!$F$2:$F$2001,0)),""))))) -> Jake Reid | E10: =IF($B10="","",IF((IFERROR(INDEX(_RefTable!$F$2:$F$501,MATCH($B10,_RefTable!$C$2:$C$501,0)),IFERROR(INDEX(_MainTable!$D$2:$D$2001,MATCH($B10,_MainTable!$F$2:$F$2001,0)),"")))&""="","—",(IFERROR(INDEX(_RefTable!$F$2:$F$501,MATCH($B10,_RefTable!$C$2:$C$501,0)),IFERROR(INDEX(_MainTable!$D$2:$D$2001,MATCH($B10,_MainTable!$F$2:$F$2001,0)),""))))) -> Letisia Speelman | F10: =IF($B10="","",IFERROR(_xlfn.MINIFS('SC Change Orders'!$E$2:$E$501,'SC Change Orders'!$B$2:$B$501,$B10,'SC Change Orders'!$C$2:$C$501,">="&Controls!$C$5,'SC Change Orders'!$C$2:$C$501,"<="&Controls!$C$6),0)) -> 0 | G10: =IF($B10="","",SUMIFS('SC Change Orders'!$F$2:$F$501,'SC Change Orders'!$B$2:$B$501,$B10,'SC Change Orders'!$C$2:$C$501,">="&Controls!$C$5,'SC Change Orders'!$C$2:$C$501,"<="&Controls!$C$6)) -> 0 | H10: =IF($B10="","",$F10+$G10) -> 0 | I10: =IF($B10="","",SUMIFS(_MainTable!$K$2:$K$2001,_MainTable!$F$2:$F$2001,$B10,_MainTable!$G$2:$G$2001,">="&Controls!$C$5,_MainTable!$G$2:$G$2001,"<="&Controls!$C$6)) -> 7945.44 | J10: =IF($B10="","",IFERROR($I10/$H10,0)) -> 0 | K10: =IF($B10="","",$H10-$I10) -> -7945.44 | L10: =IF($B10="","",IFERROR(SUMIFS(_MainTable!$K$2:$K$2001,_MainTable!$F$2:$F$2001,$B10,_MainTable!$G$2:$G$2001,">="&Controls!$C$12,_MainTable!$G$2:$G$2001,"<="&EOMONTH(Controls!$C$7,0))/MIN(Controls!$C$9,Controls!$C$10),0)) -> 2466.1667 | M10: =IF($B10="","",$L10*Controls!$C$11) -> 4932.3333 | N10: =IF($B10="","",$I10+$M10) -> 12877.773 | O10: =IF($B10="","",IFERROR($N10/$H10,0)) -> 0 | P10: =IF($B10="","",$H10-$N10) -> -12877.773 | Q10: =IF($B10="","",IF($L10<=0,"n/a",IFERROR($K10/$L10,"n/a"))) -> -3.2217774 | R10: =IF($B10="","",IF(AND($H10=0,$I10=0),"⚪ No Activity",IF(AND($H10=0,COUNTIFS('SC Change Orders'!$B$2:$B$501,$B10,'SC Change Orders'!$C$2:$C$501,">="&Controls!$C$5,'SC Change Orders'!$C$2:$C$501,"<="&Controls!$C$6)=0),"⚪ No Funding on File",IF($H10=0,"🔴 Unfunded Spend",IF($I10>=$H10,"🔴 Over Budget",IF($N10>$H10,"🔴 Projected Shortfall",IF($J10>=Controls!$C$8,"🟡 Watch","🟢 On Track"))))))) -> ⚪ No Funding on File
A11: =IF($B11="","",IF((IFERROR(INDEX(_RefTable!$A$2:$A$501,MATCH($B11,_RefTable!$C$2:$C$501,0)),IFERROR(INDEX(_MainTable!$A$2:$A$2001,MATCH($B11,_MainTable!$F$2:$F$2001,0)),IFERROR(INDEX('SC Change Orders'!$A$2:$A$501,MATCH($B11,'SC Change Orders'!$B$2:$B$501,0)),"(unknown vendor)"))))&""="","—",(IFERROR(INDEX(_RefTable!$A$2:$A$501,MATCH($B11,_RefTable!$C$2:$C$501,0)),IFERROR(INDEX(_MainTable!$A$2:$A$2001,MATCH($B11,_MainTable!$F$2:$F$2001,0)),IFERROR(INDEX('SC Change Orders'!$A$2:$A$501,MATCH($B11,'SC Change Orders'!$B$2:$B$501,0)),"(unknown vendor)")))))) -> ETYON | B11: =IFERROR(INDEX('PO Index'!$B$5:$B$84,7),"") -> 7927 | C11: =IF($B11="","",IF((IFERROR(INDEX(_RefTable!$B$2:$B$501,MATCH($B11,_RefTable!$C$2:$C$501,0))&IF(COUNTIF(_RefTable!$C$2:$C$501,$B11)>1," (+"&COUNTIF(_RefTable!$C$2:$C$501,$B11)-1&" more)",""),IFERROR(INDEX(_MainTable!$B$2:$B$2001,MATCH($B11,_MainTable!$F$2:$F$2001,0)),"")))&""="","—",(IFERROR(INDEX(_RefTable!$B$2:$B$501,MATCH($B11,_RefTable!$C$2:$C$501,0))&IF(COUNTIF(_RefTable!$C$2:$C$501,$B11)>1," (+"&COUNTIF(_RefTable!$C$2:$C$501,$B11)-1&" more)",""),IFERROR(INDEX(_MainTable!$B$2:$B$2001,MATCH($B11,_MainTable!$F$2:$F$2001,0)),""))))) -> Analytics | D11: =IF($B11="","",IF((IFERROR(INDEX(_RefTable!$E$2:$E$501,MATCH($B11,_RefTable!$C$2:$C$501,0)),IFERROR(INDEX(_MainTable!$C$2:$C$2001,MATCH($B11,_MainTable!$F$2:$F$2001,0)),"")))&""="","—",(IFERROR(INDEX(_RefTable!$E$2:$E$501,MATCH($B11,_RefTable!$C$2:$C$501,0)),IFERROR(INDEX(_MainTable!$C$2:$C$2001,MATCH($B11,_MainTable!$F$2:$F$2001,0)),""))))) -> Matt Morishita | E11: =IF($B11="","",IF((IFERROR(INDEX(_RefTable!$F$2:$F$501,MATCH($B11,_RefTable!$C$2:$C$501,0)),IFERROR(INDEX(_MainTable!$D$2:$D$2001,MATCH($B11,_MainTable!$F$2:$F$2001,0)),"")))&""="","—",(IFERROR(INDEX(_RefTable!$F$2:$F$501,MATCH($B11,_RefTable!$C$2:$C$501,0)),IFERROR(INDEX(_MainTable!$D$2:$D$2001,MATCH($B11,_MainTable!$F$2:$F$2001,0)),""))))) -> Amanda Leroue | F11: =IF($B11="","",IFERROR(_xlfn.MINIFS('SC Change Orders'!$E$2:$E$501,'SC Change Orders'!$B$2:$B$501,$B11,'SC Change Orders'!$C$2:$C$501,">="&Controls!$C$5,'SC Change Orders'!$C$2:$C$501,"<="&Controls!$C$6),0)) -> 0 | G11: =IF($B11="","",SUMIFS('SC Change Orders'!$F$2:$F$501,'SC Change Orders'!$B$2:$B$501,$B11,'SC Change Orders'!$C$2:$C$501,">="&Controls!$C$5,'SC Change Orders'!$C$2:$C$501,"<="&Controls!$C$6)) -> 0 | H11: =IF($B11="","",$F11+$G11) -> 0 | I11: =IF($B11="","",SUMIFS(_MainTable!$K$2:$K$2001,_MainTable!$F$2:$F$2001,$B11,_MainTable!$G$2:$G$2001,">="&Controls!$C$5,_MainTable!$G$2:$G$2001,"<="&Controls!$C$6)) -> 39026 | J11: =IF($B11="","",IFERROR($I11/$H11,0)) -> 0 | K11: =IF($B11="","",$H11-$I11) -> -39026 | L11: =IF($B11="","",IFERROR(SUMIFS(_MainTable!$K$2:$K$2001,_MainTable!$F$2:$F$2001,$B11,_MainTable!$G$2:$G$2001,">="&Controls!$C$12,_MainTable!$G$2:$G$2001,"<="&EOMONTH(Controls!$C$7,0))/MIN(Controls!$C$9,Controls!$C$10),0)) -> 9756.5 | M11: =IF($B11="","",$L11*Controls!$C$11) -> 19513 | N11: =IF($B11="","",$I11+$M11) -> 58539 | O11: =IF($B11="","",IFERROR($N11/$H11,0)) -> 0 | P11: =IF($B11="","",$H11-$N11) -> -58539 | Q11: =IF($B11="","",IF($L11<=0,"n/a",IFERROR($K11/$L11,"n/a"))) -> -4 | R11: =IF($B11="","",IF(AND($H11=0,$I11=0),"⚪ No Activity",IF(AND($H11=0,COUNTIFS('SC Change Orders'!$B$2:$B$501,$B11,'SC Change Orders'!$C$2:$C$501,">="&Controls!$C$5,'SC Change Orders'!$C$2:$C$501,"<="&Controls!$C$6)=0),"⚪ No Funding on File",IF($H11=0,"🔴 Unfunded Spend",IF($I11>=$H11,"🔴 Over Budget",IF($N11>$H11,"🔴 Projected Shortfall",IF($J11>=Controls!$C$8,"🟡 Watch","🟢 On Track"))))))) -> ⚪ No Funding on File
A12: =IF($B12="","",IF((IFERROR(INDEX(_RefTable!$A$2:$A$501,MATCH($B12,_RefTable!$C$2:$C$501,0)),IFERROR(INDEX(_MainTable!$A$2:$A$2001,MATCH($B12,_MainTable!$F$2:$F$2001,0)),IFERROR(INDEX('SC Change Orders'!$A$2:$A$501,MATCH($B12,'SC Change Orders'!$B$2:$B$501,0)),"(unknown vendor)"))))&""="","—",(IFERROR(INDEX(_RefTable!$A$2:$A$501,MATCH($B12,_RefTable!$C$2:$C$501,0)),IFERROR(INDEX(_MainTable!$A$2:$A$2001,MATCH($B12,_MainTable!$F$2:$F$2001,0)),IFERROR(INDEX('SC Change Orders'!$A$2:$A$501,MATCH($B12,'SC Change Orders'!$B$2:$B$501,0)),"(unknown vendor)")))))) -> HEALTHFUSE LLC | B12: =IFERROR(INDEX('PO Index'!$B$5:$B$84,8),"") -> 8438 | C12: =IF($B12="","",IF((IFERROR(INDEX(_RefTable!$B$2:$B$501,MATCH($B12,_RefTable!$C$2:$C$501,0))&IF(COUNTIF(_RefTable!$C$2:$C$501,$B12)>1," (+"&COUNTIF(_RefTable!$C$2:$C$501,$B12)-1&" more)",""),IFERROR(INDEX(_MainTable!$B$2:$B$2001,MATCH($B12,_MainTable!$F$2:$F$2001,0)),"")))&""="","—",(IFERROR(INDEX(_RefTable!$B$2:$B$501,MATCH($B12,_RefTable!$C$2:$C$501,0))&IF(COUNTIF(_RefTable!$C$2:$C$501,$B12)>1," (+"&COUNTIF(_RefTable!$C$2:$C$501,$B12)-1&" more)",""),IFERROR(INDEX(_MainTable!$B$2:$B$2001,MATCH($B12,_MainTable!$F$2:$F$2001,0)),""))))) -> Consultation | D12: =IF($B12="","",IF((IFERROR(INDEX(_RefTable!$E$2:$E$501,MATCH($B12,_RefTable!$C$2:$C$501,0)),IFERROR(INDEX(_MainTable!$C$2:$C$2001,MATCH($B12,_MainTable!$F$2:$F$2001,0)),"")))&""="","—",(IFERROR(INDEX(_RefTable!$E$2:$E$501,MATCH($B12,_RefTable!$C$2:$C$501,0)),IFERROR(INDEX(_MainTable!$C$2:$C$2001,MATCH($B12,_MainTable!$F$2:$F$2001,0)),""))))) -> Adam Vardaman | E12: =IF($B12="","",IF((IFERROR(INDEX(_RefTable!$F$2:$F$501,MATCH($B12,_RefTable!$C$2:$C$501,0)),IFERROR(INDEX(_MainTable!$D$2:$D$2001,MATCH($B12,_MainTable!$F$2:$F$2001,0)),"")))&""="","—",(IFERROR(INDEX(_RefTable!$F$2:$F$501,MATCH($B12,_RefTable!$C$2:$C$501,0)),IFERROR(INDEX(_MainTable!$D$2:$D$2001,MATCH($B12,_MainTable!$F$2:$F$2001,0)),""))))) -> — | F12: =IF($B12="","",IFERROR(_xlfn.MINIFS('SC Change Orders'!$E$2:$E$501,'SC Change Orders'!$B$2:$B$501,$B12,'SC Change Orders'!$C$2:$C$501,">="&Controls!$C$5,'SC Change Orders'!$C$2:$C$501,"<="&Controls!$C$6),0)) -> 0 | G12: =IF($B12="","",SUMIFS('SC Change Orders'!$F$2:$F$501,'SC Change Orders'!$B$2:$B$501,$B12,'SC Change Orders'!$C$2:$C$501,">="&Controls!$C$5,'SC Change Orders'!$C$2:$C$501,"<="&Controls!$C$6)) -> 0 | H12: =IF($B12="","",$F12+$G12) -> 0 | I12: =IF($B12="","",SUMIFS(_MainTable!$K$2:$K$2001,_MainTable!$F$2:$F$2001,$B12,_MainTable!$G$2:$G$2001,">="&Controls!$C$5,_MainTable!$G$2:$G$2001,"<="&Controls!$C$6)) -> 218875 | J12: =IF($B12="","",IFERROR($I12/$H12,0)) -> 0 | K12: =IF($B12="","",$H12-$I12) -> -218875 | L12: =IF($B12="","",IFERROR(SUMIFS(_MainTable!$K$2:$K$2001,_MainTable!$F$2:$F$2001,$B12,_MainTable!$G$2:$G$2001,">="&Controls!$C$12,_MainTable!$G$2:$G$2001,"<="&EOMONTH(Controls!$C$7,0))/MIN(Controls!$C$9,Controls!$C$10),0)) -> 43775 | M12: =IF($B12="","",$L12*Controls!$C$11) -> 87550 | N12: =IF($B12="","",$I12+$M12) -> 306425 | O12: =IF($B12="","",IFERROR($N12/$H12,0)) -> 0 | P12: =IF($B12="","",$H12-$N12) -> -306425 | Q12: =IF($B12="","",IF($L12<=0,"n/a",IFERROR($K12/$L12,"n/a"))) -> -5 | R12: =IF($B12="","",IF(AND($H12=0,$I12=0),"⚪ No Activity",IF(AND($H12=0,COUNTIFS('SC Change Orders'!$B$2:$B$501,$B12,'SC Change Orders'!$C$2:$C$501,">="&Controls!$C$5,'SC Change Orders'!$C$2:$C$501,"<="&Controls!$C$6)=0),"⚪ No Funding on File",IF($H12=0,"🔴 Unfunded Spend",IF($I12>=$H12,"🔴 Over Budget",IF($N12>$H12,"🔴 Projected Shortfall",IF($J12>=Controls!$C$8,"🟡 Watch","🟢 On Track"))))))) -> ⚪ No Funding on File
A13: =IF($B13="","",IF((IFERROR(INDEX(_RefTable!$A$2:$A$501,MATCH($B13,_RefTable!$C$2:$C$501,0)),IFERROR(INDEX(_MainTable!$A$2:$A$2001,MATCH($B13,_MainTable!$F$2:$F$2001,0)),IFERROR(INDEX('SC Change Orders'!$A$2:$A$501,MATCH($B13,'SC Change Orders'!$B$2:$B$501,0)),"(unknown vendor)"))))&""="","—",(IFERROR(INDEX(_RefTable!$A$2:$A$501,MATCH($B13,_RefTable!$C$2:$C$501,0)),IFERROR(INDEX(_MainTable!$A$2:$A$2001,MATCH($B13,_MainTable!$F$2:$F$2001,0)),IFERROR(INDEX('SC Change Orders'!$A$2:$A$501,MATCH($B13,'SC Change Orders'!$B$2:$B$501,0)),"(unknown vendor)")))))) -> CLOUDMED | B13: =IFERROR(INDEX('PO Index'!$B$5:$B$84,9),"") -> 8658 | C13: =IF($B13="","",IF((IFERROR(INDEX(_RefTable!$B$2:$B$501,MATCH($B13,_RefTable!$C$2:$C$501,0))&IF(COUNTIF(_RefTable!$C$2:$C$501,$B13)>1," (+"&COUNTIF(_RefTable!$C$2:$C$501,$B13)-1&" more)",""),IFERROR(INDEX(_MainTable!$B$2:$B$2001,MATCH($B13,_MainTable!$F$2:$F$2001,0)),"")))&""="","—",(IFERROR(INDEX(_RefTable!$B$2:$B$501,MATCH($B13,_RefTable!$C$2:$C$501,0))&IF(COUNTIF(_RefTable!$C$2:$C$501,$B13)>1," (+"&COUNTIF(_RefTable!$C$2:$C$501,$B13)-1&" more)",""),IFERROR(INDEX(_MainTable!$B$2:$B$2001,MATCH($B13,_MainTable!$F$2:$F$2001,0)),""))))) -> Charge Capture | D13: =IF($B13="","",IF((IFERROR(INDEX(_RefTable!$E$2:$E$501,MATCH($B13,_RefTable!$C$2:$C$501,0)),IFERROR(INDEX(_MainTable!$C$2:$C$2001,MATCH($B13,_MainTable!$F$2:$F$2001,0)),"")))&""="","—",(IFERROR(INDEX(_RefTable!$E$2:$E$501,MATCH($B13,_RefTable!$C$2:$C$501,0)),IFERROR(INDEX(_MainTable!$C$2:$C$2001,MATCH($B13,_MainTable!$F$2:$F$2001,0)),""))))) -> Sona Buchanan | E13: =IF($B13="","",IF((IFERROR(INDEX(_RefTable!$F$2:$F$501,MATCH($B13,_RefTable!$C$2:$C$501,0)),IFERROR(INDEX(_MainTable!$D$2:$D$2001,MATCH($B13,_MainTable!$F$2:$F$2001,0)),"")))&""="","—",(IFERROR(INDEX(_RefTable!$F$2:$F$501,MATCH($B13,_RefTable!$C$2:$C$501,0)),IFERROR(INDEX(_MainTable!$D$2:$D$2001,MATCH($B13,_MainTable!$F$2:$F$2001,0)),""))))) -> Heather Geile | F13: =IF($B13="","",IFERROR(_xlfn.MINIFS('SC Change Orders'!$E$2:$E$501,'SC Change Orders'!$B$2:$B$501,$B13,'SC Change Orders'!$C$2:$C$501,">="&Controls!$C$5,'SC Change Orders'!$C$2:$C$501,"<="&Controls!$C$6),0)) -> 250000 | G13: =IF($B13="","",SUMIFS('SC Change Orders'!$F$2:$F$501,'SC Change Orders'!$B$2:$B$501,$B13,'SC Change Orders'!$C$2:$C$501,">="&Controls!$C$5,'SC Change Orders'!$C$2:$C$501,"<="&Controls!$C$6)) -> 190000 | H13: =IF($B13="","",$F13+$G13) -> 440000 | I13: =IF($B13="","",SUMIFS(_MainTable!$K$2:$K$2001,_MainTable!$F$2:$F$2001,$B13,_MainTable!$G$2:$G$2001,">="&Controls!$C$5,_MainTable!$G$2:$G$2001,"<="&Controls!$C$6)) -> 80970.97 | J13: =IF($B13="","",IFERROR($I13/$H13,0)) -> 0.18402493 | K13: =IF($B13="","",$H13-$I13) -> 359029.03 | L13: =IF($B13="","",IFERROR(SUMIFS(_MainTable!$K$2:$K$2001,_MainTable!$F$2:$F$2001,$B13,_MainTable!$G$2:$G$2001,">="&Controls!$C$12,_MainTable!$G$2:$G$2001,"<="&EOMONTH(Controls!$C$7,0))/MIN(Controls!$C$9,Controls!$C$10),0)) -> 16519.443 | M13: =IF($B13="","",$L13*Controls!$C$11) -> 33038.887 | N13: =IF($B13="","",$I13+$M13) -> 114009.86 | O13: =IF($B13="","",IFERROR($N13/$H13,0)) -> 0.25911331 | P13: =IF($B13="","",$H13-$N13) -> 325990.14 | Q13: =IF($B13="","",IF($L13<=0,"n/a",IFERROR($K13/$L13,"n/a"))) -> 21.733724 | R13: =IF($B13="","",IF(AND($H13=0,$I13=0),"⚪ No Activity",IF(AND($H13=0,COUNTIFS('SC Change Orders'!$B$2:$B$501,$B13,'SC Change Orders'!$C$2:$C$501,">="&Controls!$C$5,'SC Change Orders'!$C$2:$C$501,"<="&Controls!$C$6)=0),"⚪ No Funding on File",IF($H13=0,"🔴 Unfunded Spend",IF($I13>=$H13,"🔴 Over Budget",IF($N13>$H13,"🔴 Projected Shortfall",IF($J13>=Controls!$C$8,"🟡 Watch","🟢 On Track"))))))) -> 🟢 On Track
A14: =IF($B14="","",IF((IFERROR(INDEX(_RefTable!$A$2:$A$501,MATCH($B14,_RefTable!$C$2:$C$501,0)),IFERROR(INDEX(_MainTable!$A$2:$A$2001,MATCH($B14,_MainTable!$F$2:$F$2001,0)),IFERROR(INDEX('SC Change Orders'!$A$2:$A$501,MATCH($B14,'SC Change Orders'!$B$2:$B$501,0)),"(unknown vendor)"))))&""="","—",(IFERROR(INDEX(_RefTable!$A$2:$A$501,MATCH($B14,_RefTable!$C$2:$C$501,0)),IFERROR(INDEX(_MainTable!$A$2:$A$2001,MATCH($B14,_MainTable!$F$2:$F$2001,0)),IFERROR(INDEX('SC Change Orders'!$A$2:$A$501,MATCH($B14,'SC Change Orders'!$B$2:$B$501,0)),"(unknown vendor)")))))) -> CLOUDMED | B14: =IFERROR(INDEX('PO Index'!$B$5:$B$84,10),"") -> 8659 | C14: =IF($B14="","",IF((IFERROR(INDEX(_RefTable!$B$2:$B$501,MATCH($B14,_RefTable!$C$2:$C$501,0))&IF(COUNTIF(_RefTable!$C$2:$C$501,$B14)>1," (+"&COUNTIF(_RefTable!$C$2:$C$501,$B14)-1&" more)",""),IFERROR(INDEX(_MainTable!$B$2:$B$2001,MATCH($B14,_MainTable!$F$2:$F$2001,0)),"")))&""="","—",(IFERROR(INDEX(_RefTable!$B$2:$B$501,MATCH($B14,_RefTable!$C$2:$C$501,0))&IF(COUNTIF(_RefTable!$C$2:$C$501,$B14)>1," (+"&COUNTIF(_RefTable!$C$2:$C$501,$B14)-1&" more)",""),IFERROR(INDEX(_MainTable!$B$2:$B$2001,MATCH($B14,_MainTable!$F$2:$F$2001,0)),""))))) -> DRG Validation | D14: =IF($B14="","",IF((IFERROR(INDEX(_RefTable!$E$2:$E$501,MATCH($B14,_RefTable!$C$2:$C$501,0)),IFERROR(INDEX(_MainTable!$C$2:$C$2001,MATCH($B14,_MainTable!$F$2:$F$2001,0)),"")))&""="","—",(IFERROR(INDEX(_RefTable!$E$2:$E$501,MATCH($B14,_RefTable!$C$2:$C$501,0)),IFERROR(INDEX(_MainTable!$C$2:$C$2001,MATCH($B14,_MainTable!$F$2:$F$2001,0)),""))))) -> Sona Buchanan | E14: =IF($B14="","",IF((IFERROR(INDEX(_RefTable!$F$2:$F$501,MATCH($B14,_RefTable!$C$2:$C$501,0)),IFERROR(INDEX(_MainTable!$D$2:$D$2001,MATCH($B14,_MainTable!$F$2:$F$2001,0)),"")))&""="","—",(IFERROR(INDEX(_RefTable!$F$2:$F$501,MATCH($B14,_RefTable!$C$2:$C$501,0)),IFERROR(INDEX(_MainTable!$D$2:$D$2001,MATCH($B14,_MainTable!$F$2:$F$2001,0)),""))))) -> Heather Geile | F14: =IF($B14="","",IFERROR(_xlfn.MINIFS('SC Change Orders'!$E$2:$E$501,'SC Change Orders'!$B$2:$B$501,$B14,'SC Change Orders'!$C$2:$C$501,">="&Controls!$C$5,'SC Change Orders'!$C$2:$C$501,"<="&Controls!$C$6),0)) -> 0 | G14: =IF($B14="","",SUMIFS('SC Change Orders'!$F$2:$F$501,'SC Change Orders'!$B$2:$B$501,$B14,'SC Change Orders'!$C$2:$C$501,">="&Controls!$C$5,'SC Change Orders'!$C$2:$C$501,"<="&Controls!$C$6)) -> 0 | H14: =IF($B14="","",$F14+$G14) -> 0 | I14: =IF($B14="","",SUMIFS(_MainTable!$K$2:$K$2001,_MainTable!$F$2:$F$2001,$B14,_MainTable!$G$2:$G$2001,">="&Controls!$C$5,_MainTable!$G$2:$G$2001,"<="&Controls!$C$6)) -> 106560.16 | J14: =IF($B14="","",IFERROR($I14/$H14,0)) -> 0 | K14: =IF($B14="","",$H14-$I14) -> -106560.16 | L14: =IF($B14="","",IFERROR(SUMIFS(_MainTable!$K$2:$K$2001,_MainTable!$F$2:$F$2001,$B14,_MainTable!$G$2:$G$2001,">="&Controls!$C$12,_MainTable!$G$2:$G$2001,"<="&EOMONTH(Controls!$C$7,0))/MIN(Controls!$C$9,Controls!$C$10),0)) -> 29782.7 | M14: =IF($B14="","",$L14*Controls!$C$11) -> 59565.4 | N14: =IF($B14="","",$I14+$M14) -> 166125.56 | O14: =IF($B14="","",IFERROR($N14/$H14,0)) -> 0 | P14: =IF($B14="","",$H14-$N14) -> -166125.56 | Q14: =IF($B14="","",IF($L14<=0,"n/a",IFERROR($K14/$L14,"n/a"))) -> -3.5779214 | R14: =IF($B14="","",IF(AND($H14=0,$I14=0),"⚪ No Activity",IF(AND($H14=0,COUNTIFS('SC Change Orders'!$B$2:$B$501,$B14,'SC Change Orders'!$C$2:$C$501,">="&Controls!$C$5,'SC Change Orders'!$C$2:$C$501,"<="&Controls!$C$6)=0),"⚪ No Funding on File",IF($H14=0,"🔴 Unfunded Spend",IF($I14>=$H14,"🔴 Over Budget",IF($N14>$H14,"🔴 Projected Shortfall",IF($J14>=Controls!$C$8,"🟡 Watch","🟢 On Track"))))))) -> ⚪ No Funding on File
A15: =IF($B15="","",IF((IFERROR(INDEX(_RefTable!$A$2:$A$501,MATCH($B15,_RefTable!$C$2:$C$501,0)),IFERROR(INDEX(_MainTable!$A$2:$A$2001,MATCH($B15,_MainTable!$F$2:$F$2001,0)),IFERROR(INDEX('SC Change Orders'!$A$2:$A$501,MATCH($B15,'SC Change Orders'!$B$2:$B$501,0)),"(unknown vendor)"))))&""="","—",(IFERROR(INDEX(_RefTable!$A$2:$A$501,MATCH($B15,_RefTable!$C$2:$C$501,0)),IFERROR(INDEX(_MainTable!$A$2:$A$2001,MATCH($B15,_MainTable!$F$2:$F$2001,0)),IFERROR(INDEX('SC Change Orders'!$A$2:$A$501,MATCH($B15,'SC Change Orders'!$B$2:$B$501,0)),"(unknown vendor)")))))) -> SOLVENTUM HEALTH INFO SYSTEM | B15: =IFERROR(INDEX('PO Index'!$B$5:$B$84,11),"") -> 9916 | C15: =IF($B15="","",IF((IFERROR(INDEX(_RefTable!$B$2:$B$501,MATCH($B15,_RefTable!$C$2:$C$501,0))&IF(COUNTIF(_RefTable!$C$2:$C$501,$B15)>1," (+"&COUNTIF(_RefTable!$C$2:$C$501,$B15)-1&" more)",""),IFERROR(INDEX(_MainTable!$B$2:$B$2001,MATCH($B15,_MainTable!$F$2:$F$2001,0)),"")))&""="","—",(IFERROR(INDEX(_RefTable!$B$2:$B$501,MATCH($B15,_RefTable!$C$2:$C$501,0))&IF(COUNTIF(_RefTable!$C$2:$C$501,$B15)>1," (+"&COUNTIF(_RefTable!$C$2:$C$501,$B15)-1&" more)",""),IFERROR(INDEX(_MainTable!$B$2:$B$2001,MATCH($B15,_MainTable!$F$2:$F$2001,0)),""))))) -> Inpatient CDI | D15: =IF($B15="","",IF((IFERROR(INDEX(_RefTable!$E$2:$E$501,MATCH($B15,_RefTable!$C$2:$C$501,0)),IFERROR(INDEX(_MainTable!$C$2:$C$2001,MATCH($B15,_MainTable!$F$2:$F$2001,0)),"")))&""="","—",(IFERROR(INDEX(_RefTable!$E$2:$E$501,MATCH($B15,_RefTable!$C$2:$C$501,0)),IFERROR(INDEX(_MainTable!$C$2:$C$2001,MATCH($B15,_MainTable!$F$2:$F$2001,0)),""))))) -> Sona Buchanan | E15: =IF($B15="","",IF((IFERROR(INDEX(_RefTable!$F$2:$F$501,MATCH($B15,_RefTable!$C$2:$C$501,0)),IFERROR(INDEX(_MainTable!$D$2:$D$2001,MATCH($B15,_MainTable!$F$2:$F$2001,0)),"")))&""="","—",(IFERROR(INDEX(_RefTable!$F$2:$F$501,MATCH($B15,_RefTable!$C$2:$C$501,0)),IFERROR(INDEX(_MainTable!$D$2:$D$2001,MATCH($B15,_MainTable!$F$2:$F$2001,0)),""))))) -> Janae Schumacher | F15: =IF($B15="","",IFERROR(_xlfn.MINIFS('SC Change Orders'!$E$2:$E$501,'SC Change Orders'!$B$2:$B$501,$B15,'SC Change Orders'!$C$2:$C$501,">="&Controls!$C$5,'SC Change Orders'!$C$2:$C$501,"<="&Controls!$C$6),0)) -> 0 | G15: =IF($B15="","",SUMIFS('SC Change Orders'!$F$2:$F$501,'SC Change Orders'!$B$2:$B$501,$B15,'SC Change Orders'!$C$2:$C$501,">="&Controls!$C$5,'SC Change Orders'!$C$2:$C$501,"<="&Controls!$C$6)) -> 0 | H15: =IF($B15="","",$F15+$G15) -> 0 | I15: =IF($B15="","",SUMIFS(_MainTable!$K$2:$K$2001,_MainTable!$F$2:$F$2001,$B15,_MainTable!$G$2:$G$2001,">="&Controls!$C$5,_MainTable!$G$2:$G$2001,"<="&Controls!$C$6)) -> 185499.25 | J15: =IF($B15="","",IFERROR($I15/$H15,0)) -> 0 | K15: =IF($B15="","",$H15-$I15) -> -185499.25 | L15: =IF($B15="","",IFERROR(SUMIFS(_MainTable!$K$2:$K$2001,_MainTable!$F$2:$F$2001,$B15,_MainTable!$G$2:$G$2001,">="&Controls!$C$12,_MainTable!$G$2:$G$2001,"<="&EOMONTH(Controls!$C$7,0))/MIN(Controls!$C$9,Controls!$C$10),0)) -> 0 | M15: =IF($B15="","",$L15*Controls!$C$11) -> 0 | N15: =IF($B15="","",$I15+$M15) -> 185499.25 | O15: =IF($B15="","",IFERROR($N15/$H15,0)) -> 0 | P15: =IF($B15="","",$H15-$N15) -> -185499.25 | Q15: =IF($B15="","",IF($L15<=0,"n/a",IFERROR($K15/$L15,"n/a"))) -> n/a | R15: =IF($B15="","",IF(AND($H15=0,$I15=0),"⚪ No Activity",IF(AND($H15=0,COUNTIFS('SC Change Orders'!$B$2:$B$501,$B15,'SC Change Orders'!$C$2:$C$501,">="&Controls!$C$5,'SC Change Orders'!$C$2:$C$501,"<="&Controls!$C$6)=0),"⚪ No Funding on File",IF($H15=0,"🔴 Unfunded Spend",IF($I15>=$H15,"🔴 Over Budget",IF($N15>$H15,"🔴 Projected Shortfall",IF($J15>=Controls!$C$8,"🟡 Watch","🟢 On Track"))))))) -> ⚪ No Funding on File
A16: =IF($B16="","",IF((IFERROR(INDEX(_RefTable!$A$2:$A$501,MATCH($B16,_RefTable!$C$2:$C$501,0)),IFERROR(INDEX(_MainTable!$A$2:$A$2001,MATCH($B16,_MainTable!$F$2:$F$2001,0)),IFERROR(INDEX('SC Change Orders'!$A$2:$A$501,MATCH($B16,'SC Change Orders'!$B$2:$B$501,0)),"(unknown vendor)"))))&""="","—",(IFERROR(INDEX(_RefTable!$A$2:$A$501,MATCH($B16,_RefTable!$C$2:$C$501,0)),IFERROR(INDEX(_MainTable!$A$2:$A$2001,MATCH($B16,_MainTable!$F$2:$F$2001,0)),IFERROR(INDEX('SC Change Orders'!$A$2:$A$501,MATCH($B16,'SC Change Orders'!$B$2:$B$501,0)),"(unknown vendor)")))))) -> TERNIUM LLC | B16: =IFERROR(INDEX('PO Index'!$B$5:$B$84,12),"") -> 10118 | C16: =IF($B16="","",IF((IFERROR(INDEX(_RefTable!$B$2:$B$501,MATCH($B16,_RefTable!$C$2:$C$501,0))&IF(COUNTIF(_RefTable!$C$2:$C$501,$B16)>1," (+"&COUNTIF(_RefTable!$C$2:$C$501,$B16)-1&" more)",""),IFERROR(INDEX(_MainTable!$B$2:$B$2001,MATCH($B16,_MainTable!$F$2:$F$2001,0)),"")))&""="","—",(IFERROR(INDEX(_RefTable!$B$2:$B$501,MATCH($B16,_RefTable!$C$2:$C$501,0))&IF(COUNTIF(_RefTable!$C$2:$C$501,$B16)>1," (+"&COUNTIF(_RefTable!$C$2:$C$501,$B16)-1&" more)",""),IFERROR(INDEX(_MainTable!$B$2:$B$2001,MATCH($B16,_MainTable!$F$2:$F$2001,0)),""))))) -> High dollar appeals | D16: =IF($B16="","",IF((IFERROR(INDEX(_RefTable!$E$2:$E$501,MATCH($B16,_RefTable!$C$2:$C$501,0)),IFERROR(INDEX(_MainTable!$C$2:$C$2001,MATCH($B16,_MainTable!$F$2:$F$2001,0)),"")))&""="","—",(IFERROR(INDEX(_RefTable!$E$2:$E$501,MATCH($B16,_RefTable!$C$2:$C$501,0)),IFERROR(INDEX(_MainTable!$C$2:$C$2001,MATCH($B16,_MainTable!$F$2:$F$2001,0)),""))))) -> Jake Reid | E16: =IF($B16="","",IF((IFERROR(INDEX(_RefTable!$F$2:$F$501,MATCH($B16,_RefTable!$C$2:$C$501,0)),IFERROR(INDEX(_MainTable!$D$2:$D$2001,MATCH($B16,_MainTable!$F$2:$F$2001,0)),"")))&""="","—",(IFERROR(INDEX(_RefTable!$F$2:$F$501,MATCH($B16,_RefTable!$C$2:$C$501,0)),IFERROR(INDEX(_MainTable!$D$2:$D$2001,MATCH($B16,_MainTable!$F$2:$F$2001,0)),""))))) -> Cody Thornock | F16: =IF($B16="","",IFERROR(_xlfn.MINIFS('SC Change Orders'!$E$2:$E$501,'SC Change Orders'!$B$2:$B$501,$B16,'SC Change Orders'!$C$2:$C$501,">="&Controls!$C$5,'SC Change Orders'!$C$2:$C$501,"<="&Controls!$C$6),0)) -> 0 | G16: =IF($B16="","",SUMIFS('SC Change Orders'!$F$2:$F$501,'SC Change Orders'!$B$2:$B$501,$B16,'SC Change Orders'!$C$2:$C$501,">="&Controls!$C$5,'SC Change Orders'!$C$2:$C$501,"<="&Controls!$C$6)) -> 0 | H16: =IF($B16="","",$F16+$G16) -> 0 | I16: =IF($B16="","",SUMIFS(_MainTable!$K$2:$K$2001,_MainTable!$F$2:$F$2001,$B16,_MainTable!$G$2:$G$2001,">="&Controls!$C$5,_MainTable!$G$2:$G$2001,"<="&Controls!$C$6)) -> 572803.83 | J16: =IF($B16="","",IFERROR($I16/$H16,0)) -> 0 | K16: =IF($B16="","",$H16-$I16) -> -572803.83 | L16: =IF($B16="","",IFERROR(SUMIFS(_MainTable!$K$2:$K$2001,_MainTable!$F$2:$F$2001,$B16,_MainTable!$G$2:$G$2001,">="&Controls!$C$12,_MainTable!$G$2:$G$2001,"<="&EOMONTH(Controls!$C$7,0))/MIN(Controls!$C$9,Controls!$C$10),0)) -> 126869.25 | M16: =IF($B16="","",$L16*Controls!$C$11) -> 253738.51 | N16: =IF($B16="","",$I16+$M16) -> 826542.34 | O16: =IF($B16="","",IFERROR($N16/$H16,0)) -> 0 | P16: =IF($B16="","",$H16-$N16) -> -826542.34 | Q16: =IF($B16="","",IF($L16<=0,"n/a",IFERROR($K16/$L16,"n/a"))) -> -4.5149145 | R16: =IF($B16="","",IF(AND($H16=0,$I16=0),"⚪ No Activity",IF(AND($H16=0,COUNTIFS('SC Change Orders'!$B$2:$B$501,$B16,'SC Change Orders'!$C$2:$C$501,">="&Controls!$C$5,'SC Change Orders'!$C$2:$C$501,"<="&Controls!$C$6)=0),"⚪ No Funding on File",IF($H16=0,"🔴 Unfunded Spend",IF($I16>=$H16,"🔴 Over Budget",IF($N16>$H16,"🔴 Projected Shortfall",IF($J16>=Controls!$C$8,"🟡 Watch","🟢 On Track"))))))) -> ⚪ No Funding on File
A17: =IF($B17="","",IF((IFERROR(INDEX(_RefTable!$A$2:$A$501,MATCH($B17,_RefTable!$C$2:$C$501,0)),IFERROR(INDEX(_MainTable!$A$2:$A$2001,MATCH($B17,_MainTable!$F$2:$F$2001,0)),IFERROR(INDEX('SC Change Orders'!$A$2:$A$501,MATCH($B17,'SC Change Orders'!$B$2:$B$501,0)),"(unknown vendor)"))))&""="","—",(IFERROR(INDEX(_RefTable!$A$2:$A$501,MATCH($B17,_RefTable!$C$2:$C$501,0)),IFERROR(INDEX(_MainTable!$A$2:$A$2001,MATCH($B17,_MainTable!$F$2:$F$2001,0)),IFERROR(INDEX('SC Change Orders'!$A$2:$A$501,MATCH($B17,'SC Change Orders'!$B$2:$B$501,0)),"(unknown vendor)")))))) -> EPIC ADVISORS GROUP LLC | B17: =IFERROR(INDEX('PO Index'!$B$5:$B$84,13),"") -> 10138 | C17: =IF($B17="","",IF((IFERROR(INDEX(_RefTable!$B$2:$B$501,MATCH($B17,_RefTable!$C$2:$C$501,0))&IF(COUNTIF(_RefTable!$C$2:$C$501,$B17)>1," (+"&COUNTIF(_RefTable!$C$2:$C$501,$B17)-1&" more)",""),IFERROR(INDEX(_MainTable!$B$2:$B$2001,MATCH($B17,_MainTable!$F$2:$F$2001,0)),"")))&""="","—",(IFERROR(INDEX(_RefTable!$B$2:$B$501,MATCH($B17,_RefTable!$C$2:$C$501,0))&IF(COUNTIF(_RefTable!$C$2:$C$501,$B17)>1," (+"&COUNTIF(_RefTable!$C$2:$C$501,$B17)-1&" more)",""),IFERROR(INDEX(_MainTable!$B$2:$B$2001,MATCH($B17,_MainTable!$F$2:$F$2001,0)),""))))) -> Consultation | D17: =IF($B17="","",IF((IFERROR(INDEX(_RefTable!$E$2:$E$501,MATCH($B17,_RefTable!$C$2:$C$501,0)),IFERROR(INDEX(_MainTable!$C$2:$C$2001,MATCH($B17,_MainTable!$F$2:$F$2001,0)),"")))&""="","—",(IFERROR(INDEX(_RefTable!$E$2:$E$501,MATCH($B17,_RefTable!$C$2:$C$501,0)),IFERROR(INDEX(_MainTable!$C$2:$C$2001,MATCH($B17,_MainTable!$F$2:$F$2001,0)),""))))) -> Michelle Lewis | E17: =IF($B17="","",IF((IFERROR(INDEX(_RefTable!$F$2:$F$501,MATCH($B17,_RefTable!$C$2:$C$501,0)),IFERROR(INDEX(_MainTable!$D$2:$D$2001,MATCH($B17,_MainTable!$F$2:$F$2001,0)),"")))&""="","—",(IFERROR(INDEX(_RefTable!$F$2:$F$501,MATCH($B17,_RefTable!$C$2:$C$501,0)),IFERROR(INDEX(_MainTable!$D$2:$D$2001,MATCH($B17,_MainTable!$F$2:$F$2001,0)),""))))) -> Adam Vardaman | F17: =IF($B17="","",IFERROR(_xlfn.MINIFS('SC Change Orders'!$E$2:$E$501,'SC Change Orders'!$B$2:$B$501,$B17,'SC Change Orders'!$C$2:$C$501,">="&Controls!$C$5,'SC Change Orders'!$C$2:$C$501,"<="&Controls!$C$6),0)) -> 72000 | G17: =IF($B17="","",SUMIFS('SC Change Orders'!$F$2:$F$501,'SC Change Orders'!$B$2:$B$501,$B17,'SC Change Orders'!$C$2:$C$501,">="&Controls!$C$5,'SC Change Orders'!$C$2:$C$501,"<="&Controls!$C$6)) -> 258295 | H17: =IF($B17="","",$F17+$G17) -> 330295 | I17: =IF($B17="","",SUMIFS(_MainTable!$K$2:$K$2001,_MainTable!$F$2:$F$2001,$B17,_MainTable!$G$2:$G$2001,">="&Controls!$C$5,_MainTable!$G$2:$G$2001,"<="&Controls!$C$6)) -> 119515.42 | J17: =IF($B17="","",IFERROR($I17/$H17,0)) -> 0.36184447 | K17: =IF($B17="","",$H17-$I17) -> 210779.58 | L17: =IF($B17="","",IFERROR(SUMIFS(_MainTable!$K$2:$K$2001,_MainTable!$F$2:$F$2001,$B17,_MainTable!$G$2:$G$2001,">="&Controls!$C$12,_MainTable!$G$2:$G$2001,"<="&EOMONTH(Controls!$C$7,0))/MIN(Controls!$C$9,Controls!$C$10),0)) -> 25215.473 | M17: =IF($B17="","",$L17*Controls!$C$11) -> 50430.947 | N17: =IF($B17="","",$I17+$M17) -> 169946.37 | O17: =IF($B17="","",IFERROR($N17/$H17,0)) -> 0.51452903 | P17: =IF($B17="","",$H17-$N17) -> 160348.63 | Q17: =IF($B17="","",IF($L17<=0,"n/a",IFERROR($K17/$L17,"n/a"))) -> 8.3591364 | R17: =IF($B17="","",IF(AND($H17=0,$I17=0),"⚪ No Activity",IF(AND($H17=0,COUNTIFS('SC Change Orders'!$B$2:$B$501,$B17,'SC Change Orders'!$C$2:$C$501,">="&Controls!$C$5,'SC Change Orders'!$C$2:$C$501,"<="&Controls!$C$6)=0),"⚪ No Funding on File",IF($H17=0,"🔴 Unfunded Spend",IF($I17>=$H17,"🔴 Over Budget",IF($N17>$H17,"🔴 Projected Shortfall",IF($J17>=Controls!$C$8,"🟡 Watch","🟢 On Track"))))))) -> 🟢 On Track
A18: =IF($B18="","",IF((IFERROR(INDEX(_RefTable!$A$2:$A$501,MATCH($B18,_RefTable!$C$2:$C$501,0)),IFERROR(INDEX(_MainTable!$A$2:$A$2001,MATCH($B18,_MainTable!$F$2:$F$2001,0)),IFERROR(INDEX('SC Change Orders'!$A$2:$A$501,MATCH($B18,'SC Change Orders'!$B$2:$B$501,0)),"(unknown vendor)"))))&""="","—",(IFERROR(INDEX(_RefTable!$A$2:$A$501,MATCH($B18,_RefTable!$C$2:$C$501,0)),IFERROR(INDEX(_MainTable!$A$2:$A$2001,MATCH($B18,_MainTable!$F$2:$F$2001,0)),IFERROR(INDEX('SC Change Orders'!$A$2:$A$501,MATCH($B18,'SC Change Orders'!$B$2:$B$501,0)),"(unknown vendor)")))))) -> ASPIRION HEALTH RESOURCES | B18: =IFERROR(INDEX('PO Index'!$B$5:$B$84,14),"") -> 10200 | C18: =IF($B18="","",IF((IFERROR(INDEX(_RefTable!$B$2:$B$501,MATCH($B18,_RefTable!$C$2:$C$501,0))&IF(COUNTIF(_RefTable!$C$2:$C$501,$B18)>1," (+"&COUNTIF(_RefTable!$C$2:$C$501,$B18)-1&" more)",""),IFERROR(INDEX(_MainTable!$B$2:$B$2001,MATCH($B18,_MainTable!$F$2:$F$2001,0)),"")))&""="","—",(IFERROR(INDEX(_RefTable!$B$2:$B$501,MATCH($B18,_RefTable!$C$2:$C$501,0))&IF(COUNTIF(_RefTable!$C$2:$C$501,$B18)>1," (+"&COUNTIF(_RefTable!$C$2:$C$501,$B18)-1&" more)",""),IFERROR(INDEX(_MainTable!$B$2:$B$2001,MATCH($B18,_MainTable!$F$2:$F$2001,0)),""))))) -> MVA (+1 more) | D18: =IF($B18="","",IF((IFERROR(INDEX(_RefTable!$E$2:$E$501,MATCH($B18,_RefTable!$C$2:$C$501,0)),IFERROR(INDEX(_MainTable!$C$2:$C$2001,MATCH($B18,_MainTable!$F$2:$F$2001,0)),"")))&""="","—",(IFERROR(INDEX(_RefTable!$E$2:$E$501,MATCH($B18,_RefTable!$C$2:$C$501,0)),IFERROR(INDEX(_MainTable!$C$2:$C$2001,MATCH($B18,_MainTable!$F$2:$F$2001,0)),""))))) -> Jake Reid | E18: =IF($B18="","",IF((IFERROR(INDEX(_RefTable!$F$2:$F$501,MATCH($B18,_RefTable!$C$2:$C$501,0)),IFERROR(INDEX(_MainTable!$D$2:$D$2001,MATCH($B18,_MainTable!$F$2:$F$2001,0)),"")))&""="","—",(IFERROR(INDEX(_RefTable!$F$2:$F$501,MATCH($B18,_RefTable!$C$2:$C$501,0)),IFERROR(INDEX(_MainTable!$D$2:$D$2001,MATCH($B18,_MainTable!$F$2:$F$2001,0)),""))))) -> Cody Thornock | F18: =IF($B18="","",IFERROR(_xlfn.MINIFS('SC Change Orders'!$E$2:$E$501,'SC Change Orders'!$B$2:$B$501,$B18,'SC Change Orders'!$C$2:$C$501,">="&Controls!$C$5,'SC Change Orders'!$C$2:$C$501,"<="&Controls!$C$6),0)) -> 92500 | G18: =IF($B18="","",SUMIFS('SC Change Orders'!$F$2:$F$501,'SC Change Orders'!$B$2:$B$501,$B18,'SC Change Orders'!$C$2:$C$501,">="&Controls!$C$5,'SC Change Orders'!$C$2:$C$501,"<="&Controls!$C$6)) -> 6353265.8 | H18: =IF($B18="","",$F18+$G18) -> 6445765.8 | I18: =IF($B18="","",SUMIFS(_MainTable!$K$2:$K$2001,_MainTable!$F$2:$F$2001,$B18,_MainTable!$G$2:$G$2001,">="&Controls!$C$5,_MainTable!$G$2:$G$2001,"<="&Controls!$C$6)) -> 4119364.1 | J18: =IF($B18="","",IFERROR($I18/$H18,0)) -> 0.63908063 | K18: =IF($B18="","",$H18-$I18) -> 2326401.8 | L18: =IF($B18="","",IFERROR(SUMIFS(_MainTable!$K$2:$K$2001,_MainTable!$F$2:$F$2001,$B18,_MainTable!$G$2:$G$2001,">="&Controls!$C$12,_MainTable!$G$2:$G$2001,"<="&EOMONTH(Controls!$C$7,0))/MIN(Controls!$C$9,Controls!$C$10),0)) -> 565165.09 | M18: =IF($B18="","",$L18*Controls!$C$11) -> 1130330.2 | N18: =IF($B18="","",$I18+$M18) -> 5249694.2 | O18: =IF($B18="","",IFERROR($N18/$H18,0)) -> 0.81444073 | P18: =IF($B18="","",$H18-$N18) -> 1196071.6 | Q18: =IF($B18="","",IF($L18<=0,"n/a",IFERROR($K18/$L18,"n/a"))) -> 4.1163225 | R18: =IF($B18="","",IF(AND($H18=0,$I18=0),"⚪ No Activity",IF(AND($H18=0,COUNTIFS('SC Change Orders'!$B$2:$B$501,$B18,'SC Change Orders'!$C$2:$C$501,">="&Controls!$C$5,'SC Change Orders'!$C$2:$C$501,"<="&Controls!$C$6)=0),"⚪ No Funding on File",IF($H18=0,"🔴 Unfunded Spend",IF($I18>=$H18,"🔴 Over Budget",IF($N18>$H18,"🔴 Projected Shortfall",IF($J18>=Controls!$C$8,"🟡 Watch","🟢 On Track"))))))) -> 🟢 On Track
A19: =IF($B19="","",IF((IFERROR(INDEX(_RefTable!$A$2:$A$501,MATCH($B19,_RefTable!$C$2:$C$501,0)),IFERROR(INDEX(_MainTable!$A$2:$A$2001,MATCH($B19,_MainTable!$F$2:$F$2001,0)),IFERROR(INDEX('SC Change Orders'!$A$2:$A$501,MATCH($B19,'SC Change Orders'!$B$2:$B$501,0)),"(unknown vendor)"))))&""="","—",(IFERROR(INDEX(_RefTable!$A$2:$A$501,MATCH($B19,_RefTable!$C$2:$C$501,0)),IFERROR(INDEX(_MainTable!$A$2:$A$2001,MATCH($B19,_MainTable!$F$2:$F$2001,0)),IFERROR(INDEX('SC Change Orders'!$A$2:$A$501,MATCH($B19,'SC Change Orders'!$B$2:$B$501,0)),"(unknown vendor)")))))) -> FINTHRIVE HEALTHCARE INC | B19: =IFERROR(INDEX('PO Index'!$B$5:$B$84,15),"") -> 10406 | C19: =IF($B19="","",IF((IFERROR(INDEX(_RefTable!$B$2:$B$501,MATCH($B19,_RefTable!$C$2:$C$501,0))&IF(COUNTIF(_RefTable!$C$2:$C$501,$B19)>1," (+"&COUNTIF(_RefTable!$C$2:$C$501,$B19)-1&" more)",""),IFERROR(INDEX(_MainTable!$B$2:$B$2001,MATCH($B19,_MainTable!$F$2:$F$2001,0)),"")))&""="","—",(IFERROR(INDEX(_RefTable!$B$2:$B$501,MATCH($B19,_RefTable!$C$2:$C$501,0))&IF(COUNTIF(_RefTable!$C$2:$C$501,$B19)>1," (+"&COUNTIF(_RefTable!$C$2:$C$501,$B19)-1&" more)",""),IFERROR(INDEX(_MainTable!$B$2:$B$2001,MATCH($B19,_MainTable!$F$2:$F$2001,0)),""))))) -> Transunion (+1 more) | D19: =IF($B19="","",IF((IFERROR(INDEX(_RefTable!$E$2:$E$501,MATCH($B19,_RefTable!$C$2:$C$501,0)),IFERROR(INDEX(_MainTable!$C$2:$C$2001,MATCH($B19,_MainTable!$F$2:$F$2001,0)),"")))&""="","—",(IFERROR(INDEX(_RefTable!$E$2:$E$501,MATCH($B19,_RefTable!$C$2:$C$501,0)),IFERROR(INDEX(_MainTable!$C$2:$C$2001,MATCH($B19,_MainTable!$F$2:$F$2001,0)),""))))) -> Sona Buchanan | E19: =IF($B19="","",IF((IFERROR(INDEX(_RefTable!$F$2:$F$501,MATCH($B19,_RefTable!$C$2:$C$501,0)),IFERROR(INDEX(_MainTable!$D$2:$D$2001,MATCH($B19,_MainTable!$F$2:$F$2001,0)),"")))&""="","—",(IFERROR(INDEX(_RefTable!$F$2:$F$501,MATCH($B19,_RefTable!$C$2:$C$501,0)),IFERROR(INDEX(_MainTable!$D$2:$D$2001,MATCH($B19,_MainTable!$F$2:$F$2001,0)),""))))) -> Tawnya Kraus | F19: =IF($B19="","",IFERROR(_xlfn.MINIFS('SC Change Orders'!$E$2:$E$501,'SC Change Orders'!$B$2:$B$501,$B19,'SC Change Orders'!$C$2:$C$501,">="&Controls!$C$5,'SC Change Orders'!$C$2:$C$501,"<="&Controls!$C$6),0)) -> 0 | G19: =IF($B19="","",SUMIFS('SC Change Orders'!$F$2:$F$501,'SC Change Orders'!$B$2:$B$501,$B19,'SC Change Orders'!$C$2:$C$501,">="&Controls!$C$5,'SC Change Orders'!$C$2:$C$501,"<="&Controls!$C$6)) -> 0 | H19: =IF($B19="","",$F19+$G19) -> 0 | I19: =IF($B19="","",SUMIFS(_MainTable!$K$2:$K$2001,_MainTable!$F$2:$F$2001,$B19,_MainTable!$G$2:$G$2001,">="&Controls!$C$5,_MainTable!$G$2:$G$2001,"<="&Controls!$C$6)) -> 4095.63 | J19: =IF($B19="","",IFERROR($I19/$H19,0)) -> 0 | K19: =IF($B19="","",$H19-$I19) -> -4095.63 | L19: =IF($B19="","",IFERROR(SUMIFS(_MainTable!$K$2:$K$2001,_MainTable!$F$2:$F$2001,$B19,_MainTable!$G$2:$G$2001,">="&Controls!$C$12,_MainTable!$G$2:$G$2001,"<="&EOMONTH(Controls!$C$7,0))/MIN(Controls!$C$9,Controls!$C$10),0)) -> 847.31 | M19: =IF($B19="","",$L19*Controls!$C$11) -> 1694.62 | N19: =IF($B19="","",$I19+$M19) -> 5790.25 | O19: =IF($B19="","",IFERROR($N19/$H19,0)) -> 0 | P19: =IF($B19="","",$H19-$N19) -> -5790.25 | Q19: =IF($B19="","",IF($L19<=0,"n/a",IFERROR($K19/$L19,"n/a"))) -> -4.8336854 | R19: =IF($B19="","",IF(AND($H19=0,$I19=0),"⚪ No Activity",IF(AND($H19=0,COUNTIFS('SC Change Orders'!$B$2:$B$501,$B19,'SC Change Orders'!$C$2:$C$501,">="&Controls!$C$5,'SC Change Orders'!$C$2:$C$501,"<="&Controls!$C$6)=0),"⚪ No Funding on File",IF($H19=0,"🔴 Unfunded Spend",IF($I19>=$H19,"🔴 Over Budget",IF($N19>$H19,"🔴 Projected Shortfall",IF($J19>=Controls!$C$8,"🟡 Watch","🟢 On Track"))))))) -> ⚪ No Funding on File
A20: =IF($B20="","",IF((IFERROR(INDEX(_RefTable!$A$2:$A$501,MATCH($B20,_RefTable!$C$2:$C$501,0)),IFERROR(INDEX(_MainTable!$A$2:$A$2001,MATCH($B20,_MainTable!$F$2:$F$2001,0)),IFERROR(INDEX('SC Change Orders'!$A$2:$A$501,MATCH($B20,'SC Change Orders'!$B$2:$B$501,0)),"(unknown vendor)"))))&""="","—",(IFERROR(INDEX(_RefTable!$A$2:$A$501,MATCH($B20,_RefTable!$C$2:$C$501,0)),IFERROR(INDEX(_MainTable!$A$2:$A$2001,MATCH($B20,_MainTable!$F$2:$F$2001,0)),IFERROR(INDEX('SC Change Orders'!$A$2:$A$501,MATCH($B20,'SC Change Orders'!$B$2:$B$501,0)),"(unknown vendor)")))))) -> FMS INC | B20: =IFERROR(INDEX('PO Index'!$B$5:$B$84,16),"") -> 10407 | C20: =IF($B20="","",IF((IFERROR(INDEX(_RefTable!$B$2:$B$501,MATCH($B20,_RefTable!$C$2:$C$501,0))&IF(COUNTIF(_RefTable!$C$2:$C$501,$B20)>1," (+"&COUNTIF(_RefTable!$C$2:$C$501,$B20)-1&" more)",""),IFERROR(INDEX(_MainTable!$B$2:$B$2001,MATCH($B20,_MainTable!$F$2:$F$2001,0)),"")))&""="","—",(IFERROR(INDEX(_RefTable!$B$2:$B$501,MATCH($B20,_RefTable!$C$2:$C$501,0))&IF(COUNTIF(_RefTable!$C$2:$C$501,$B20)>1," (+"&COUNTIF(_RefTable!$C$2:$C$501,$B20)-1&" more)",""),IFERROR(INDEX(_MainTable!$B$2:$B$2001,MATCH($B20,_MainTable!$F$2:$F$2001,0)),""))))) -> Early Out (+1 more) | D20: =IF($B20="","",IF((IFERROR(INDEX(_RefTable!$E$2:$E$501,MATCH($B20,_RefTable!$C$2:$C$501,0)),IFERROR(INDEX(_MainTable!$C$2:$C$2001,MATCH($B20,_MainTable!$F$2:$F$2001,0)),"")))&""="","—",(IFERROR(INDEX(_RefTable!$E$2:$E$501,MATCH($B20,_RefTable!$C$2:$C$501,0)),IFERROR(INDEX(_MainTable!$C$2:$C$2001,MATCH($B20,_MainTable!$F$2:$F$2001,0)),""))))) -> Jake Reid | E20: =IF($B20="","",IF((IFERROR(INDEX(_RefTable!$F$2:$F$501,MATCH($B20,_RefTable!$C$2:$C$501,0)),IFERROR(INDEX(_MainTable!$D$2:$D$2001,MATCH($B20,_MainTable!$F$2:$F$2001,0)),"")))&""="","—",(IFERROR(INDEX(_RefTable!$F$2:$F$501,MATCH($B20,_RefTable!$C$2:$C$501,0)),IFERROR(INDEX(_MainTable!$D$2:$D$2001,MATCH($B20,_MainTable!$F$2:$F$2001,0)),""))))) -> Letisia Speelman | F20: =IF($B20="","",IFERROR(_xlfn.MINIFS('SC Change Orders'!$E$2:$E$501,'SC Change Orders'!$B$2:$B$501,$B20,'SC Change Orders'!$C$2:$C$501,">="&Controls!$C$5,'SC Change Orders'!$C$2:$C$501,"<="&Controls!$C$6),0)) -> 0 | G20: =IF($B20="","",SUMIFS('SC Change Orders'!$F$2:$F$501,'SC Change Orders'!$B$2:$B$501,$B20,'SC Change Orders'!$C$2:$C$501,">="&Controls!$C$5,'SC Change Orders'!$C$2:$C$501,"<="&Controls!$C$6)) -> 0 | H20: =IF($B20="","",$F20+$G20) -> 0 | I20: =IF($B20="","",SUMIFS(_MainTable!$K$2:$K$2001,_MainTable!$F$2:$F$2001,$B20,_MainTable!$G$2:$G$2001,">="&Controls!$C$5,_MainTable!$G$2:$G$2001,"<="&Controls!$C$6)) -> 973131.24 | J20: =IF($B20="","",IFERROR($I20/$H20,0)) -> 0 | K20: =IF($B20="","",$H20-$I20) -> -973131.24 | L20: =IF($B20="","",IFERROR(SUMIFS(_MainTable!$K$2:$K$2001,_MainTable!$F$2:$F$2001,$B20,_MainTable!$G$2:$G$2001,">="&Controls!$C$12,_MainTable!$G$2:$G$2001,"<="&EOMONTH(Controls!$C$7,0))/MIN(Controls!$C$9,Controls!$C$10),0)) -> 218321.6 | M20: =IF($B20="","",$L20*Controls!$C$11) -> 436643.21 | N20: =IF($B20="","",$I20+$M20) -> 1409774.4 | O20: =IF($B20="","",IFERROR($N20/$H20,0)) -> 0 | P20: =IF($B20="","",$H20-$N20) -> -1409774.4 | Q20: =IF($B20="","",IF($L20<=0,"n/a",IFERROR($K20/$L20,"n/a"))) -> -4.4573291 | R20: =IF($B20="","",IF(AND($H20=0,$I20=0),"⚪ No Activity",IF(AND($H20=0,COUNTIFS('SC Change Orders'!$B$2:$B$501,$B20,'SC Change Orders'!$C$2:$C$501,">="&Controls!$C$5,'SC Change Orders'!$C$2:$C$501,"<="&Controls!$C$6)=0),"⚪ No Funding on File",IF($H20=0,"🔴 Unfunded Spend",IF($I20>=$H20,"🔴 Over Budget",IF($N20>$H20,"🔴 Projected Shortfall",IF($J20>=Controls!$C$8,"🟡 Watch","🟢 On Track"))))))) -> ⚪ No Funding on File
A21: =IF($B21="","",IF((IFERROR(INDEX(_RefTable!$A$2:$A$501,MATCH($B21,_RefTable!$C$2:$C$501,0)),IFERROR(INDEX(_MainTable!$A$2:$A$2001,MATCH($B21,_MainTable!$F$2:$F$2001,0)),IFERROR(INDEX('SC Change Orders'!$A$2:$A$501,MATCH($B21,'SC Change Orders'!$B$2:$B$501,0)),"(unknown vendor)"))))&""="","—",(IFERROR(INDEX(_RefTable!$A$2:$A$501,MATCH($B21,_RefTable!$C$2:$C$501,0)),IFERROR(INDEX(_MainTable!$A$2:$A$2001,MATCH($B21,_MainTable!$F$2:$F$2001,0)),IFERROR(INDEX('SC Change Orders'!$A$2:$A$501,MATCH($B21,'SC Change Orders'!$B$2:$B$501,0)),"(unknown vendor)")))))) -> FMS INC | B21: =IFERROR(INDEX('PO Index'!$B$5:$B$84,17),"") -> 10410 | C21: =IF($B21="","",IF((IFERROR(INDEX(_RefTable!$B$2:$B$501,MATCH($B21,_RefTable!$C$2:$C$501,0))&IF(COUNTIF(_RefTable!$C$2:$C$501,$B21)>1," (+"&COUNTIF(_RefTable!$C$2:$C$501,$B21)-1&" more)",""),IFERROR(INDEX(_MainTable!$B$2:$B$2001,MATCH($B21,_MainTable!$F$2:$F$2001,0)),"")))&""="","—",(IFERROR(INDEX(_RefTable!$B$2:$B$501,MATCH($B21,_RefTable!$C$2:$C$501,0))&IF(COUNTIF(_RefTable!$C$2:$C$501,$B21)>1," (+"&COUNTIF(_RefTable!$C$2:$C$501,$B21)-1&" more)",""),IFERROR(INDEX(_MainTable!$B$2:$B$2001,MATCH($B21,_MainTable!$F$2:$F$2001,0)),""))))) -> 2BD | D21: =IF($B21="","",IF((IFERROR(INDEX(_RefTable!$E$2:$E$501,MATCH($B21,_RefTable!$C$2:$C$501,0)),IFERROR(INDEX(_MainTable!$C$2:$C$2001,MATCH($B21,_MainTable!$F$2:$F$2001,0)),"")))&""="","—",(IFERROR(INDEX(_RefTable!$E$2:$E$501,MATCH($B21,_RefTable!$C$2:$C$501,0)),IFERROR(INDEX(_MainTable!$C$2:$C$2001,MATCH($B21,_MainTable!$F$2:$F$2001,0)),""))))) -> Jake Reid | E21: =IF($B21="","",IF((IFERROR(INDEX(_RefTable!$F$2:$F$501,MATCH($B21,_RefTable!$C$2:$C$501,0)),IFERROR(INDEX(_MainTable!$D$2:$D$2001,MATCH($B21,_MainTable!$F$2:$F$2001,0)),"")))&""="","—",(IFERROR(INDEX(_RefTable!$F$2:$F$501,MATCH($B21,_RefTable!$C$2:$C$501,0)),IFERROR(INDEX(_MainTable!$D$2:$D$2001,MATCH($B21,_MainTable!$F$2:$F$2001,0)),""))))) -> Letisia Speelman | F21: =IF($B21="","",IFERROR(_xlfn.MINIFS('SC Change Orders'!$E$2:$E$501,'SC Change Orders'!$B$2:$B$501,$B21,'SC Change Orders'!$C$2:$C$501,">="&Controls!$C$5,'SC Change Orders'!$C$2:$C$501,"<="&Controls!$C$6),0)) -> 0 | G21: =IF($B21="","",SUMIFS('SC Change Orders'!$F$2:$F$501,'SC Change Orders'!$B$2:$B$501,$B21,'SC Change Orders'!$C$2:$C$501,">="&Controls!$C$5,'SC Change Orders'!$C$2:$C$501,"<="&Controls!$C$6)) -> 0 | H21: =IF($B21="","",$F21+$G21) -> 0 | I21: =IF($B21="","",SUMIFS(_MainTable!$K$2:$K$2001,_MainTable!$F$2:$F$2001,$B21,_MainTable!$G$2:$G$2001,">="&Controls!$C$5,_MainTable!$G$2:$G$2001,"<="&Controls!$C$6)) -> 313022.74 | J21: =IF($B21="","",IFERROR($I21/$H21,0)) -> 0 | K21: =IF($B21="","",$H21-$I21) -> -313022.74 | L21: =IF($B21="","",IFERROR(SUMIFS(_MainTable!$K$2:$K$2001,_MainTable!$F$2:$F$2001,$B21,_MainTable!$G$2:$G$2001,">="&Controls!$C$12,_MainTable!$G$2:$G$2001,"<="&EOMONTH(Controls!$C$7,0))/MIN(Controls!$C$9,Controls!$C$10),0)) -> 71552.47 | M21: =IF($B21="","",$L21*Controls!$C$11) -> 143104.94 | N21: =IF($B21="","",$I21+$M21) -> 456127.68 | O21: =IF($B21="","",IFERROR($N21/$H21,0)) -> 0 | P21: =IF($B21="","",$H21-$N21) -> -456127.68 | Q21: =IF($B21="","",IF($L21<=0,"n/a",IFERROR($K21/$L21,"n/a"))) -> -4.37473 | R21: =IF($B21="","",IF(AND($H21=0,$I21=0),"⚪ No Activity",IF(AND($H21=0,COUNTIFS('SC Change Orders'!$B$2:$B$501,$B21,'SC Change Orders'!$C$2:$C$501,">="&Controls!$C$5,'SC Change Orders'!$C$2:$C$501,"<="&Controls!$C$6)=0),"⚪ No Funding on File",IF($H21=0,"🔴 Unfunded Spend",IF($I21>=$H21,"🔴 Over Budget",IF($N21>$H21,"🔴 Projected Shortfall",IF($J21>=Controls!$C$8,"🟡 Watch","🟢 On Track"))))))) -> ⚪ No Funding on File
A22: =IF($B22="","",IF((IFERROR(INDEX(_RefTable!$A$2:$A$501,MATCH($B22,_RefTable!$C$2:$C$501,0)),IFERROR(INDEX(_MainTable!$A$2:$A$2001,MATCH($B22,_MainTable!$F$2:$F$2001,0)),IFERROR(INDEX('SC Change Orders'!$A$2:$A$501,MATCH($B22,'SC Change Orders'!$B$2:$B$501,0)),"(unknown vendor)"))))&""="","—",(IFERROR(INDEX(_RefTable!$A$2:$A$501,MATCH($B22,_RefTable!$C$2:$C$501,0)),IFERROR(INDEX(_MainTable!$A$2:$A$2001,MATCH($B22,_MainTable!$F$2:$F$2001,0)),IFERROR(INDEX('SC Change Orders'!$A$2:$A$501,MATCH($B22,'SC Change Orders'!$B$2:$B$501,0)),"(unknown vendor)")))))) -> RMP LLC | B22: =IFERROR(INDEX('PO Index'!$B$5:$B$84,18),"") -> 10415 | C22: =IF($B22="","",IF((IFERROR(INDEX(_RefTable!$B$2:$B$501,MATCH($B22,_RefTable!$C$2:$C$501,0))&IF(COUNTIF(_RefTable!$C$2:$C$501,$B22)>1," (+"&COUNTIF(_RefTable!$C$2:$C$501,$B22)-1&" more)",""),IFERROR(INDEX(_MainTable!$B$2:$B$2001,MATCH($B22,_MainTable!$F$2:$F$2001,0)),"")))&""="","—",(IFERROR(INDEX(_RefTable!$B$2:$B$501,MATCH($B22,_RefTable!$C$2:$C$501,0))&IF(COUNTIF(_RefTable!$C$2:$C$501,$B22)>1," (+"&COUNTIF(_RefTable!$C$2:$C$501,$B22)-1&" more)",""),IFERROR(INDEX(_MainTable!$B$2:$B$2001,MATCH($B22,_MainTable!$F$2:$F$2001,0)),""))))) -> 1BD | D22: =IF($B22="","",IF((IFERROR(INDEX(_RefTable!$E$2:$E$501,MATCH($B22,_RefTable!$C$2:$C$501,0)),IFERROR(INDEX(_MainTable!$C$2:$C$2001,MATCH($B22,_MainTable!$F$2:$F$2001,0)),"")))&""="","—",(IFERROR(INDEX(_RefTable!$E$2:$E$501,MATCH($B22,_RefTable!$C$2:$C$501,0)),IFERROR(INDEX(_MainTable!$C$2:$C$2001,MATCH($B22,_MainTable!$F$2:$F$2001,0)),""))))) -> Jake Reid | E22: =IF($B22="","",IF((IFERROR(INDEX(_RefTable!$F$2:$F$501,MATCH($B22,_RefTable!$C$2:$C$501,0)),IFERROR(INDEX(_MainTable!$D$2:$D$2001,MATCH($B22,_MainTable!$F$2:$F$2001,0)),"")))&""="","—",(IFERROR(INDEX(_RefTable!$F$2:$F$501,MATCH($B22,_RefTable!$C$2:$C$501,0)),IFERROR(INDEX(_MainTable!$D$2:$D$2001,MATCH($B22,_MainTable!$F$2:$F$2001,0)),""))))) -> Letisia Speelman | F22: =IF($B22="","",IFERROR(_xlfn.MINIFS('SC Change Orders'!$E$2:$E$501,'SC Change Orders'!$B$2:$B$501,$B22,'SC Change Orders'!$C$2:$C$501,">="&Controls!$C$5,'SC Change Orders'!$C$2:$C$501,"<="&Controls!$C$6),0)) -> 0 | G22: =IF($B22="","",SUMIFS('SC Change Orders'!$F$2:$F$501,'SC Change Orders'!$B$2:$B$501,$B22,'SC Change Orders'!$C$2:$C$501,">="&Controls!$C$5,'SC Change Orders'!$C$2:$C$501,"<="&Controls!$C$6)) -> 0 | H22: =IF($B22="","",$F22+$G22) -> 0 | I22: =IF($B22="","",SUMIFS(_MainTable!$K$2:$K$2001,_MainTable!$F$2:$F$2001,$B22,_MainTable!$G$2:$G$2001,">="&Controls!$C$5,_MainTable!$G$2:$G$2001,"<="&Controls!$C$6)) -> 261275.2 | J22: =IF($B22="","",IFERROR($I22/$H22,0)) -> 0 | K22: =IF($B22="","",$H22-$I22) -> -261275.2 | L22: =IF($B22="","",IFERROR(SUMIFS(_MainTable!$K$2:$K$2001,_MainTable!$F$2:$F$2001,$B22,_MainTable!$G$2:$G$2001,">="&Controls!$C$12,_MainTable!$G$2:$G$2001,"<="&EOMONTH(Controls!$C$7,0))/MIN(Controls!$C$9,Controls!$C$10),0)) -> 49711.247 | M22: =IF($B22="","",$L22*Controls!$C$11) -> 99422.493 | N22: =IF($B22="","",$I22+$M22) -> 360697.69 | O22: =IF($B22="","",IFERROR($N22/$H22,0)) -> 0 | P22: =IF($B22="","",$H22-$N22) -> -360697.69 | Q22: =IF($B22="","",IF($L22<=0,"n/a",IFERROR($K22/$L22,"n/a"))) -> -5.2558569 | R22: =IF($B22="","",IF(AND($H22=0,$I22=0),"⚪ No Activity",IF(AND($H22=0,COUNTIFS('SC Change Orders'!$B$2:$B$501,$B22,'SC Change Orders'!$C$2:$C$501,">="&Controls!$C$5,'SC Change Orders'!$C$2:$C$501,"<="&Controls!$C$6)=0),"⚪ No Funding on File",IF($H22=0,"🔴 Unfunded Spend",IF($I22>=$H22,"🔴 Over Budget",IF($N22>$H22,"🔴 Projected Shortfall",IF($J22>=Controls!$C$8,"🟡 Watch","🟢 On Track"))))))) -> ⚪ No Funding on File
A23: =IF($B23="","",IF((IFERROR(INDEX(_RefTable!$A$2:$A$501,MATCH($B23,_RefTable!$C$2:$C$501,0)),IFERROR(INDEX(_MainTable!$A$2:$A$2001,MATCH($B23,_MainTable!$F$2:$F$2001,0)),IFERROR(INDEX('SC Change Orders'!$A$2:$A$501,MATCH($B23,'SC Change Orders'!$B$2:$B$501,0)),"(unknown vendor)"))))&""="","—",(IFERROR(INDEX(_RefTable!$A$2:$A$501,MATCH($B23,_RefTable!$C$2:$C$501,0)),IFERROR(INDEX(_MainTable!$A$2:$A$2001,MATCH($B23,_MainTable!$F$2:$F$2001,0)),IFERROR(INDEX('SC Change Orders'!$A$2:$A$501,MATCH($B23,'SC Change Orders'!$B$2:$B$501,0)),"(unknown vendor)")))))) -> RMP LLC | B23: =IFERROR(INDEX('PO Index'!$B$5:$B$84,19),"") -> 10417 | C23: =IF($B23="","",IF((IFERROR(INDEX(_RefTable!$B$2:$B$501,MATCH($B23,_RefTable!$C$2:$C$501,0))&IF(COUNTIF(_RefTable!$C$2:$C$501,$B23)>1," (+"&COUNTIF(_RefTable!$C$2:$C$501,$B23)-1&" more)",""),IFERROR(INDEX(_MainTable!$B$2:$B$2001,MATCH($B23,_MainTable!$F$2:$F$2001,0)),"")))&""="","—",(IFERROR(INDEX(_RefTable!$B$2:$B$501,MATCH($B23,_RefTable!$C$2:$C$501,0))&IF(COUNTIF(_RefTable!$C$2:$C$501,$B23)>1," (+"&COUNTIF(_RefTable!$C$2:$C$501,$B23)-1&" more)",""),IFERROR(INDEX(_MainTable!$B$2:$B$2001,MATCH($B23,_MainTable!$F$2:$F$2001,0)),""))))) -> Early Out (+1 more) | D23: =IF($B23="","",IF((IFERROR(INDEX(_RefTable!$E$2:$E$501,MATCH($B23,_RefTable!$C$2:$C$501,0)),IFERROR(INDEX(_MainTable!$C$2:$C$2001,MATCH($B23,_MainTable!$F$2:$F$2001,0)),"")))&""="","—",(IFERROR(INDEX(_RefTable!$E$2:$E$501,MATCH($B23,_RefTable!$C$2:$C$501,0)),IFERROR(INDEX(_MainTable!$C$2:$C$2001,MATCH($B23,_MainTable!$F$2:$F$2001,0)),""))))) -> Jake Reid | E23: =IF($B23="","",IF((IFERROR(INDEX(_RefTable!$F$2:$F$501,MATCH($B23,_RefTable!$C$2:$C$501,0)),IFERROR(INDEX(_MainTable!$D$2:$D$2001,MATCH($B23,_MainTable!$F$2:$F$2001,0)),"")))&""="","—",(IFERROR(INDEX(_RefTable!$F$2:$F$501,MATCH($B23,_RefTable!$C$2:$C$501,0)),IFERROR(INDEX(_MainTable!$D$2:$D$2001,MATCH($B23,_MainTable!$F$2:$F$2001,0)),""))))) -> Letisia Speelman | F23: =IF($B23="","",IFERROR(_xlfn.MINIFS('SC Change Orders'!$E$2:$E$501,'SC Change Orders'!$B$2:$B$501,$B23,'SC Change Orders'!$C$2:$C$501,">="&Controls!$C$5,'SC Change Orders'!$C$2:$C$501,"<="&Controls!$C$6),0)) -> 0 | G23: =IF($B23="","",SUMIFS('SC Change Orders'!$F$2:$F$501,'SC Change Orders'!$B$2:$B$501,$B23,'SC Change Orders'!$C$2:$C$501,">="&Controls!$C$5,'SC Change Orders'!$C$2:$C$501,"<="&Controls!$C$6)) -> 0 | H23: =IF($B23="","",$F23+$G23) -> 0 | I23: =IF($B23="","",SUMIFS(_MainTable!$K$2:$K$2001,_MainTable!$F$2:$F$2001,$B23,_MainTable!$G$2:$G$2001,">="&Controls!$C$5,_MainTable!$G$2:$G$2001,"<="&Controls!$C$6)) -> 737789.45 | J23: =IF($B23="","",IFERROR($I23/$H23,0)) -> 0 | K23: =IF($B23="","",$H23-$I23) -> -737789.45 | L23: =IF($B23="","",IFERROR(SUMIFS(_MainTable!$K$2:$K$2001,_MainTable!$F$2:$F$2001,$B23,_MainTable!$G$2:$G$2001,">="&Controls!$C$12,_MainTable!$G$2:$G$2001,"<="&EOMONTH(Controls!$C$7,0))/MIN(Controls!$C$9,Controls!$C$10),0)) -> 155839.9 | M23: =IF($B23="","",$L23*Controls!$C$11) -> 311679.81 | N23: =IF($B23="","",$I23+$M23) -> 1049469.3 | O23: =IF($B23="","",IFERROR($N23/$H23,0)) -> 0 | P23: =IF($B23="","",$H23-$N23) -> -1049469.3 | Q23: =IF($B23="","",IF($L23<=0,"n/a",IFERROR($K23/$L23,"n/a"))) -> -4.7342782 | R23: =IF($B23="","",IF(AND($H23=0,$I23=0),"⚪ No Activity",IF(AND($H23=0,COUNTIFS('SC Change Orders'!$B$2:$B$501,$B23,'SC Change Orders'!$C$2:$C$501,">="&Controls!$C$5,'SC Change Orders'!$C$2:$C$501,"<="&Controls!$C$6)=0),"⚪ No Funding on File",IF($H23=0,"🔴 Unfunded Spend",IF($I23>=$H23,"🔴 Over Budget",IF($N23>$H23,"🔴 Projected Shortfall",IF($J23>=Controls!$C$8,"🟡 Watch","🟢 On Track"))))))) -> ⚪ No Funding on File
A24: =IF($B24="","",IF((IFERROR(INDEX(_RefTable!$A$2:$A$501,MATCH($B24,_RefTable!$C$2:$C$501,0)),IFERROR(INDEX(_MainTable!$A$2:$A$2001,MATCH($B24,_MainTable!$F$2:$F$2001,0)),IFERROR(INDEX('SC Change Orders'!$A$2:$A$501,MATCH($B24,'SC Change Orders'!$B$2:$B$501,0)),"(unknown vendor)"))))&""="","—",(IFERROR(INDEX(_RefTable!$A$2:$A$501,MATCH($B24,_RefTable!$C$2:$C$501,0)),IFERROR(INDEX(_MainTable!$A$2:$A$2001,MATCH($B24,_MainTable!$F$2:$F$2001,0)),IFERROR(INDEX('SC Change Orders'!$A$2:$A$501,MATCH($B24,'SC Change Orders'!$B$2:$B$501,0)),"(unknown vendor)")))))) -> RMP LLC | B24: =IFERROR(INDEX('PO Index'!$B$5:$B$84,20),"") -> 10418 | C24: =IF($B24="","",IF((IFERROR(INDEX(_RefTable!$B$2:$B$501,MATCH($B24,_RefTable!$C$2:$C$501,0))&IF(COUNTIF(_RefTable!$C$2:$C$501,$B24)>1," (+"&COUNTIF(_RefTable!$C$2:$C$501,$B24)-1&" more)",""),IFERROR(INDEX(_MainTable!$B$2:$B$2001,MATCH($B24,_MainTable!$F$2:$F$2001,0)),"")))&""="","—",(IFERROR(INDEX(_RefTable!$B$2:$B$501,MATCH($B24,_RefTable!$C$2:$C$501,0))&IF(COUNTIF(_RefTable!$C$2:$C$501,$B24)>1," (+"&COUNTIF(_RefTable!$C$2:$C$501,$B24)-1&" more)",""),IFERROR(INDEX(_MainTable!$B$2:$B$2001,MATCH($B24,_MainTable!$F$2:$F$2001,0)),""))))) -> Postage | D24: =IF($B24="","",IF((IFERROR(INDEX(_RefTable!$E$2:$E$501,MATCH($B24,_RefTable!$C$2:$C$501,0)),IFERROR(INDEX(_MainTable!$C$2:$C$2001,MATCH($B24,_MainTable!$F$2:$F$2001,0)),"")))&""="","—",(IFERROR(INDEX(_RefTable!$E$2:$E$501,MATCH($B24,_RefTable!$C$2:$C$501,0)),IFERROR(INDEX(_MainTable!$C$2:$C$2001,MATCH($B24,_MainTable!$F$2:$F$2001,0)),""))))) -> Jake Reid | E24: =IF($B24="","",IF((IFERROR(INDEX(_RefTable!$F$2:$F$501,MATCH($B24,_RefTable!$C$2:$C$501,0)),IFERROR(INDEX(_MainTable!$D$2:$D$2001,MATCH($B24,_MainTable!$F$2:$F$2001,0)),"")))&""="","—",(IFERROR(INDEX(_RefTable!$F$2:$F$501,MATCH($B24,_RefTable!$C$2:$C$501,0)),IFERROR(INDEX(_MainTable!$D$2:$D$2001,MATCH($B24,_MainTable!$F$2:$F$2001,0)),""))))) -> Letisia Speelman | F24: =IF($B24="","",IFERROR(_xlfn.MINIFS('SC Change Orders'!$E$2:$E$501,'SC Change Orders'!$B$2:$B$501,$B24,'SC Change Orders'!$C$2:$C$501,">="&Controls!$C$5,'SC Change Orders'!$C$2:$C$501,"<="&Controls!$C$6),0)) -> 0 | G24: =IF($B24="","",SUMIFS('SC Change Orders'!$F$2:$F$501,'SC Change Orders'!$B$2:$B$501,$B24,'SC Change Orders'!$C$2:$C$501,">="&Controls!$C$5,'SC Change Orders'!$C$2:$C$501,"<="&Controls!$C$6)) -> 0 | H24: =IF($B24="","",$F24+$G24) -> 0 | I24: =IF($B24="","",SUMIFS(_MainTable!$K$2:$K$2001,_MainTable!$F$2:$F$2001,$B24,_MainTable!$G$2:$G$2001,">="&Controls!$C$5,_MainTable!$G$2:$G$2001,"<="&Controls!$C$6)) -> 333203.62 | J24: =IF($B24="","",IFERROR($I24/$H24,0)) -> 0 | K24: =IF($B24="","",$H24-$I24) -> -333203.62 | L24: =IF($B24="","",IFERROR(SUMIFS(_MainTable!$K$2:$K$2001,_MainTable!$F$2:$F$2001,$B24,_MainTable!$G$2:$G$2001,">="&Controls!$C$12,_MainTable!$G$2:$G$2001,"<="&EOMONTH(Controls!$C$7,0))/MIN(Controls!$C$9,Controls!$C$10),0)) -> 111067.87 | M24: =IF($B24="","",$L24*Controls!$C$11) -> 222135.75 | N24: =IF($B24="","",$I24+$M24) -> 555339.37 | O24: =IF($B24="","",IFERROR($N24/$H24,0)) -> 0 | P24: =IF($B24="","",$H24-$N24) -> -555339.37 | Q24: =IF($B24="","",IF($L24<=0,"n/a",IFERROR($K24/$L24,"n/a"))) -> -3 | R24: =IF($B24="","",IF(AND($H24=0,$I24=0),"⚪ No Activity",IF(AND($H24=0,COUNTIFS('SC Change Orders'!$B$2:$B$501,$B24,'SC Change Orders'!$C$2:$C$501,">="&Controls!$C$5,'SC Change Orders'!$C$2:$C$501,"<="&Controls!$C$6)=0),"⚪ No Funding on File",IF($H24=0,"🔴 Unfunded Spend",IF($I24>=$H24,"🔴 Over Budget",IF($N24>$H24,"🔴 Projected Shortfall",IF($J24>=Controls!$C$8,"🟡 Watch","🟢 On Track"))))))) -> ⚪ No Funding on File
A25: =IF($B25="","",IF((IFERROR(INDEX(_RefTable!$A$2:$A$501,MATCH($B25,_RefTable!$C$2:$C$501,0)),IFERROR(INDEX(_MainTable!$A$2:$A$2001,MATCH($B25,_MainTable!$F$2:$F$2001,0)),IFERROR(INDEX('SC Change Orders'!$A$2:$A$501,MATCH($B25,'SC Change Orders'!$B$2:$B$501,0)),"(unknown vendor)"))))&""="","—",(IFERROR(INDEX(_RefTable!$A$2:$A$501,MATCH($B25,_RefTable!$C$2:$C$501,0)),IFERROR(INDEX(_MainTable!$A$2:$A$2001,MATCH($B25,_MainTable!$F$2:$F$2001,0)),IFERROR(INDEX('SC Change Orders'!$A$2:$A$501,MATCH($B25,'SC Change Orders'!$B$2:$B$501,0)),"(unknown vendor)")))))) -> RMP LLC | B25: =IFERROR(INDEX('PO Index'!$B$5:$B$84,21),"") -> 10419 | C25: =IF($B25="","",IF((IFERROR(INDEX(_RefTable!$B$2:$B$501,MATCH($B25,_RefTable!$C$2:$C$501,0))&IF(COUNTIF(_RefTable!$C$2:$C$501,$B25)>1," (+"&COUNTIF(_RefTable!$C$2:$C$501,$B25)-1&" more)",""),IFERROR(INDEX(_MainTable!$B$2:$B$2001,MATCH($B25,_MainTable!$F$2:$F$2001,0)),"")))&""="","—",(IFERROR(INDEX(_RefTable!$B$2:$B$501,MATCH($B25,_RefTable!$C$2:$C$501,0))&IF(COUNTIF(_RefTable!$C$2:$C$501,$B25)>1," (+"&COUNTIF(_RefTable!$C$2:$C$501,$B25)-1&" more)",""),IFERROR(INDEX(_MainTable!$B$2:$B$2001,MATCH($B25,_MainTable!$F$2:$F$2001,0)),""))))) -> Production | D25: =IF($B25="","",IF((IFERROR(INDEX(_RefTable!$E$2:$E$501,MATCH($B25,_RefTable!$C$2:$C$501,0)),IFERROR(INDEX(_MainTable!$C$2:$C$2001,MATCH($B25,_MainTable!$F$2:$F$2001,0)),"")))&""="","—",(IFERROR(INDEX(_RefTable!$E$2:$E$501,MATCH($B25,_RefTable!$C$2:$C$501,0)),IFERROR(INDEX(_MainTable!$C$2:$C$2001,MATCH($B25,_MainTable!$F$2:$F$2001,0)),""))))) -> Jake Reid | E25: =IF($B25="","",IF((IFERROR(INDEX(_RefTable!$F$2:$F$501,MATCH($B25,_RefTable!$C$2:$C$501,0)),IFERROR(INDEX(_MainTable!$D$2:$D$2001,MATCH($B25,_MainTable!$F$2:$F$2001,0)),"")))&""="","—",(IFERROR(INDEX(_RefTable!$F$2:$F$501,MATCH($B25,_RefTable!$C$2:$C$501,0)),IFERROR(INDEX(_MainTable!$D$2:$D$2001,MATCH($B25,_MainTable!$F$2:$F$2001,0)),""))))) -> Letisia Speelman | F25: =IF($B25="","",IFERROR(_xlfn.MINIFS('SC Change Orders'!$E$2:$E$501,'SC Change Orders'!$B$2:$B$501,$B25,'SC Change Orders'!$C$2:$C$501,">="&Controls!$C$5,'SC Change Orders'!$C$2:$C$501,"<="&Controls!$C$6),0)) -> 0 | G25: =IF($B25="","",SUMIFS('SC Change Orders'!$F$2:$F$501,'SC Change Orders'!$B$2:$B$501,$B25,'SC Change Orders'!$C$2:$C$501,">="&Controls!$C$5,'SC Change Orders'!$C$2:$C$501,"<="&Controls!$C$6)) -> 0 | H25: =IF($B25="","",$F25+$G25) -> 0 | I25: =IF($B25="","",SUMIFS(_MainTable!$K$2:$K$2001,_MainTable!$F$2:$F$2001,$B25,_MainTable!$G$2:$G$2001,">="&Controls!$C$5,_MainTable!$G$2:$G$2001,"<="&Controls!$C$6)) -> 144946.08 | J25: =IF($B25="","",IFERROR($I25/$H25,0)) -> 0 | K25: =IF($B25="","",$H25-$I25) -> -144946.08 | L25: =IF($B25="","",IFERROR(SUMIFS(_MainTable!$K$2:$K$2001,_MainTable!$F$2:$F$2001,$B25,_MainTable!$G$2:$G$2001,">="&Controls!$C$12,_MainTable!$G$2:$G$2001,"<="&EOMONTH(Controls!$C$7,0))/MIN(Controls!$C$9,Controls!$C$10),0)) -> 48315.36 | M25: =IF($B25="","",$L25*Controls!$C$11) -> 96630.72 | N25: =IF($B25="","",$I25+$M25) -> 241576.8 | O25: =IF($B25="","",IFERROR($N25/$H25,0)) -> 0 | P25: =IF($B25="","",$H25-$N25) -> -241576.8 | Q25: =IF($B25="","",IF($L25<=0,"n/a",IFERROR($K25/$L25,"n/a"))) -> -3 | R25: =IF($B25="","",IF(AND($H25=0,$I25=0),"⚪ No Activity",IF(AND($H25=0,COUNTIFS('SC Change Orders'!$B$2:$B$501,$B25,'SC Change Orders'!$C$2:$C$501,">="&Controls!$C$5,'SC Change Orders'!$C$2:$C$501,"<="&Controls!$C$6)=0),"⚪ No Funding on File",IF($H25=0,"🔴 Unfunded Spend",IF($I25>=$H25,"🔴 Over Budget",IF($N25>$H25,"🔴 Projected Shortfall",IF($J25>=Controls!$C$8,"🟡 Watch","🟢 On Track"))))))) -> ⚪ No Funding on File
A26: =IF($B26="","",IF((IFERROR(INDEX(_RefTable!$A$2:$A$501,MATCH($B26,_RefTable!$C$2:$C$501,0)),IFERROR(INDEX(_MainTable!$A$2:$A$2001,MATCH($B26,_MainTable!$F$2:$F$2001,0)),IFERROR(INDEX('SC Change Orders'!$A$2:$A$501,MATCH($B26,'SC Change Orders'!$B$2:$B$501,0)),"(unknown vendor)"))))&""="","—",(IFERROR(INDEX(_RefTable!$A$2:$A$501,MATCH($B26,_RefTable!$C$2:$C$501,0)),IFERROR(INDEX(_MainTable!$A$2:$A$2001,MATCH($B26,_MainTable!$F$2:$F$2001,0)),IFERROR(INDEX('SC Change Orders'!$A$2:$A$501,MATCH($B26,'SC Change Orders'!$B$2:$B$501,0)),"(unknown vendor)")))))) -> RMP LLC | B26: =IFERROR(INDEX('PO Index'!$B$5:$B$84,22),"") -> 10420 | C26: =IF($B26="","",IF((IFERROR(INDEX(_RefTable!$B$2:$B$501,MATCH($B26,_RefTable!$C$2:$C$501,0))&IF(COUNTIF(_RefTable!$C$2:$C$501,$B26)>1," (+"&COUNTIF(_RefTable!$C$2:$C$501,$B26)-1&" more)",""),IFERROR(INDEX(_MainTable!$B$2:$B$2001,MATCH($B26,_MainTable!$F$2:$F$2001,0)),"")))&""="","—",(IFERROR(INDEX(_RefTable!$B$2:$B$501,MATCH($B26,_RefTable!$C$2:$C$501,0))&IF(COUNTIF(_RefTable!$C$2:$C$501,$B26)>1," (+"&COUNTIF(_RefTable!$C$2:$C$501,$B26)-1&" more)",""),IFERROR(INDEX(_MainTable!$B$2:$B$2001,MATCH($B26,_MainTable!$F$2:$F$2001,0)),""))))) -> Storage | D26: =IF($B26="","",IF((IFERROR(INDEX(_RefTable!$E$2:$E$501,MATCH($B26,_RefTable!$C$2:$C$501,0)),IFERROR(INDEX(_MainTable!$C$2:$C$2001,MATCH($B26,_MainTable!$F$2:$F$2001,0)),"")))&""="","—",(IFERROR(INDEX(_RefTable!$E$2:$E$501,MATCH($B26,_RefTable!$C$2:$C$501,0)),IFERROR(INDEX(_MainTable!$C$2:$C$2001,MATCH($B26,_MainTable!$F$2:$F$2001,0)),""))))) -> Jake Reid | E26: =IF($B26="","",IF((IFERROR(INDEX(_RefTable!$F$2:$F$501,MATCH($B26,_RefTable!$C$2:$C$501,0)),IFERROR(INDEX(_MainTable!$D$2:$D$2001,MATCH($B26,_MainTable!$F$2:$F$2001,0)),"")))&""="","—",(IFERROR(INDEX(_RefTable!$F$2:$F$501,MATCH($B26,_RefTable!$C$2:$C$501,0)),IFERROR(INDEX(_MainTable!$D$2:$D$2001,MATCH($B26,_MainTable!$F$2:$F$2001,0)),""))))) -> Letisia Speelman | F26: =IF($B26="","",IFERROR(_xlfn.MINIFS('SC Change Orders'!$E$2:$E$501,'SC Change Orders'!$B$2:$B$501,$B26,'SC Change Orders'!$C$2:$C$501,">="&Controls!$C$5,'SC Change Orders'!$C$2:$C$501,"<="&Controls!$C$6),0)) -> 0 | G26: =IF($B26="","",SUMIFS('SC Change Orders'!$F$2:$F$501,'SC Change Orders'!$B$2:$B$501,$B26,'SC Change Orders'!$C$2:$C$501,">="&Controls!$C$5,'SC Change Orders'!$C$2:$C$501,"<="&Controls!$C$6)) -> 0 | H26: =IF($B26="","",$F26+$G26) -> 0 | I26: =IF($B26="","",SUMIFS(_MainTable!$K$2:$K$2001,_MainTable!$F$2:$F$2001,$B26,_MainTable!$G$2:$G$2001,">="&Controls!$C$5,_MainTable!$G$2:$G$2001,"<="&Controls!$C$6)) -> 600 | J26: =IF($B26="","",IFERROR($I26/$H26,0)) -> 0 | K26: =IF($B26="","",$H26-$I26) -> -600 | L26: =IF($B26="","",IFERROR(SUMIFS(_MainTable!$K$2:$K$2001,_MainTable!$F$2:$F$2001,$B26,_MainTable!$G$2:$G$2001,">="&Controls!$C$12,_MainTable!$G$2:$G$2001,"<="&EOMONTH(Controls!$C$7,0))/MIN(Controls!$C$9,Controls!$C$10),0)) -> 200 | M26: =IF($B26="","",$L26*Controls!$C$11) -> 400 | N26: =IF($B26="","",$I26+$M26) -> 1000 | O26: =IF($B26="","",IFERROR($N26/$H26,0)) -> 0 | P26: =IF($B26="","",$H26-$N26) -> -1000 | Q26: =IF($B26="","",IF($L26<=0,"n/a",IFERROR($K26/$L26,"n/a"))) -> -3 | R26: =IF($B26="","",IF(AND($H26=0,$I26=0),"⚪ No Activity",IF(AND($H26=0,COUNTIFS('SC Change Orders'!$B$2:$B$501,$B26,'SC Change Orders'!$C$2:$C$501,">="&Controls!$C$5,'SC Change Orders'!$C$2:$C$501,"<="&Controls!$C$6)=0),"⚪ No Funding on File",IF($H26=0,"🔴 Unfunded Spend",IF($I26>=$H26,"🔴 Over Budget",IF($N26>$H26,"🔴 Projected Shortfall",IF($J26>=Controls!$C$8,"🟡 Watch","🟢 On Track"))))))) -> ⚪ No Funding on File
A27: =IF($B27="","",IF((IFERROR(INDEX(_RefTable!$A$2:$A$501,MATCH($B27,_RefTable!$C$2:$C$501,0)),IFERROR(INDEX(_MainTable!$A$2:$A$2001,MATCH($B27,_MainTable!$F$2:$F$2001,0)),IFERROR(INDEX('SC Change Orders'!$A$2:$A$501,MATCH($B27,'SC Change Orders'!$B$2:$B$501,0)),"(unknown vendor)"))))&""="","—",(IFERROR(INDEX(_RefTable!$A$2:$A$501,MATCH($B27,_RefTable!$C$2:$C$501,0)),IFERROR(INDEX(_MainTable!$A$2:$A$2001,MATCH($B27,_MainTable!$F$2:$F$2001,0)),IFERROR(INDEX('SC Change Orders'!$A$2:$A$501,MATCH($B27,'SC Change Orders'!$B$2:$B$501,0)),"(unknown vendor)")))))) -> REVSPRING INC | B27: =IFERROR(INDEX('PO Index'!$B$5:$B$84,23),"") -> 10423 | C27: =IF($B27="","",IF((IFERROR(INDEX(_RefTable!$B$2:$B$501,MATCH($B27,_RefTable!$C$2:$C$501,0))&IF(COUNTIF(_RefTable!$C$2:$C$501,$B27)>1," (+"&COUNTIF(_RefTable!$C$2:$C$501,$B27)-1&" more)",""),IFERROR(INDEX(_MainTable!$B$2:$B$2001,MATCH($B27,_MainTable!$F$2:$F$2001,0)),"")))&""="","—",(IFERROR(INDEX(_RefTable!$B$2:$B$501,MATCH($B27,_RefTable!$C$2:$C$501,0))&IF(COUNTIF(_RefTable!$C$2:$C$501,$B27)>1," (+"&COUNTIF(_RefTable!$C$2:$C$501,$B27)-1&" more)",""),IFERROR(INDEX(_MainTable!$B$2:$B$2001,MATCH($B27,_MainTable!$F$2:$F$2001,0)),""))))) -> Payment processing- IVR | D27: =IF($B27="","",IF((IFERROR(INDEX(_RefTable!$E$2:$E$501,MATCH($B27,_RefTable!$C$2:$C$501,0)),IFERROR(INDEX(_MainTable!$C$2:$C$2001,MATCH($B27,_MainTable!$F$2:$F$2001,0)),"")))&""="","—",(IFERROR(INDEX(_RefTable!$E$2:$E$501,MATCH($B27,_RefTable!$C$2:$C$501,0)),IFERROR(INDEX(_MainTable!$C$2:$C$2001,MATCH($B27,_MainTable!$F$2:$F$2001,0)),""))))) -> Jake Reid | E27: =IF($B27="","",IF((IFERROR(INDEX(_RefTable!$F$2:$F$501,MATCH($B27,_RefTable!$C$2:$C$501,0)),IFERROR(INDEX(_MainTable!$D$2:$D$2001,MATCH($B27,_MainTable!$F$2:$F$2001,0)),"")))&""="","—",(IFERROR(INDEX(_RefTable!$F$2:$F$501,MATCH($B27,_RefTable!$C$2:$C$501,0)),IFERROR(INDEX(_MainTable!$D$2:$D$2001,MATCH($B27,_MainTable!$F$2:$F$2001,0)),""))))) -> Letisia Speelman | F27: =IF($B27="","",IFERROR(_xlfn.MINIFS('SC Change Orders'!$E$2:$E$501,'SC Change Orders'!$B$2:$B$501,$B27,'SC Change Orders'!$C$2:$C$501,">="&Controls!$C$5,'SC Change Orders'!$C$2:$C$501,"<="&Controls!$C$6),0)) -> 0 | G27: =IF($B27="","",SUMIFS('SC Change Orders'!$F$2:$F$501,'SC Change Orders'!$B$2:$B$501,$B27,'SC Change Orders'!$C$2:$C$501,">="&Controls!$C$5,'SC Change Orders'!$C$2:$C$501,"<="&Controls!$C$6)) -> 0 | H27: =IF($B27="","",$F27+$G27) -> 0 | I27: =IF($B27="","",SUMIFS(_MainTable!$K$2:$K$2001,_MainTable!$F$2:$F$2001,$B27,_MainTable!$G$2:$G$2001,">="&Controls!$C$5,_MainTable!$G$2:$G$2001,"<="&Controls!$C$6)) -> 48227.35 | J27: =IF($B27="","",IFERROR($I27/$H27,0)) -> 0 | K27: =IF($B27="","",$H27-$I27) -> -48227.35 | L27: =IF($B27="","",IFERROR(SUMIFS(_MainTable!$K$2:$K$2001,_MainTable!$F$2:$F$2001,$B27,_MainTable!$G$2:$G$2001,">="&Controls!$C$12,_MainTable!$G$2:$G$2001,"<="&EOMONTH(Controls!$C$7,0))/MIN(Controls!$C$9,Controls!$C$10),0)) -> 13040.033 | M27: =IF($B27="","",$L27*Controls!$C$11) -> 26080.067 | N27: =IF($B27="","",$I27+$M27) -> 74307.417 | O27: =IF($B27="","",IFERROR($N27/$H27,0)) -> 0 | P27: =IF($B27="","",$H27-$N27) -> -74307.417 | Q27: =IF($B27="","",IF($L27<=0,"n/a",IFERROR($K27/$L27,"n/a"))) -> -3.698407 | R27: =IF($B27="","",IF(AND($H27=0,$I27=0),"⚪ No Activity",IF(AND($H27=0,COUNTIFS('SC Change Orders'!$B$2:$B$501,$B27,'SC Change Orders'!$C$2:$C$501,">="&Controls!$C$5,'SC Change Orders'!$C$2:$C$501,"<="&Controls!$C$6)=0),"⚪ No Funding on File",IF($H27=0,"🔴 Unfunded Spend",IF($I27>=$H27,"🔴 Over Budget",IF($N27>$H27,"🔴 Projected Shortfall",IF($J27>=Controls!$C$8,"🟡 Watch","🟢 On Track"))))))) -> ⚪ No Funding on File
A28: =IF($B28="","",IF((IFERROR(INDEX(_RefTable!$A$2:$A$501,MATCH($B28,_RefTable!$C$2:$C$501,0)),IFERROR(INDEX(_MainTable!$A$2:$A$2001,MATCH($B28,_MainTable!$F$2:$F$2001,0)),IFERROR(INDEX('SC Change Orders'!$A$2:$A$501,MATCH($B28,'SC Change Orders'!$B$2:$B$501,0)),"(unknown vendor)"))))&""="","—",(IFERROR(INDEX(_RefTable!$A$2:$A$501,MATCH($B28,_RefTable!$C$2:$C$501,0)),IFERROR(INDEX(_MainTable!$A$2:$A$2001,MATCH($B28,_MainTable!$F$2:$F$2001,0)),IFERROR(INDEX('SC Change Orders'!$A$2:$A$501,MATCH($B28,'SC Change Orders'!$B$2:$B$501,0)),"(unknown vendor)")))))) -> REVSPRING INC | B28: =IFERROR(INDEX('PO Index'!$B$5:$B$84,24),"") -> 10424 | C28: =IF($B28="","",IF((IFERROR(INDEX(_RefTable!$B$2:$B$501,MATCH($B28,_RefTable!$C$2:$C$501,0))&IF(COUNTIF(_RefTable!$C$2:$C$501,$B28)>1," (+"&COUNTIF(_RefTable!$C$2:$C$501,$B28)-1&" more)",""),IFERROR(INDEX(_MainTable!$B$2:$B$2001,MATCH($B28,_MainTable!$F$2:$F$2001,0)),"")))&""="","—",(IFERROR(INDEX(_RefTable!$B$2:$B$501,MATCH($B28,_RefTable!$C$2:$C$501,0))&IF(COUNTIF(_RefTable!$C$2:$C$501,$B28)>1," (+"&COUNTIF(_RefTable!$C$2:$C$501,$B28)-1&" more)",""),IFERROR(INDEX(_MainTable!$B$2:$B$2001,MATCH($B28,_MainTable!$F$2:$F$2001,0)),""))))) -> Payment processing- Persona Pay | D28: =IF($B28="","",IF((IFERROR(INDEX(_RefTable!$E$2:$E$501,MATCH($B28,_RefTable!$C$2:$C$501,0)),IFERROR(INDEX(_MainTable!$C$2:$C$2001,MATCH($B28,_MainTable!$F$2:$F$2001,0)),"")))&""="","—",(IFERROR(INDEX(_RefTable!$E$2:$E$501,MATCH($B28,_RefTable!$C$2:$C$501,0)),IFERROR(INDEX(_MainTable!$C$2:$C$2001,MATCH($B28,_MainTable!$F$2:$F$2001,0)),""))))) -> Jake Reid | E28: =IF($B28="","",IF((IFERROR(INDEX(_RefTable!$F$2:$F$501,MATCH($B28,_RefTable!$C$2:$C$501,0)),IFERROR(INDEX(_MainTable!$D$2:$D$2001,MATCH($B28,_MainTable!$F$2:$F$2001,0)),"")))&""="","—",(IFERROR(INDEX(_RefTable!$F$2:$F$501,MATCH($B28,_RefTable!$C$2:$C$501,0)),IFERROR(INDEX(_MainTable!$D$2:$D$2001,MATCH($B28,_MainTable!$F$2:$F$2001,0)),""))))) -> Letisia Speelman | F28: =IF($B28="","",IFERROR(_xlfn.MINIFS('SC Change Orders'!$E$2:$E$501,'SC Change Orders'!$B$2:$B$501,$B28,'SC Change Orders'!$C$2:$C$501,">="&Controls!$C$5,'SC Change Orders'!$C$2:$C$501,"<="&Controls!$C$6),0)) -> 0 | G28: =IF($B28="","",SUMIFS('SC Change Orders'!$F$2:$F$501,'SC Change Orders'!$B$2:$B$501,$B28,'SC Change Orders'!$C$2:$C$501,">="&Controls!$C$5,'SC Change Orders'!$C$2:$C$501,"<="&Controls!$C$6)) -> 0 | H28: =IF($B28="","",$F28+$G28) -> 0 | I28: =IF($B28="","",SUMIFS(_MainTable!$K$2:$K$2001,_MainTable!$F$2:$F$2001,$B28,_MainTable!$G$2:$G$2001,">="&Controls!$C$5,_MainTable!$G$2:$G$2001,"<="&Controls!$C$6)) -> 35307.06 | J28: =IF($B28="","",IFERROR($I28/$H28,0)) -> 0 | K28: =IF($B28="","",$H28-$I28) -> -35307.06 | L28: =IF($B28="","",IFERROR(SUMIFS(_MainTable!$K$2:$K$2001,_MainTable!$F$2:$F$2001,$B28,_MainTable!$G$2:$G$2001,">="&Controls!$C$12,_MainTable!$G$2:$G$2001,"<="&EOMONTH(Controls!$C$7,0))/MIN(Controls!$C$9,Controls!$C$10),0)) -> 7846.0133 | M28: =IF($B28="","",$L28*Controls!$C$11) -> 15692.027 | N28: =IF($B28="","",$I28+$M28) -> 50999.087 | O28: =IF($B28="","",IFERROR($N28/$H28,0)) -> 0 | P28: =IF($B28="","",$H28-$N28) -> -50999.087 | Q28: =IF($B28="","",IF($L28<=0,"n/a",IFERROR($K28/$L28,"n/a"))) -> -4.5 | R28: =IF($B28="","",IF(AND($H28=0,$I28=0),"⚪ No Activity",IF(AND($H28=0,COUNTIFS('SC Change Orders'!$B$2:$B$501,$B28,'SC Change Orders'!$C$2:$C$501,">="&Controls!$C$5,'SC Change Orders'!$C$2:$C$501,"<="&Controls!$C$6)=0),"⚪ No Funding on File",IF($H28=0,"🔴 Unfunded Spend",IF($I28>=$H28,"🔴 Over Budget",IF($N28>$H28,"🔴 Projected Shortfall",IF($J28>=Controls!$C$8,"🟡 Watch","🟢 On Track"))))))) -> ⚪ No Funding on File
A29: =IF($B29="","",IF((IFERROR(INDEX(_RefTable!$A$2:$A$501,MATCH($B29,_RefTable!$C$2:$C$501,0)),IFERROR(INDEX(_MainTable!$A$2:$A$2001,MATCH($B29,_MainTable!$F$2:$F$2001,0)),IFERROR(INDEX('SC Change Orders'!$A$2:$A$501,MATCH($B29,'SC Change Orders'!$B$2:$B$501,0)),"(unknown vendor)"))))&""="","—",(IFERROR(INDEX(_RefTable!$A$2:$A$501,MATCH($B29,_RefTable!$C$2:$C$501,0)),IFERROR(INDEX(_MainTable!$A$2:$A$2001,MATCH($B29,_MainTable!$F$2:$F$2001,0)),IFERROR(INDEX('SC Change Orders'!$A$2:$A$501,MATCH($B29,'SC Change Orders'!$B$2:$B$501,0)),"(unknown vendor)")))))) -> EXPERIAN HEALTH | B29: =IFERROR(INDEX('PO Index'!$B$5:$B$84,25),"") -> 10473 | C29: =IF($B29="","",IF((IFERROR(INDEX(_RefTable!$B$2:$B$501,MATCH($B29,_RefTable!$C$2:$C$501,0))&IF(COUNTIF(_RefTable!$C$2:$C$501,$B29)>1," (+"&COUNTIF(_RefTable!$C$2:$C$501,$B29)-1&" more)",""),IFERROR(INDEX(_MainTable!$B$2:$B$2001,MATCH($B29,_MainTable!$F$2:$F$2001,0)),"")))&""="","—",(IFERROR(INDEX(_RefTable!$B$2:$B$501,MATCH($B29,_RefTable!$C$2:$C$501,0))&IF(COUNTIF(_RefTable!$C$2:$C$501,$B29)>1," (+"&COUNTIF(_RefTable!$C$2:$C$501,$B29)-1&" more)",""),IFERROR(INDEX(_MainTable!$B$2:$B$2001,MATCH($B29,_MainTable!$F$2:$F$2001,0)),""))))) -> Claims Clearinghouse | D29: =IF($B29="","",IF((IFERROR(INDEX(_RefTable!$E$2:$E$501,MATCH($B29,_RefTable!$C$2:$C$501,0)),IFERROR(INDEX(_MainTable!$C$2:$C$2001,MATCH($B29,_MainTable!$F$2:$F$2001,0)),"")))&""="","—",(IFERROR(INDEX(_RefTable!$E$2:$E$501,MATCH($B29,_RefTable!$C$2:$C$501,0)),IFERROR(INDEX(_MainTable!$C$2:$C$2001,MATCH($B29,_MainTable!$F$2:$F$2001,0)),""))))) -> Jake Reid | E29: =IF($B29="","",IF((IFERROR(INDEX(_RefTable!$F$2:$F$501,MATCH($B29,_RefTable!$C$2:$C$501,0)),IFERROR(INDEX(_MainTable!$D$2:$D$2001,MATCH($B29,_MainTable!$F$2:$F$2001,0)),"")))&""="","—",(IFERROR(INDEX(_RefTable!$F$2:$F$501,MATCH($B29,_RefTable!$C$2:$C$501,0)),IFERROR(INDEX(_MainTable!$D$2:$D$2001,MATCH($B29,_MainTable!$F$2:$F$2001,0)),""))))) -> Adam Vardaman | F29: =IF($B29="","",IFERROR(_xlfn.MINIFS('SC Change Orders'!$E$2:$E$501,'SC Change Orders'!$B$2:$B$501,$B29,'SC Change Orders'!$C$2:$C$501,">="&Controls!$C$5,'SC Change Orders'!$C$2:$C$501,"<="&Controls!$C$6),0)) -> 1300000 | G29: =IF($B29="","",SUMIFS('SC Change Orders'!$F$2:$F$501,'SC Change Orders'!$B$2:$B$501,$B29,'SC Change Orders'!$C$2:$C$501,">="&Controls!$C$5,'SC Change Orders'!$C$2:$C$501,"<="&Controls!$C$6)) -> 508790 | H29: =IF($B29="","",$F29+$G29) -> 1808790 | I29: =IF($B29="","",SUMIFS(_MainTable!$K$2:$K$2001,_MainTable!$F$2:$F$2001,$B29,_MainTable!$G$2:$G$2001,">="&Controls!$C$5,_MainTable!$G$2:$G$2001,"<="&Controls!$C$6)) -> 686916.08 | J29: =IF($B29="","",IFERROR($I29/$H29,0)) -> 0.37976552 | K29: =IF($B29="","",$H29-$I29) -> 1121873.9 | L29: =IF($B29="","",IFERROR(SUMIFS(_MainTable!$K$2:$K$2001,_MainTable!$F$2:$F$2001,$B29,_MainTable!$G$2:$G$2001,">="&Controls!$C$12,_MainTable!$G$2:$G$2001,"<="&EOMONTH(Controls!$C$7,0))/MIN(Controls!$C$9,Controls!$C$10),0)) -> 119429.7 | M29: =IF($B29="","",$L29*Controls!$C$11) -> 238859.41 | N29: =IF($B29="","",$I29+$M29) -> 925775.49 | O29: =IF($B29="","",IFERROR($N29/$H29,0)) -> 0.51182033 | P29: =IF($B29="","",$H29-$N29) -> 883014.51 | Q29: =IF($B29="","",IF($L29<=0,"n/a",IFERROR($K29/$L29,"n/a"))) -> 9.3935921 | R29: =IF($B29="","",IF(AND($H29=0,$I29=0),"⚪ No Activity",IF(AND($H29=0,COUNTIFS('SC Change Orders'!$B$2:$B$501,$B29,'SC Change Orders'!$C$2:$C$501,">="&Controls!$C$5,'SC Change Orders'!$C$2:$C$501,"<="&Controls!$C$6)=0),"⚪ No Funding on File",IF($H29=0,"🔴 Unfunded Spend",IF($I29>=$H29,"🔴 Over Budget",IF($N29>$H29,"🔴 Projected Shortfall",IF($J29>=Controls!$C$8,"🟡 Watch","🟢 On Track"))))))) -> 🟢 On Track
A30: =IF($B30="","",IF((IFERROR(INDEX(_RefTable!$A$2:$A$501,MATCH($B30,_RefTable!$C$2:$C$501,0)),IFERROR(INDEX(_MainTable!$A$2:$A$2001,MATCH($B30,_MainTable!$F$2:$F$2001,0)),IFERROR(INDEX('SC Change Orders'!$A$2:$A$501,MATCH($B30,'SC Change Orders'!$B$2:$B$501,0)),"(unknown vendor)"))))&""="","—",(IFERROR(INDEX(_RefTable!$A$2:$A$501,MATCH($B30,_RefTable!$C$2:$C$501,0)),IFERROR(INDEX(_MainTable!$A$2:$A$2001,MATCH($B30,_MainTable!$F$2:$F$2001,0)),IFERROR(INDEX('SC Change Orders'!$A$2:$A$501,MATCH($B30,'SC Change Orders'!$B$2:$B$501,0)),"(unknown vendor)")))))) -> MCBEE ASSOCIATES INC | B30: =IFERROR(INDEX('PO Index'!$B$5:$B$84,26),"") -> 10479 | C30: =IF($B30="","",IF((IFERROR(INDEX(_RefTable!$B$2:$B$501,MATCH($B30,_RefTable!$C$2:$C$501,0))&IF(COUNTIF(_RefTable!$C$2:$C$501,$B30)>1," (+"&COUNTIF(_RefTable!$C$2:$C$501,$B30)-1&" more)",""),IFERROR(INDEX(_MainTable!$B$2:$B$2001,MATCH($B30,_MainTable!$F$2:$F$2001,0)),"")))&""="","—",(IFERROR(INDEX(_RefTable!$B$2:$B$501,MATCH($B30,_RefTable!$C$2:$C$501,0))&IF(COUNTIF(_RefTable!$C$2:$C$501,$B30)>1," (+"&COUNTIF(_RefTable!$C$2:$C$501,$B30)-1&" more)",""),IFERROR(INDEX(_MainTable!$B$2:$B$2001,MATCH($B30,_MainTable!$F$2:$F$2001,0)),""))))) -> Transfer DRG (+1 more) | D30: =IF($B30="","",IF((IFERROR(INDEX(_RefTable!$E$2:$E$501,MATCH($B30,_RefTable!$C$2:$C$501,0)),IFERROR(INDEX(_MainTable!$C$2:$C$2001,MATCH($B30,_MainTable!$F$2:$F$2001,0)),"")))&""="","—",(IFERROR(INDEX(_RefTable!$E$2:$E$501,MATCH($B30,_RefTable!$C$2:$C$501,0)),IFERROR(INDEX(_MainTable!$C$2:$C$2001,MATCH($B30,_MainTable!$F$2:$F$2001,0)),""))))) -> Jake Reid | E30: =IF($B30="","",IF((IFERROR(INDEX(_RefTable!$F$2:$F$501,MATCH($B30,_RefTable!$C$2:$C$501,0)),IFERROR(INDEX(_MainTable!$D$2:$D$2001,MATCH($B30,_MainTable!$F$2:$F$2001,0)),"")))&""="","—",(IFERROR(INDEX(_RefTable!$F$2:$F$501,MATCH($B30,_RefTable!$C$2:$C$501,0)),IFERROR(INDEX(_MainTable!$D$2:$D$2001,MATCH($B30,_MainTable!$F$2:$F$2001,0)),""))))) -> Jaime Burnham | F30: =IF($B30="","",IFERROR(_xlfn.MINIFS('SC Change Orders'!$E$2:$E$501,'SC Change Orders'!$B$2:$B$501,$B30,'SC Change Orders'!$C$2:$C$501,">="&Controls!$C$5,'SC Change Orders'!$C$2:$C$501,"<="&Controls!$C$6),0)) -> 0 | G30: =IF($B30="","",SUMIFS('SC Change Orders'!$F$2:$F$501,'SC Change Orders'!$B$2:$B$501,$B30,'SC Change Orders'!$C$2:$C$501,">="&Controls!$C$5,'SC Change Orders'!$C$2:$C$501,"<="&Controls!$C$6)) -> 0 | H30: =IF($B30="","",$F30+$G30) -> 0 | I30: =IF($B30="","",SUMIFS(_MainTable!$K$2:$K$2001,_MainTable!$F$2:$F$2001,$B30,_MainTable!$G$2:$G$2001,">="&Controls!$C$5,_MainTable!$G$2:$G$2001,"<="&Controls!$C$6)) -> 26620.51 | J30: =IF($B30="","",IFERROR($I30/$H30,0)) -> 0 | K30: =IF($B30="","",$H30-$I30) -> -26620.51 | L30: =IF($B30="","",IFERROR(SUMIFS(_MainTable!$K$2:$K$2001,_MainTable!$F$2:$F$2001,$B30,_MainTable!$G$2:$G$2001,">="&Controls!$C$12,_MainTable!$G$2:$G$2001,"<="&EOMONTH(Controls!$C$7,0))/MIN(Controls!$C$9,Controls!$C$10),0)) -> 8873.5033 | M30: =IF($B30="","",$L30*Controls!$C$11) -> 17747.007 | N30: =IF($B30="","",$I30+$M30) -> 44367.517 | O30: =IF($B30="","",IFERROR($N30/$H30,0)) -> 0 | P30: =IF($B30="","",$H30-$N30) -> -44367.517 | Q30: =IF($B30="","",IF($L30<=0,"n/a",IFERROR($K30/$L30,"n/a"))) -> -3 | R30: =IF($B30="","",IF(AND($H30=0,$I30=0),"⚪ No Activity",IF(AND($H30=0,COUNTIFS('SC Change Orders'!$B$2:$B$501,$B30,'SC Change Orders'!$C$2:$C$501,">="&Controls!$C$5,'SC Change Orders'!$C$2:$C$501,"<="&Controls!$C$6)=0),"⚪ No Funding on File",IF($H30=0,"🔴 Unfunded Spend",IF($I30>=$H30,"🔴 Over Budget",IF($N30>$H30,"🔴 Projected Shortfall",IF($J30>=Controls!$C$8,"🟡 Watch","🟢 On Track"))))))) -> ⚪ No Funding on File
A31: =IF($B31="","",IF((IFERROR(INDEX(_RefTable!$A$2:$A$501,MATCH($B31,_RefTable!$C$2:$C$501,0)),IFERROR(INDEX(_MainTable!$A$2:$A$2001,MATCH($B31,_MainTable!$F$2:$F$2001,0)),IFERROR(INDEX('SC Change Orders'!$A$2:$A$501,MATCH($B31,'SC Change Orders'!$B$2:$B$501,0)),"(unknown vendor)"))))&""="","—",(IFERROR(INDEX(_RefTable!$A$2:$A$501,MATCH($B31,_RefTable!$C$2:$C$501,0)),IFERROR(INDEX(_MainTable!$A$2:$A$2001,MATCH($B31,_MainTable!$F$2:$F$2001,0)),IFERROR(INDEX('SC Change Orders'!$A$2:$A$501,MATCH($B31,'SC Change Orders'!$B$2:$B$501,0)),"(unknown vendor)")))))) -> GUIDEHOUSE INC | B31: =IFERROR(INDEX('PO Index'!$B$5:$B$84,27),"") -> 10782 | C31: =IF($B31="","",IF((IFERROR(INDEX(_RefTable!$B$2:$B$501,MATCH($B31,_RefTable!$C$2:$C$501,0))&IF(COUNTIF(_RefTable!$C$2:$C$501,$B31)>1," (+"&COUNTIF(_RefTable!$C$2:$C$501,$B31)-1&" more)",""),IFERROR(INDEX(_MainTable!$B$2:$B$2001,MATCH($B31,_MainTable!$F$2:$F$2001,0)),"")))&""="","—",(IFERROR(INDEX(_RefTable!$B$2:$B$501,MATCH($B31,_RefTable!$C$2:$C$501,0))&IF(COUNTIF(_RefTable!$C$2:$C$501,$B31)>1," (+"&COUNTIF(_RefTable!$C$2:$C$501,$B31)-1&" more)",""),IFERROR(INDEX(_MainTable!$B$2:$B$2001,MATCH($B31,_MainTable!$F$2:$F$2001,0)),""))))) -> Coding | D31: =IF($B31="","",IF((IFERROR(INDEX(_RefTable!$E$2:$E$501,MATCH($B31,_RefTable!$C$2:$C$501,0)),IFERROR(INDEX(_MainTable!$C$2:$C$2001,MATCH($B31,_MainTable!$F$2:$F$2001,0)),"")))&""="","—",(IFERROR(INDEX(_RefTable!$E$2:$E$501,MATCH($B31,_RefTable!$C$2:$C$501,0)),IFERROR(INDEX(_MainTable!$C$2:$C$2001,MATCH($B31,_MainTable!$F$2:$F$2001,0)),""))))) -> Sona Buchanan | E31: =IF($B31="","",IF((IFERROR(INDEX(_RefTable!$F$2:$F$501,MATCH($B31,_RefTable!$C$2:$C$501,0)),IFERROR(INDEX(_MainTable!$D$2:$D$2001,MATCH($B31,_MainTable!$F$2:$F$2001,0)),"")))&""="","—",(IFERROR(INDEX(_RefTable!$F$2:$F$501,MATCH($B31,_RefTable!$C$2:$C$501,0)),IFERROR(INDEX(_MainTable!$D$2:$D$2001,MATCH($B31,_MainTable!$F$2:$F$2001,0)),""))))) -> Heather Geile | F31: =IF($B31="","",IFERROR(_xlfn.MINIFS('SC Change Orders'!$E$2:$E$501,'SC Change Orders'!$B$2:$B$501,$B31,'SC Change Orders'!$C$2:$C$501,">="&Controls!$C$5,'SC Change Orders'!$C$2:$C$501,"<="&Controls!$C$6),0)) -> 288447 | G31: =IF($B31="","",SUMIFS('SC Change Orders'!$F$2:$F$501,'SC Change Orders'!$B$2:$B$501,$B31,'SC Change Orders'!$C$2:$C$501,">="&Controls!$C$5,'SC Change Orders'!$C$2:$C$501,"<="&Controls!$C$6)) -> 690247.88 | H31: =IF($B31="","",$F31+$G31) -> 978694.88 | I31: =IF($B31="","",SUMIFS(_MainTable!$K$2:$K$2001,_MainTable!$F$2:$F$2001,$B31,_MainTable!$G$2:$G$2001,">="&Controls!$C$5,_MainTable!$G$2:$G$2001,"<="&Controls!$C$6)) -> 563185.59 | J31: =IF($B31="","",IFERROR($I31/$H31,0)) -> 0.57544553 | K31: =IF($B31="","",$H31-$I31) -> 415509.29 | L31: =IF($B31="","",IFERROR(SUMIFS(_MainTable!$K$2:$K$2001,_MainTable!$F$2:$F$2001,$B31,_MainTable!$G$2:$G$2001,">="&Controls!$C$12,_MainTable!$G$2:$G$2001,"<="&EOMONTH(Controls!$C$7,0))/MIN(Controls!$C$9,Controls!$C$10),0)) -> 139726.65 | M31: =IF($B31="","",$L31*Controls!$C$11) -> 279453.29 | N31: =IF($B31="","",$I31+$M31) -> 842638.88 | O31: =IF($B31="","",IFERROR($N31/$H31,0)) -> 0.86098221 | P31: =IF($B31="","",$H31-$N31) -> 136056 | Q31: =IF($B31="","",IF($L31<=0,"n/a",IFERROR($K31/$L31,"n/a"))) -> 2.9737298 | R31: =IF($B31="","",IF(AND($H31=0,$I31=0),"⚪ No Activity",IF(AND($H31=0,COUNTIFS('SC Change Orders'!$B$2:$B$501,$B31,'SC Change Orders'!$C$2:$C$501,">="&Controls!$C$5,'SC Change Orders'!$C$2:$C$501,"<="&Controls!$C$6)=0),"⚪ No Funding on File",IF($H31=0,"🔴 Unfunded Spend",IF($I31>=$H31,"🔴 Over Budget",IF($N31>$H31,"🔴 Projected Shortfall",IF($J31>=Controls!$C$8,"🟡 Watch","🟢 On Track"))))))) -> 🟢 On Track
A32: =IF($B32="","",IF((IFERROR(INDEX(_RefTable!$A$2:$A$501,MATCH($B32,_RefTable!$C$2:$C$501,0)),IFERROR(INDEX(_MainTable!$A$2:$A$2001,MATCH($B32,_MainTable!$F$2:$F$2001,0)),IFERROR(INDEX('SC Change Orders'!$A$2:$A$501,MATCH($B32,'SC Change Orders'!$B$2:$B$501,0)),"(unknown vendor)"))))&""="","—",(IFERROR(INDEX(_RefTable!$A$2:$A$501,MATCH($B32,_RefTable!$C$2:$C$501,0)),IFERROR(INDEX(_MainTable!$A$2:$A$2001,MATCH($B32,_MainTable!$F$2:$F$2001,0)),IFERROR(INDEX('SC Change Orders'!$A$2:$A$501,MATCH($B32,'SC Change Orders'!$B$2:$B$501,0)),"(unknown vendor)")))))) -> GUIDEHOUSE INC | B32: =IFERROR(INDEX('PO Index'!$B$5:$B$84,28),"") -> 10783 | C32: =IF($B32="","",IF((IFERROR(INDEX(_RefTable!$B$2:$B$501,MATCH($B32,_RefTable!$C$2:$C$501,0))&IF(COUNTIF(_RefTable!$C$2:$C$501,$B32)>1," (+"&COUNTIF(_RefTable!$C$2:$C$501,$B32)-1&" more)",""),IFERROR(INDEX(_MainTable!$B$2:$B$2001,MATCH($B32,_MainTable!$F$2:$F$2001,0)),"")))&""="","—",(IFERROR(INDEX(_RefTable!$B$2:$B$501,MATCH($B32,_RefTable!$C$2:$C$501,0))&IF(COUNTIF(_RefTable!$C$2:$C$501,$B32)>1," (+"&COUNTIF(_RefTable!$C$2:$C$501,$B32)-1&" more)",""),IFERROR(INDEX(_MainTable!$B$2:$B$2001,MATCH($B32,_MainTable!$F$2:$F$2001,0)),""))))) -> ASA | D32: =IF($B32="","",IF((IFERROR(INDEX(_RefTable!$E$2:$E$501,MATCH($B32,_RefTable!$C$2:$C$501,0)),IFERROR(INDEX(_MainTable!$C$2:$C$2001,MATCH($B32,_MainTable!$F$2:$F$2001,0)),"")))&""="","—",(IFERROR(INDEX(_RefTable!$E$2:$E$501,MATCH($B32,_RefTable!$C$2:$C$501,0)),IFERROR(INDEX(_MainTable!$C$2:$C$2001,MATCH($B32,_MainTable!$F$2:$F$2001,0)),""))))) -> Rachel Seaman | E32: =IF($B32="","",IF((IFERROR(INDEX(_RefTable!$F$2:$F$501,MATCH($B32,_RefTable!$C$2:$C$501,0)),IFERROR(INDEX(_MainTable!$D$2:$D$2001,MATCH($B32,_MainTable!$F$2:$F$2001,0)),"")))&""="","—",(IFERROR(INDEX(_RefTable!$F$2:$F$501,MATCH($B32,_RefTable!$C$2:$C$501,0)),IFERROR(INDEX(_MainTable!$D$2:$D$2001,MATCH($B32,_MainTable!$F$2:$F$2001,0)),""))))) -> — | F32: =IF($B32="","",IFERROR(_xlfn.MINIFS('SC Change Orders'!$E$2:$E$501,'SC Change Orders'!$B$2:$B$501,$B32,'SC Change Orders'!$C$2:$C$501,">="&Controls!$C$5,'SC Change Orders'!$C$2:$C$501,"<="&Controls!$C$6),0)) -> 47625 | G32: =IF($B32="","",SUMIFS('SC Change Orders'!$F$2:$F$501,'SC Change Orders'!$B$2:$B$501,$B32,'SC Change Orders'!$C$2:$C$501,">="&Controls!$C$5,'SC Change Orders'!$C$2:$C$501,"<="&Controls!$C$6)) -> 35181.25 | H32: =IF($B32="","",$F32+$G32) -> 82806.25 | I32: =IF($B32="","",SUMIFS(_MainTable!$K$2:$K$2001,_MainTable!$F$2:$F$2001,$B32,_MainTable!$G$2:$G$2001,">="&Controls!$C$5,_MainTable!$G$2:$G$2001,"<="&Controls!$C$6)) -> 176107.72 | J32: =IF($B32="","",IFERROR($I32/$H32,0)) -> 2.1267443 | K32: =IF($B32="","",$H32-$I32) -> -93301.47 | L32: =IF($B32="","",IFERROR(SUMIFS(_MainTable!$K$2:$K$2001,_MainTable!$F$2:$F$2001,$B32,_MainTable!$G$2:$G$2001,">="&Controls!$C$12,_MainTable!$G$2:$G$2001,"<="&EOMONTH(Controls!$C$7,0))/MIN(Controls!$C$9,Controls!$C$10),0)) -> 35249.303 | M32: =IF($B32="","",$L32*Controls!$C$11) -> 70498.607 | N32: =IF($B32="","",$I32+$M32) -> 246606.33 | O32: =IF($B32="","",IFERROR($N32/$H32,0)) -> 2.9781125 | P32: =IF($B32="","",$H32-$N32) -> -163800.08 | Q32: =IF($B32="","",IF($L32<=0,"n/a",IFERROR($K32/$L32,"n/a"))) -> -2.6469025 | R32: =IF($B32="","",IF(AND($H32=0,$I32=0),"⚪ No Activity",IF(AND($H32=0,COUNTIFS('SC Change Orders'!$B$2:$B$501,$B32,'SC Change Orders'!$C$2:$C$501,">="&Controls!$C$5,'SC Change Orders'!$C$2:$C$501,"<="&Controls!$C$6)=0),"⚪ No Funding on File",IF($H32=0,"🔴 Unfunded Spend",IF($I32>=$H32,"🔴 Over Budget",IF($N32>$H32,"🔴 Projected Shortfall",IF($J32>=Controls!$C$8,"🟡 Watch","🟢 On Track"))))))) -> 🔴 Over Budget
A33: =IF($B33="","",IF((IFERROR(INDEX(_RefTable!$A$2:$A$501,MATCH($B33,_RefTable!$C$2:$C$501,0)),IFERROR(INDEX(_MainTable!$A$2:$A$2001,MATCH($B33,_MainTable!$F$2:$F$2001,0)),IFERROR(INDEX('SC Change Orders'!$A$2:$A$501,MATCH($B33,'SC Change Orders'!$B$2:$B$501,0)),"(unknown vendor)"))))&""="","—",(IFERROR(INDEX(_RefTable!$A$2:$A$501,MATCH($B33,_RefTable!$C$2:$C$501,0)),IFERROR(INDEX(_MainTable!$A$2:$A$2001,MATCH($B33,_MainTable!$F$2:$F$2001,0)),IFERROR(INDEX('SC Change Orders'!$A$2:$A$501,MATCH($B33,'SC Change Orders'!$B$2:$B$501,0)),"(unknown vendor)")))))) -> CLOUDMED | B33: =IFERROR(INDEX('PO Index'!$B$5:$B$84,29),"") -> 10798 | C33: =IF($B33="","",IF((IFERROR(INDEX(_RefTable!$B$2:$B$501,MATCH($B33,_RefTable!$C$2:$C$501,0))&IF(COUNTIF(_RefTable!$C$2:$C$501,$B33)>1," (+"&COUNTIF(_RefTable!$C$2:$C$501,$B33)-1&" more)",""),IFERROR(INDEX(_MainTable!$B$2:$B$2001,MATCH($B33,_MainTable!$F$2:$F$2001,0)),"")))&""="","—",(IFERROR(INDEX(_RefTable!$B$2:$B$501,MATCH($B33,_RefTable!$C$2:$C$501,0))&IF(COUNTIF(_RefTable!$C$2:$C$501,$B33)>1," (+"&COUNTIF(_RefTable!$C$2:$C$501,$B33)-1&" more)",""),IFERROR(INDEX(_MainTable!$B$2:$B$2001,MATCH($B33,_MainTable!$F$2:$F$2001,0)),""))))) -> Denials (+1 more) | D33: =IF($B33="","",IF((IFERROR(INDEX(_RefTable!$E$2:$E$501,MATCH($B33,_RefTable!$C$2:$C$501,0)),IFERROR(INDEX(_MainTable!$C$2:$C$2001,MATCH($B33,_MainTable!$F$2:$F$2001,0)),"")))&""="","—",(IFERROR(INDEX(_RefTable!$E$2:$E$501,MATCH($B33,_RefTable!$C$2:$C$501,0)),IFERROR(INDEX(_MainTable!$C$2:$C$2001,MATCH($B33,_MainTable!$F$2:$F$2001,0)),""))))) -> Jake Reid | E33: =IF($B33="","",IF((IFERROR(INDEX(_RefTable!$F$2:$F$501,MATCH($B33,_RefTable!$C$2:$C$501,0)),IFERROR(INDEX(_MainTable!$D$2:$D$2001,MATCH($B33,_MainTable!$F$2:$F$2001,0)),"")))&""="","—",(IFERROR(INDEX(_RefTable!$F$2:$F$501,MATCH($B33,_RefTable!$C$2:$C$501,0)),IFERROR(INDEX(_MainTable!$D$2:$D$2001,MATCH($B33,_MainTable!$F$2:$F$2001,0)),""))))) -> Cody Thornock | F33: =IF($B33="","",IFERROR(_xlfn.MINIFS('SC Change Orders'!$E$2:$E$501,'SC Change Orders'!$B$2:$B$501,$B33,'SC Change Orders'!$C$2:$C$501,">="&Controls!$C$5,'SC Change Orders'!$C$2:$C$501,"<="&Controls!$C$6),0)) -> 1000000 | G33: =IF($B33="","",SUMIFS('SC Change Orders'!$F$2:$F$501,'SC Change Orders'!$B$2:$B$501,$B33,'SC Change Orders'!$C$2:$C$501,">="&Controls!$C$5,'SC Change Orders'!$C$2:$C$501,"<="&Controls!$C$6)) -> 1600000 | H33: =IF($B33="","",$F33+$G33) -> 2600000 | I33: =IF($B33="","",SUMIFS(_MainTable!$K$2:$K$2001,_MainTable!$F$2:$F$2001,$B33,_MainTable!$G$2:$G$2001,">="&Controls!$C$5,_MainTable!$G$2:$G$2001,"<="&Controls!$C$6)) -> 387040.78 | J33: =IF($B33="","",IFERROR($I33/$H33,0)) -> 0.14886184 | K33: =IF($B33="","",$H33-$I33) -> 2212959.2 | L33: =IF($B33="","",IFERROR(SUMIFS(_MainTable!$K$2:$K$2001,_MainTable!$F$2:$F$2001,$B33,_MainTable!$G$2:$G$2001,">="&Controls!$C$12,_MainTable!$G$2:$G$2001,"<="&EOMONTH(Controls!$C$7,0))/MIN(Controls!$C$9,Controls!$C$10),0)) -> 66261.27 | M33: =IF($B33="","",$L33*Controls!$C$11) -> 132522.54 | N33: =IF($B33="","",$I33+$M33) -> 519563.32 | O33: =IF($B33="","",IFERROR($N33/$H33,0)) -> 0.19983205 | P33: =IF($B33="","",$H33-$N33) -> 2080436.7 | Q33: =IF($B33="","",IF($L33<=0,"n/a",IFERROR($K33/$L33,"n/a"))) -> 33.397477 | R33: =IF($B33="","",IF(AND($H33=0,$I33=0),"⚪ No Activity",IF(AND($H33=0,COUNTIFS('SC Change Orders'!$B$2:$B$501,$B33,'SC Change Orders'!$C$2:$C$501,">="&Controls!$C$5,'SC Change Orders'!$C$2:$C$501,"<="&Controls!$C$6)=0),"⚪ No Funding on File",IF($H33=0,"🔴 Unfunded Spend",IF($I33>=$H33,"🔴 Over Budget",IF($N33>$H33,"🔴 Projected Shortfall",IF($J33>=Controls!$C$8,"🟡 Watch","🟢 On Track"))))))) -> 🟢 On Track
A34: =IF($B34="","",IF((IFERROR(INDEX(_RefTable!$A$2:$A$501,MATCH($B34,_RefTable!$C$2:$C$501,0)),IFERROR(INDEX(_MainTable!$A$2:$A$2001,MATCH($B34,_MainTable!$F$2:$F$2001,0)),IFERROR(INDEX('SC Change Orders'!$A$2:$A$501,MATCH($B34,'SC Change Orders'!$B$2:$B$501,0)),"(unknown vendor)"))))&""="","—",(IFERROR(INDEX(_RefTable!$A$2:$A$501,MATCH($B34,_RefTable!$C$2:$C$501,0)),IFERROR(INDEX(_MainTable!$A$2:$A$2001,MATCH($B34,_MainTable!$F$2:$F$2001,0)),IFERROR(INDEX('SC Change Orders'!$A$2:$A$501,MATCH($B34,'SC Change Orders'!$B$2:$B$501,0)),"(unknown vendor)")))))) -> HIMAGINE SOLUTIONS INC | B34: =IFERROR(INDEX('PO Index'!$B$5:$B$84,30),"") -> 10800 | C34: =IF($B34="","",IF((IFERROR(INDEX(_RefTable!$B$2:$B$501,MATCH($B34,_RefTable!$C$2:$C$501,0))&IF(COUNTIF(_RefTable!$C$2:$C$501,$B34)>1," (+"&COUNTIF(_RefTable!$C$2:$C$501,$B34)-1&" more)",""),IFERROR(INDEX(_MainTable!$B$2:$B$2001,MATCH($B34,_MainTable!$F$2:$F$2001,0)),"")))&""="","—",(IFERROR(INDEX(_RefTable!$B$2:$B$501,MATCH($B34,_RefTable!$C$2:$C$501,0))&IF(COUNTIF(_RefTable!$C$2:$C$501,$B34)>1," (+"&COUNTIF(_RefTable!$C$2:$C$501,$B34)-1&" more)",""),IFERROR(INDEX(_MainTable!$B$2:$B$2001,MATCH($B34,_MainTable!$F$2:$F$2001,0)),""))))) -> Coding (+1 more) | D34: =IF($B34="","",IF((IFERROR(INDEX(_RefTable!$E$2:$E$501,MATCH($B34,_RefTable!$C$2:$C$501,0)),IFERROR(INDEX(_MainTable!$C$2:$C$2001,MATCH($B34,_MainTable!$F$2:$F$2001,0)),"")))&""="","—",(IFERROR(INDEX(_RefTable!$E$2:$E$501,MATCH($B34,_RefTable!$C$2:$C$501,0)),IFERROR(INDEX(_MainTable!$C$2:$C$2001,MATCH($B34,_MainTable!$F$2:$F$2001,0)),""))))) -> Sona Buchanan | E34: =IF($B34="","",IF((IFERROR(INDEX(_RefTable!$F$2:$F$501,MATCH($B34,_RefTable!$C$2:$C$501,0)),IFERROR(INDEX(_MainTable!$D$2:$D$2001,MATCH($B34,_MainTable!$F$2:$F$2001,0)),"")))&""="","—",(IFERROR(INDEX(_RefTable!$F$2:$F$501,MATCH($B34,_RefTable!$C$2:$C$501,0)),IFERROR(INDEX(_MainTable!$D$2:$D$2001,MATCH($B34,_MainTable!$F$2:$F$2001,0)),""))))) -> Jolene Armstrong | F34: =IF($B34="","",IFERROR(_xlfn.MINIFS('SC Change Orders'!$E$2:$E$501,'SC Change Orders'!$B$2:$B$501,$B34,'SC Change Orders'!$C$2:$C$501,">="&Controls!$C$5,'SC Change Orders'!$C$2:$C$501,"<="&Controls!$C$6),0)) -> 0 | G34: =IF($B34="","",SUMIFS('SC Change Orders'!$F$2:$F$501,'SC Change Orders'!$B$2:$B$501,$B34,'SC Change Orders'!$C$2:$C$501,">="&Controls!$C$5,'SC Change Orders'!$C$2:$C$501,"<="&Controls!$C$6)) -> 0 | H34: =IF($B34="","",$F34+$G34) -> 0 | I34: =IF($B34="","",SUMIFS(_MainTable!$K$2:$K$2001,_MainTable!$F$2:$F$2001,$B34,_MainTable!$G$2:$G$2001,">="&Controls!$C$5,_MainTable!$G$2:$G$2001,"<="&Controls!$C$6)) -> 11173.33 | J34: =IF($B34="","",IFERROR($I34/$H34,0)) -> 0 | K34: =IF($B34="","",$H34-$I34) -> -11173.33 | L34: =IF($B34="","",IFERROR(SUMIFS(_MainTable!$K$2:$K$2001,_MainTable!$F$2:$F$2001,$B34,_MainTable!$G$2:$G$2001,">="&Controls!$C$12,_MainTable!$G$2:$G$2001,"<="&EOMONTH(Controls!$C$7,0))/MIN(Controls!$C$9,Controls!$C$10),0)) -> 0 | M34: =IF($B34="","",$L34*Controls!$C$11) -> 0 | N34: =IF($B34="","",$I34+$M34) -> 11173.33 | O34: =IF($B34="","",IFERROR($N34/$H34,0)) -> 0 | P34: =IF($B34="","",$H34-$N34) -> -11173.33 | Q34: =IF($B34="","",IF($L34<=0,"n/a",IFERROR($K34/$L34,"n/a"))) -> n/a | R34: =IF($B34="","",IF(AND($H34=0,$I34=0),"⚪ No Activity",IF(AND($H34=0,COUNTIFS('SC Change Orders'!$B$2:$B$501,$B34,'SC Change Orders'!$C$2:$C$501,">="&Controls!$C$5,'SC Change Orders'!$C$2:$C$501,"<="&Controls!$C$6)=0),"⚪ No Funding on File",IF($H34=0,"🔴 Unfunded Spend",IF($I34>=$H34,"🔴 Over Budget",IF($N34>$H34,"🔴 Projected Shortfall",IF($J34>=Controls!$C$8,"🟡 Watch","🟢 On Track"))))))) -> ⚪ No Funding on File
A35: =IF($B35="","",IF((IFERROR(INDEX(_RefTable!$A$2:$A$501,MATCH($B35,_RefTable!$C$2:$C$501,0)),IFERROR(INDEX(_MainTable!$A$2:$A$2001,MATCH($B35,_MainTable!$F$2:$F$2001,0)),IFERROR(INDEX('SC Change Orders'!$A$2:$A$501,MATCH($B35,'SC Change Orders'!$B$2:$B$501,0)),"(unknown vendor)"))))&""="","—",(IFERROR(INDEX(_RefTable!$A$2:$A$501,MATCH($B35,_RefTable!$C$2:$C$501,0)),IFERROR(INDEX(_MainTable!$A$2:$A$2001,MATCH($B35,_MainTable!$F$2:$F$2001,0)),IFERROR(INDEX('SC Change Orders'!$A$2:$A$501,MATCH($B35,'SC Change Orders'!$B$2:$B$501,0)),"(unknown vendor)")))))) -> UNIFIED HEALTH SERVICES LLC | B35: =IFERROR(INDEX('PO Index'!$B$5:$B$84,31),"") -> 10824 | C35: =IF($B35="","",IF((IFERROR(INDEX(_RefTable!$B$2:$B$501,MATCH($B35,_RefTable!$C$2:$C$501,0))&IF(COUNTIF(_RefTable!$C$2:$C$501,$B35)>1," (+"&COUNTIF(_RefTable!$C$2:$C$501,$B35)-1&" more)",""),IFERROR(INDEX(_MainTable!$B$2:$B$2001,MATCH($B35,_MainTable!$F$2:$F$2001,0)),"")))&""="","—",(IFERROR(INDEX(_RefTable!$B$2:$B$501,MATCH($B35,_RefTable!$C$2:$C$501,0))&IF(COUNTIF(_RefTable!$C$2:$C$501,$B35)>1," (+"&COUNTIF(_RefTable!$C$2:$C$501,$B35)-1&" more)",""),IFERROR(INDEX(_MainTable!$B$2:$B$2001,MATCH($B35,_MainTable!$F$2:$F$2001,0)),""))))) -> Work Comp | D35: =IF($B35="","",IF((IFERROR(INDEX(_RefTable!$E$2:$E$501,MATCH($B35,_RefTable!$C$2:$C$501,0)),IFERROR(INDEX(_MainTable!$C$2:$C$2001,MATCH($B35,_MainTable!$F$2:$F$2001,0)),"")))&""="","—",(IFERROR(INDEX(_RefTable!$E$2:$E$501,MATCH($B35,_RefTable!$C$2:$C$501,0)),IFERROR(INDEX(_MainTable!$C$2:$C$2001,MATCH($B35,_MainTable!$F$2:$F$2001,0)),""))))) -> Jake Reid | E35: =IF($B35="","",IF((IFERROR(INDEX(_RefTable!$F$2:$F$501,MATCH($B35,_RefTable!$C$2:$C$501,0)),IFERROR(INDEX(_MainTable!$D$2:$D$2001,MATCH($B35,_MainTable!$F$2:$F$2001,0)),"")))&""="","—",(IFERROR(INDEX(_RefTable!$F$2:$F$501,MATCH($B35,_RefTable!$C$2:$C$501,0)),IFERROR(INDEX(_MainTable!$D$2:$D$2001,MATCH($B35,_MainTable!$F$2:$F$2001,0)),""))))) -> Cody Thornock | F35: =IF($B35="","",IFERROR(_xlfn.MINIFS('SC Change Orders'!$E$2:$E$501,'SC Change Orders'!$B$2:$B$501,$B35,'SC Change Orders'!$C$2:$C$501,">="&Controls!$C$5,'SC Change Orders'!$C$2:$C$501,"<="&Controls!$C$6),0)) -> 0 | G35: =IF($B35="","",SUMIFS('SC Change Orders'!$F$2:$F$501,'SC Change Orders'!$B$2:$B$501,$B35,'SC Change Orders'!$C$2:$C$501,">="&Controls!$C$5,'SC Change Orders'!$C$2:$C$501,"<="&Controls!$C$6)) -> 0 | H35: =IF($B35="","",$F35+$G35) -> 0 | I35: =IF($B35="","",SUMIFS(_MainTable!$K$2:$K$2001,_MainTable!$F$2:$F$2001,$B35,_MainTable!$G$2:$G$2001,">="&Controls!$C$5,_MainTable!$G$2:$G$2001,"<="&Controls!$C$6)) -> 786545.68 | J35: =IF($B35="","",IFERROR($I35/$H35,0)) -> 0 | K35: =IF($B35="","",$H35-$I35) -> -786545.68 | L35: =IF($B35="","",IFERROR(SUMIFS(_MainTable!$K$2:$K$2001,_MainTable!$F$2:$F$2001,$B35,_MainTable!$G$2:$G$2001,">="&Controls!$C$12,_MainTable!$G$2:$G$2001,"<="&EOMONTH(Controls!$C$7,0))/MIN(Controls!$C$9,Controls!$C$10),0)) -> 139733.68 | M35: =IF($B35="","",$L35*Controls!$C$11) -> 279467.36 | N35: =IF($B35="","",$I35+$M35) -> 1066013 | O35: =IF($B35="","",IFERROR($N35/$H35,0)) -> 0 | P35: =IF($B35="","",$H35-$N35) -> -1066013 | Q35: =IF($B35="","",IF($L35<=0,"n/a",IFERROR($K35/$L35,"n/a"))) -> -5.6288912 | R35: =IF($B35="","",IF(AND($H35=0,$I35=0),"⚪ No Activity",IF(AND($H35=0,COUNTIFS('SC Change Orders'!$B$2:$B$501,$B35,'SC Change Orders'!$C$2:$C$501,">="&Controls!$C$5,'SC Change Orders'!$C$2:$C$501,"<="&Controls!$C$6)=0),"⚪ No Funding on File",IF($H35=0,"🔴 Unfunded Spend",IF($I35>=$H35,"🔴 Over Budget",IF($N35>$H35,"🔴 Projected Shortfall",IF($J35>=Controls!$C$8,"🟡 Watch","🟢 On Track"))))))) -> ⚪ No Funding on File
A36: =IF($B36="","",IF((IFERROR(INDEX(_RefTable!$A$2:$A$501,MATCH($B36,_RefTable!$C$2:$C$501,0)),IFERROR(INDEX(_MainTable!$A$2:$A$2001,MATCH($B36,_MainTable!$F$2:$F$2001,0)),IFERROR(INDEX('SC Change Orders'!$A$2:$A$501,MATCH($B36,'SC Change Orders'!$B$2:$B$501,0)),"(unknown vendor)"))))&""="","—",(IFERROR(INDEX(_RefTable!$A$2:$A$501,MATCH($B36,_RefTable!$C$2:$C$501,0)),IFERROR(INDEX(_MainTable!$A$2:$A$2001,MATCH($B36,_MainTable!$F$2:$F$2001,0)),IFERROR(INDEX('SC Change Orders'!$A$2:$A$501,MATCH($B36,'SC Change Orders'!$B$2:$B$501,0)),"(unknown vendor)")))))) -> WAYSTAR HEALTH | B36: =IFERROR(INDEX('PO Index'!$B$5:$B$84,32),"") -> 10833 | C36: =IF($B36="","",IF((IFERROR(INDEX(_RefTable!$B$2:$B$501,MATCH($B36,_RefTable!$C$2:$C$501,0))&IF(COUNTIF(_RefTable!$C$2:$C$501,$B36)>1," (+"&COUNTIF(_RefTable!$C$2:$C$501,$B36)-1&" more)",""),IFERROR(INDEX(_MainTable!$B$2:$B$2001,MATCH($B36,_MainTable!$F$2:$F$2001,0)),"")))&""="","—",(IFERROR(INDEX(_RefTable!$B$2:$B$501,MATCH($B36,_RefTable!$C$2:$C$501,0))&IF(COUNTIF(_RefTable!$C$2:$C$501,$B36)>1," (+"&COUNTIF(_RefTable!$C$2:$C$501,$B36)-1&" more)",""),IFERROR(INDEX(_MainTable!$B$2:$B$2001,MATCH($B36,_MainTable!$F$2:$F$2001,0)),""))))) -> P2P, PARO | D36: =IF($B36="","",IF((IFERROR(INDEX(_RefTable!$E$2:$E$501,MATCH($B36,_RefTable!$C$2:$C$501,0)),IFERROR(INDEX(_MainTable!$C$2:$C$2001,MATCH($B36,_MainTable!$F$2:$F$2001,0)),"")))&""="","—",(IFERROR(INDEX(_RefTable!$E$2:$E$501,MATCH($B36,_RefTable!$C$2:$C$501,0)),IFERROR(INDEX(_MainTable!$C$2:$C$2001,MATCH($B36,_MainTable!$F$2:$F$2001,0)),""))))) -> Rachel Seaman | E36: =IF($B36="","",IF((IFERROR(INDEX(_RefTable!$F$2:$F$501,MATCH($B36,_RefTable!$C$2:$C$501,0)),IFERROR(INDEX(_MainTable!$D$2:$D$2001,MATCH($B36,_MainTable!$F$2:$F$2001,0)),"")))&""="","—",(IFERROR(INDEX(_RefTable!$F$2:$F$501,MATCH($B36,_RefTable!$C$2:$C$501,0)),IFERROR(INDEX(_MainTable!$D$2:$D$2001,MATCH($B36,_MainTable!$F$2:$F$2001,0)),""))))) -> Cassie Hammon | F36: =IF($B36="","",IFERROR(_xlfn.MINIFS('SC Change Orders'!$E$2:$E$501,'SC Change Orders'!$B$2:$B$501,$B36,'SC Change Orders'!$C$2:$C$501,">="&Controls!$C$5,'SC Change Orders'!$C$2:$C$501,"<="&Controls!$C$6),0)) -> 0 | G36: =IF($B36="","",SUMIFS('SC Change Orders'!$F$2:$F$501,'SC Change Orders'!$B$2:$B$501,$B36,'SC Change Orders'!$C$2:$C$501,">="&Controls!$C$5,'SC Change Orders'!$C$2:$C$501,"<="&Controls!$C$6)) -> 0 | H36: =IF($B36="","",$F36+$G36) -> 0 | I36: =IF($B36="","",SUMIFS(_MainTable!$K$2:$K$2001,_MainTable!$F$2:$F$2001,$B36,_MainTable!$G$2:$G$2001,">="&Controls!$C$5,_MainTable!$G$2:$G$2001,"<="&Controls!$C$6)) -> 138636 | J36: =IF($B36="","",IFERROR($I36/$H36,0)) -> 0 | K36: =IF($B36="","",$H36-$I36) -> -138636 | L36: =IF($B36="","",IFERROR(SUMIFS(_MainTable!$K$2:$K$2001,_MainTable!$F$2:$F$2001,$B36,_MainTable!$G$2:$G$2001,">="&Controls!$C$12,_MainTable!$G$2:$G$2001,"<="&EOMONTH(Controls!$C$7,0))/MIN(Controls!$C$9,Controls!$C$10),0)) -> 27727.2 | M36: =IF($B36="","",$L36*Controls!$C$11) -> 55454.4 | N36: =IF($B36="","",$I36+$M36) -> 194090.4 | O36: =IF($B36="","",IFERROR($N36/$H36,0)) -> 0 | P36: =IF($B36="","",$H36-$N36) -> -194090.4 | Q36: =IF($B36="","",IF($L36<=0,"n/a",IFERROR($K36/$L36,"n/a"))) -> -5 | R36: =IF($B36="","",IF(AND($H36=0,$I36=0),"⚪ No Activity",IF(AND($H36=0,COUNTIFS('SC Change Orders'!$B$2:$B$501,$B36,'SC Change Orders'!$C$2:$C$501,">="&Controls!$C$5,'SC Change Orders'!$C$2:$C$501,"<="&Controls!$C$6)=0),"⚪ No Funding on File",IF($H36=0,"🔴 Unfunded Spend",IF($I36>=$H36,"🔴 Over Budget",IF($N36>$H36,"🔴 Projected Shortfall",IF($J36>=Controls!$C$8,"🟡 Watch","🟢 On Track"))))))) -> ⚪ No Funding on File
A37: =IF($B37="","",IF((IFERROR(INDEX(_RefTable!$A$2:$A$501,MATCH($B37,_RefTable!$C$2:$C$501,0)),IFERROR(INDEX(_MainTable!$A$2:$A$2001,MATCH($B37,_MainTable!$F$2:$F$2001,0)),IFERROR(INDEX('SC Change Orders'!$A$2:$A$501,MATCH($B37,'SC Change Orders'!$B$2:$B$501,0)),"(unknown vendor)"))))&""="","—",(IFERROR(INDEX(_RefTable!$A$2:$A$501,MATCH($B37,_RefTable!$C$2:$C$501,0)),IFERROR(INDEX(_MainTable!$A$2:$A$2001,MATCH($B37,_MainTable!$F$2:$F$2001,0)),IFERROR(INDEX('SC Change Orders'!$A$2:$A$501,MATCH($B37,'SC Change Orders'!$B$2:$B$501,0)),"(unknown vendor)")))))) -> ACCESSONE | B37: =IFERROR(INDEX('PO Index'!$B$5:$B$84,33),"") -> 10891 | C37: =IF($B37="","",IF((IFERROR(INDEX(_RefTable!$B$2:$B$501,MATCH($B37,_RefTable!$C$2:$C$501,0))&IF(COUNTIF(_RefTable!$C$2:$C$501,$B37)>1," (+"&COUNTIF(_RefTable!$C$2:$C$501,$B37)-1&" more)",""),IFERROR(INDEX(_MainTable!$B$2:$B$2001,MATCH($B37,_MainTable!$F$2:$F$2001,0)),"")))&""="","—",(IFERROR(INDEX(_RefTable!$B$2:$B$501,MATCH($B37,_RefTable!$C$2:$C$501,0))&IF(COUNTIF(_RefTable!$C$2:$C$501,$B37)>1," (+"&COUNTIF(_RefTable!$C$2:$C$501,$B37)-1&" more)",""),IFERROR(INDEX(_MainTable!$B$2:$B$2001,MATCH($B37,_MainTable!$F$2:$F$2001,0)),""))))) -> Patient Financing | D37: =IF($B37="","",IF((IFERROR(INDEX(_RefTable!$E$2:$E$501,MATCH($B37,_RefTable!$C$2:$C$501,0)),IFERROR(INDEX(_MainTable!$C$2:$C$2001,MATCH($B37,_MainTable!$F$2:$F$2001,0)),"")))&""="","—",(IFERROR(INDEX(_RefTable!$E$2:$E$501,MATCH($B37,_RefTable!$C$2:$C$501,0)),IFERROR(INDEX(_MainTable!$C$2:$C$2001,MATCH($B37,_MainTable!$F$2:$F$2001,0)),""))))) -> Jake Reid | E37: =IF($B37="","",IF((IFERROR(INDEX(_RefTable!$F$2:$F$501,MATCH($B37,_RefTable!$C$2:$C$501,0)),IFERROR(INDEX(_MainTable!$D$2:$D$2001,MATCH($B37,_MainTable!$F$2:$F$2001,0)),"")))&""="","—",(IFERROR(INDEX(_RefTable!$F$2:$F$501,MATCH($B37,_RefTable!$C$2:$C$501,0)),IFERROR(INDEX(_MainTable!$D$2:$D$2001,MATCH($B37,_MainTable!$F$2:$F$2001,0)),""))))) -> Letisia Speelman | F37: =IF($B37="","",IFERROR(_xlfn.MINIFS('SC Change Orders'!$E$2:$E$501,'SC Change Orders'!$B$2:$B$501,$B37,'SC Change Orders'!$C$2:$C$501,">="&Controls!$C$5,'SC Change Orders'!$C$2:$C$501,"<="&Controls!$C$6),0)) -> 0 | G37: =IF($B37="","",SUMIFS('SC Change Orders'!$F$2:$F$501,'SC Change Orders'!$B$2:$B$501,$B37,'SC Change Orders'!$C$2:$C$501,">="&Controls!$C$5,'SC Change Orders'!$C$2:$C$501,"<="&Controls!$C$6)) -> 0 | H37: =IF($B37="","",$F37+$G37) -> 0 | I37: =IF($B37="","",SUMIFS(_MainTable!$K$2:$K$2001,_MainTable!$F$2:$F$2001,$B37,_MainTable!$G$2:$G$2001,">="&Controls!$C$5,_MainTable!$G$2:$G$2001,"<="&Controls!$C$6)) -> 3696 | J37: =IF($B37="","",IFERROR($I37/$H37,0)) -> 0 | K37: =IF($B37="","",$H37-$I37) -> -3696 | L37: =IF($B37="","",IFERROR(SUMIFS(_MainTable!$K$2:$K$2001,_MainTable!$F$2:$F$2001,$B37,_MainTable!$G$2:$G$2001,">="&Controls!$C$12,_MainTable!$G$2:$G$2001,"<="&EOMONTH(Controls!$C$7,0))/MIN(Controls!$C$9,Controls!$C$10),0)) -> 597.07333 | M37: =IF($B37="","",$L37*Controls!$C$11) -> 1194.1467 | N37: =IF($B37="","",$I37+$M37) -> 4890.1467 | O37: =IF($B37="","",IFERROR($N37/$H37,0)) -> 0 | P37: =IF($B37="","",$H37-$N37) -> -4890.1467 | Q37: =IF($B37="","",IF($L37<=0,"n/a",IFERROR($K37/$L37,"n/a"))) -> -6.1901944 | R37: =IF($B37="","",IF(AND($H37=0,$I37=0),"⚪ No Activity",IF(AND($H37=0,COUNTIFS('SC Change Orders'!$B$2:$B$501,$B37,'SC Change Orders'!$C$2:$C$501,">="&Controls!$C$5,'SC Change Orders'!$C$2:$C$501,"<="&Controls!$C$6)=0),"⚪ No Funding on File",IF($H37=0,"🔴 Unfunded Spend",IF($I37>=$H37,"🔴 Over Budget",IF($N37>$H37,"🔴 Projected Shortfall",IF($J37>=Controls!$C$8,"🟡 Watch","🟢 On Track"))))))) -> ⚪ No Funding on File
A38: =IF($B38="","",IF((IFERROR(INDEX(_RefTable!$A$2:$A$501,MATCH($B38,_RefTable!$C$2:$C$501,0)),IFERROR(INDEX(_MainTable!$A$2:$A$2001,MATCH($B38,_MainTable!$F$2:$F$2001,0)),IFERROR(INDEX('SC Change Orders'!$A$2:$A$501,MATCH($B38,'SC Change Orders'!$B$2:$B$501,0)),"(unknown vendor)"))))&""="","—",(IFERROR(INDEX(_RefTable!$A$2:$A$501,MATCH($B38,_RefTable!$C$2:$C$501,0)),IFERROR(INDEX(_MainTable!$A$2:$A$2001,MATCH($B38,_MainTable!$F$2:$F$2001,0)),IFERROR(INDEX('SC Change Orders'!$A$2:$A$501,MATCH($B38,'SC Change Orders'!$B$2:$B$501,0)),"(unknown vendor)")))))) -> CIOX HEALTH LLC | B38: =IFERROR(INDEX('PO Index'!$B$5:$B$84,34),"") -> 11023 | C38: =IF($B38="","",IF((IFERROR(INDEX(_RefTable!$B$2:$B$501,MATCH($B38,_RefTable!$C$2:$C$501,0))&IF(COUNTIF(_RefTable!$C$2:$C$501,$B38)>1," (+"&COUNTIF(_RefTable!$C$2:$C$501,$B38)-1&" more)",""),IFERROR(INDEX(_MainTable!$B$2:$B$2001,MATCH($B38,_MainTable!$F$2:$F$2001,0)),"")))&""="","—",(IFERROR(INDEX(_RefTable!$B$2:$B$501,MATCH($B38,_RefTable!$C$2:$C$501,0))&IF(COUNTIF(_RefTable!$C$2:$C$501,$B38)>1," (+"&COUNTIF(_RefTable!$C$2:$C$501,$B38)-1&" more)",""),IFERROR(INDEX(_MainTable!$B$2:$B$2001,MATCH($B38,_MainTable!$F$2:$F$2001,0)),""))))) -> Labor Only- ROI | D38: =IF($B38="","",IF((IFERROR(INDEX(_RefTable!$E$2:$E$501,MATCH($B38,_RefTable!$C$2:$C$501,0)),IFERROR(INDEX(_MainTable!$C$2:$C$2001,MATCH($B38,_MainTable!$F$2:$F$2001,0)),"")))&""="","—",(IFERROR(INDEX(_RefTable!$E$2:$E$501,MATCH($B38,_RefTable!$C$2:$C$501,0)),IFERROR(INDEX(_MainTable!$C$2:$C$2001,MATCH($B38,_MainTable!$F$2:$F$2001,0)),""))))) -> Sona Buchanan | E38: =IF($B38="","",IF((IFERROR(INDEX(_RefTable!$F$2:$F$501,MATCH($B38,_RefTable!$C$2:$C$501,0)),IFERROR(INDEX(_MainTable!$D$2:$D$2001,MATCH($B38,_MainTable!$F$2:$F$2001,0)),"")))&""="","—",(IFERROR(INDEX(_RefTable!$F$2:$F$501,MATCH($B38,_RefTable!$C$2:$C$501,0)),IFERROR(INDEX(_MainTable!$D$2:$D$2001,MATCH($B38,_MainTable!$F$2:$F$2001,0)),""))))) -> Melissa Daniels | F38: =IF($B38="","",IFERROR(_xlfn.MINIFS('SC Change Orders'!$E$2:$E$501,'SC Change Orders'!$B$2:$B$501,$B38,'SC Change Orders'!$C$2:$C$501,">="&Controls!$C$5,'SC Change Orders'!$C$2:$C$501,"<="&Controls!$C$6),0)) -> 0 | G38: =IF($B38="","",SUMIFS('SC Change Orders'!$F$2:$F$501,'SC Change Orders'!$B$2:$B$501,$B38,'SC Change Orders'!$C$2:$C$501,">="&Controls!$C$5,'SC Change Orders'!$C$2:$C$501,"<="&Controls!$C$6)) -> 0 | H38: =IF($B38="","",$F38+$G38) -> 0 | I38: =IF($B38="","",SUMIFS(_MainTable!$K$2:$K$2001,_MainTable!$F$2:$F$2001,$B38,_MainTable!$G$2:$G$2001,">="&Controls!$C$5,_MainTable!$G$2:$G$2001,"<="&Controls!$C$6)) -> 41938.75 | J38: =IF($B38="","",IFERROR($I38/$H38,0)) -> 0 | K38: =IF($B38="","",$H38-$I38) -> -41938.75 | L38: =IF($B38="","",IFERROR(SUMIFS(_MainTable!$K$2:$K$2001,_MainTable!$F$2:$F$2001,$B38,_MainTable!$G$2:$G$2001,">="&Controls!$C$12,_MainTable!$G$2:$G$2001,"<="&EOMONTH(Controls!$C$7,0))/MIN(Controls!$C$9,Controls!$C$10),0)) -> 9210.8333 | M38: =IF($B38="","",$L38*Controls!$C$11) -> 18421.667 | N38: =IF($B38="","",$I38+$M38) -> 60360.417 | O38: =IF($B38="","",IFERROR($N38/$H38,0)) -> 0 | P38: =IF($B38="","",$H38-$N38) -> -60360.417 | Q38: =IF($B38="","",IF($L38<=0,"n/a",IFERROR($K38/$L38,"n/a"))) -> -4.5531982 | R38: =IF($B38="","",IF(AND($H38=0,$I38=0),"⚪ No Activity",IF(AND($H38=0,COUNTIFS('SC Change Orders'!$B$2:$B$501,$B38,'SC Change Orders'!$C$2:$C$501,">="&Controls!$C$5,'SC Change Orders'!$C$2:$C$501,"<="&Controls!$C$6)=0),"⚪ No Funding on File",IF($H38=0,"🔴 Unfunded Spend",IF($I38>=$H38,"🔴 Over Budget",IF($N38>$H38,"🔴 Projected Shortfall",IF($J38>=Controls!$C$8,"🟡 Watch","🟢 On Track"))))))) -> ⚪ No Funding on File
A39: =IF($B39="","",IF((IFERROR(INDEX(_RefTable!$A$2:$A$501,MATCH($B39,_RefTable!$C$2:$C$501,0)),IFERROR(INDEX(_MainTable!$A$2:$A$2001,MATCH($B39,_MainTable!$F$2:$F$2001,0)),IFERROR(INDEX('SC Change Orders'!$A$2:$A$501,MATCH($B39,'SC Change Orders'!$B$2:$B$501,0)),"(unknown vendor)"))))&""="","—",(IFERROR(INDEX(_RefTable!$A$2:$A$501,MATCH($B39,_RefTable!$C$2:$C$501,0)),IFERROR(INDEX(_MainTable!$A$2:$A$2001,MATCH($B39,_MainTable!$F$2:$F$2001,0)),IFERROR(INDEX('SC Change Orders'!$A$2:$A$501,MATCH($B39,'SC Change Orders'!$B$2:$B$501,0)),"(unknown vendor)")))))) -> WAYSTAR HEALTH | B39: =IFERROR(INDEX('PO Index'!$B$5:$B$84,35),"") -> 11053 | C39: =IF($B39="","",IF((IFERROR(INDEX(_RefTable!$B$2:$B$501,MATCH($B39,_RefTable!$C$2:$C$501,0))&IF(COUNTIF(_RefTable!$C$2:$C$501,$B39)>1," (+"&COUNTIF(_RefTable!$C$2:$C$501,$B39)-1&" more)",""),IFERROR(INDEX(_MainTable!$B$2:$B$2001,MATCH($B39,_MainTable!$F$2:$F$2001,0)),"")))&""="","—",(IFERROR(INDEX(_RefTable!$B$2:$B$501,MATCH($B39,_RefTable!$C$2:$C$501,0))&IF(COUNTIF(_RefTable!$C$2:$C$501,$B39)>1," (+"&COUNTIF(_RefTable!$C$2:$C$501,$B39)-1&" more)",""),IFERROR(INDEX(_MainTable!$B$2:$B$2001,MATCH($B39,_MainTable!$F$2:$F$2001,0)),""))))) -> Claims Clearinghouse | D39: =IF($B39="","",IF((IFERROR(INDEX(_RefTable!$E$2:$E$501,MATCH($B39,_RefTable!$C$2:$C$501,0)),IFERROR(INDEX(_MainTable!$C$2:$C$2001,MATCH($B39,_MainTable!$F$2:$F$2001,0)),"")))&""="","—",(IFERROR(INDEX(_RefTable!$E$2:$E$501,MATCH($B39,_RefTable!$C$2:$C$501,0)),IFERROR(INDEX(_MainTable!$C$2:$C$2001,MATCH($B39,_MainTable!$F$2:$F$2001,0)),""))))) -> Jake Reid | E39: =IF($B39="","",IF((IFERROR(INDEX(_RefTable!$F$2:$F$501,MATCH($B39,_RefTable!$C$2:$C$501,0)),IFERROR(INDEX(_MainTable!$D$2:$D$2001,MATCH($B39,_MainTable!$F$2:$F$2001,0)),"")))&""="","—",(IFERROR(INDEX(_RefTable!$F$2:$F$501,MATCH($B39,_RefTable!$C$2:$C$501,0)),IFERROR(INDEX(_MainTable!$D$2:$D$2001,MATCH($B39,_MainTable!$F$2:$F$2001,0)),""))))) -> Rodney Frank | F39: =IF($B39="","",IFERROR(_xlfn.MINIFS('SC Change Orders'!$E$2:$E$501,'SC Change Orders'!$B$2:$B$501,$B39,'SC Change Orders'!$C$2:$C$501,">="&Controls!$C$5,'SC Change Orders'!$C$2:$C$501,"<="&Controls!$C$6),0)) -> 216000 | G39: =IF($B39="","",SUMIFS('SC Change Orders'!$F$2:$F$501,'SC Change Orders'!$B$2:$B$501,$B39,'SC Change Orders'!$C$2:$C$501,">="&Controls!$C$5,'SC Change Orders'!$C$2:$C$501,"<="&Controls!$C$6)) -> 760000 | H39: =IF($B39="","",$F39+$G39) -> 976000 | I39: =IF($B39="","",SUMIFS(_MainTable!$K$2:$K$2001,_MainTable!$F$2:$F$2001,$B39,_MainTable!$G$2:$G$2001,">="&Controls!$C$5,_MainTable!$G$2:$G$2001,"<="&Controls!$C$6)) -> 560890.19 | J39: =IF($B39="","",IFERROR($I39/$H39,0)) -> 0.57468257 | K39: =IF($B39="","",$H39-$I39) -> 415109.81 | L39: =IF($B39="","",IFERROR(SUMIFS(_MainTable!$K$2:$K$2001,_MainTable!$F$2:$F$2001,$B39,_MainTable!$G$2:$G$2001,">="&Controls!$C$12,_MainTable!$G$2:$G$2001,"<="&EOMONTH(Controls!$C$7,0))/MIN(Controls!$C$9,Controls!$C$10),0)) -> 122435.21 | M39: =IF($B39="","",$L39*Controls!$C$11) -> 244870.42 | N39: =IF($B39="","",$I39+$M39) -> 805760.61 | O39: =IF($B39="","",IFERROR($N39/$H39,0)) -> 0.8255744 | P39: =IF($B39="","",$H39-$N39) -> 170239.39 | Q39: =IF($B39="","",IF($L39<=0,"n/a",IFERROR($K39/$L39,"n/a"))) -> 3.3904447 | R39: =IF($B39="","",IF(AND($H39=0,$I39=0),"⚪ No Activity",IF(AND($H39=0,COUNTIFS('SC Change Orders'!$B$2:$B$501,$B39,'SC Change Orders'!$C$2:$C$501,">="&Controls!$C$5,'SC Change Orders'!$C$2:$C$501,"<="&Controls!$C$6)=0),"⚪ No Funding on File",IF($H39=0,"🔴 Unfunded Spend",IF($I39>=$H39,"🔴 Over Budget",IF($N39>$H39,"🔴 Projected Shortfall",IF($J39>=Controls!$C$8,"🟡 Watch","🟢 On Track"))))))) -> 🟢 On Track
A40: =IF($B40="","",IF((IFERROR(INDEX(_RefTable!$A$2:$A$501,MATCH($B40,_RefTable!$C$2:$C$501,0)),IFERROR(INDEX(_MainTable!$A$2:$A$2001,MATCH($B40,_MainTable!$F$2:$F$2001,0)),IFERROR(INDEX('SC Change Orders'!$A$2:$A$501,MATCH($B40,'SC Change Orders'!$B$2:$B$501,0)),"(unknown vendor)"))))&""="","—",(IFERROR(INDEX(_RefTable!$A$2:$A$501,MATCH($B40,_RefTable!$C$2:$C$501,0)),IFERROR(INDEX(_MainTable!$A$2:$A$2001,MATCH($B40,_MainTable!$F$2:$F$2001,0)),IFERROR(INDEX('SC Change Orders'!$A$2:$A$501,MATCH($B40,'SC Change Orders'!$B$2:$B$501,0)),"(unknown vendor)")))))) -> CLOUDMED | B40: =IFERROR(INDEX('PO Index'!$B$5:$B$84,36),"") -> 11172 | C40: =IF($B40="","",IF((IFERROR(INDEX(_RefTable!$B$2:$B$501,MATCH($B40,_RefTable!$C$2:$C$501,0))&IF(COUNTIF(_RefTable!$C$2:$C$501,$B40)>1," (+"&COUNTIF(_RefTable!$C$2:$C$501,$B40)-1&" more)",""),IFERROR(INDEX(_MainTable!$B$2:$B$2001,MATCH($B40,_MainTable!$F$2:$F$2001,0)),"")))&""="","—",(IFERROR(INDEX(_RefTable!$B$2:$B$501,MATCH($B40,_RefTable!$C$2:$C$501,0))&IF(COUNTIF(_RefTable!$C$2:$C$501,$B40)>1," (+"&COUNTIF(_RefTable!$C$2:$C$501,$B40)-1&" more)",""),IFERROR(INDEX(_MainTable!$B$2:$B$2001,MATCH($B40,_MainTable!$F$2:$F$2001,0)),""))))) -> Underpayment (+2 more) | D40: =IF($B40="","",IF((IFERROR(INDEX(_RefTable!$E$2:$E$501,MATCH($B40,_RefTable!$C$2:$C$501,0)),IFERROR(INDEX(_MainTable!$C$2:$C$2001,MATCH($B40,_MainTable!$F$2:$F$2001,0)),"")))&""="","—",(IFERROR(INDEX(_RefTable!$E$2:$E$501,MATCH($B40,_RefTable!$C$2:$C$501,0)),IFERROR(INDEX(_MainTable!$C$2:$C$2001,MATCH($B40,_MainTable!$F$2:$F$2001,0)),""))))) -> Jake Reid | E40: =IF($B40="","",IF((IFERROR(INDEX(_RefTable!$F$2:$F$501,MATCH($B40,_RefTable!$C$2:$C$501,0)),IFERROR(INDEX(_MainTable!$D$2:$D$2001,MATCH($B40,_MainTable!$F$2:$F$2001,0)),"")))&""="","—",(IFERROR(INDEX(_RefTable!$F$2:$F$501,MATCH($B40,_RefTable!$C$2:$C$501,0)),IFERROR(INDEX(_MainTable!$D$2:$D$2001,MATCH($B40,_MainTable!$F$2:$F$2001,0)),""))))) -> Cody Thornock | F40: =IF($B40="","",IFERROR(_xlfn.MINIFS('SC Change Orders'!$E$2:$E$501,'SC Change Orders'!$B$2:$B$501,$B40,'SC Change Orders'!$C$2:$C$501,">="&Controls!$C$5,'SC Change Orders'!$C$2:$C$501,"<="&Controls!$C$6),0)) -> 1000000 | G40: =IF($B40="","",SUMIFS('SC Change Orders'!$F$2:$F$501,'SC Change Orders'!$B$2:$B$501,$B40,'SC Change Orders'!$C$2:$C$501,">="&Controls!$C$5,'SC Change Orders'!$C$2:$C$501,"<="&Controls!$C$6)) -> 1600000 | H40: =IF($B40="","",$F40+$G40) -> 2600000 | I40: =IF($B40="","",SUMIFS(_MainTable!$K$2:$K$2001,_MainTable!$F$2:$F$2001,$B40,_MainTable!$G$2:$G$2001,">="&Controls!$C$5,_MainTable!$G$2:$G$2001,"<="&Controls!$C$6)) -> 833466.21 | J40: =IF($B40="","",IFERROR($I40/$H40,0)) -> 0.32056393 | K40: =IF($B40="","",$H40-$I40) -> 1766533.8 | L40: =IF($B40="","",IFERROR(SUMIFS(_MainTable!$K$2:$K$2001,_MainTable!$F$2:$F$2001,$B40,_MainTable!$G$2:$G$2001,">="&Controls!$C$12,_MainTable!$G$2:$G$2001,"<="&EOMONTH(Controls!$C$7,0))/MIN(Controls!$C$9,Controls!$C$10),0)) -> 185433.63 | M40: =IF($B40="","",$L40*Controls!$C$11) -> 370867.25 | N40: =IF($B40="","",$I40+$M40) -> 1204333.5 | O40: =IF($B40="","",IFERROR($N40/$H40,0)) -> 0.46320518 | P40: =IF($B40="","",$H40-$N40) -> 1395666.5 | Q40: =IF($B40="","",IF($L40<=0,"n/a",IFERROR($K40/$L40,"n/a"))) -> 9.5265019 | R40: =IF($B40="","",IF(AND($H40=0,$I40=0),"⚪ No Activity",IF(AND($H40=0,COUNTIFS('SC Change Orders'!$B$2:$B$501,$B40,'SC Change Orders'!$C$2:$C$501,">="&Controls!$C$5,'SC Change Orders'!$C$2:$C$501,"<="&Controls!$C$6)=0),"⚪ No Funding on File",IF($H40=0,"🔴 Unfunded Spend",IF($I40>=$H40,"🔴 Over Budget",IF($N40>$H40,"🔴 Projected Shortfall",IF($J40>=Controls!$C$8,"🟡 Watch","🟢 On Track"))))))) -> 🟢 On Track
A41: =IF($B41="","",IF((IFERROR(INDEX(_RefTable!$A$2:$A$501,MATCH($B41,_RefTable!$C$2:$C$501,0)),IFERROR(INDEX(_MainTable!$A$2:$A$2001,MATCH($B41,_MainTable!$F$2:$F$2001,0)),IFERROR(INDEX('SC Change Orders'!$A$2:$A$501,MATCH($B41,'SC Change Orders'!$B$2:$B$501,0)),"(unknown vendor)"))))&""="","—",(IFERROR(INDEX(_RefTable!$A$2:$A$501,MATCH($B41,_RefTable!$C$2:$C$501,0)),IFERROR(INDEX(_MainTable!$A$2:$A$2001,MATCH($B41,_MainTable!$F$2:$F$2001,0)),IFERROR(INDEX('SC Change Orders'!$A$2:$A$501,MATCH($B41,'SC Change Orders'!$B$2:$B$501,0)),"(unknown vendor)")))))) -> SOLVENTUM HEALTH INFO SYSTEM | B41: =IFERROR(INDEX('PO Index'!$B$5:$B$84,37),"") -> 11217 | C41: =IF($B41="","",IF((IFERROR(INDEX(_RefTable!$B$2:$B$501,MATCH($B41,_RefTable!$C$2:$C$501,0))&IF(COUNTIF(_RefTable!$C$2:$C$501,$B41)>1," (+"&COUNTIF(_RefTable!$C$2:$C$501,$B41)-1&" more)",""),IFERROR(INDEX(_MainTable!$B$2:$B$2001,MATCH($B41,_MainTable!$F$2:$F$2001,0)),"")))&""="","—",(IFERROR(INDEX(_RefTable!$B$2:$B$501,MATCH($B41,_RefTable!$C$2:$C$501,0))&IF(COUNTIF(_RefTable!$C$2:$C$501,$B41)>1," (+"&COUNTIF(_RefTable!$C$2:$C$501,$B41)-1&" more)",""),IFERROR(INDEX(_MainTable!$B$2:$B$2001,MATCH($B41,_MainTable!$F$2:$F$2001,0)),""))))) -> CAC (+1 more) | D41: =IF($B41="","",IF((IFERROR(INDEX(_RefTable!$E$2:$E$501,MATCH($B41,_RefTable!$C$2:$C$501,0)),IFERROR(INDEX(_MainTable!$C$2:$C$2001,MATCH($B41,_MainTable!$F$2:$F$2001,0)),"")))&""="","—",(IFERROR(INDEX(_RefTable!$E$2:$E$501,MATCH($B41,_RefTable!$C$2:$C$501,0)),IFERROR(INDEX(_MainTable!$C$2:$C$2001,MATCH($B41,_MainTable!$F$2:$F$2001,0)),""))))) -> Sona Buchanan | E41: =IF($B41="","",IF((IFERROR(INDEX(_RefTable!$F$2:$F$501,MATCH($B41,_RefTable!$C$2:$C$501,0)),IFERROR(INDEX(_MainTable!$D$2:$D$2001,MATCH($B41,_MainTable!$F$2:$F$2001,0)),"")))&""="","—",(IFERROR(INDEX(_RefTable!$F$2:$F$501,MATCH($B41,_RefTable!$C$2:$C$501,0)),IFERROR(INDEX(_MainTable!$D$2:$D$2001,MATCH($B41,_MainTable!$F$2:$F$2001,0)),""))))) -> Heather Geile | F41: =IF($B41="","",IFERROR(_xlfn.MINIFS('SC Change Orders'!$E$2:$E$501,'SC Change Orders'!$B$2:$B$501,$B41,'SC Change Orders'!$C$2:$C$501,">="&Controls!$C$5,'SC Change Orders'!$C$2:$C$501,"<="&Controls!$C$6),0)) -> 0 | G41: =IF($B41="","",SUMIFS('SC Change Orders'!$F$2:$F$501,'SC Change Orders'!$B$2:$B$501,$B41,'SC Change Orders'!$C$2:$C$501,">="&Controls!$C$5,'SC Change Orders'!$C$2:$C$501,"<="&Controls!$C$6)) -> 0 | H41: =IF($B41="","",$F41+$G41) -> 0 | I41: =IF($B41="","",SUMIFS(_MainTable!$K$2:$K$2001,_MainTable!$F$2:$F$2001,$B41,_MainTable!$G$2:$G$2001,">="&Controls!$C$5,_MainTable!$G$2:$G$2001,"<="&Controls!$C$6)) -> 441141.26 | J41: =IF($B41="","",IFERROR($I41/$H41,0)) -> 0 | K41: =IF($B41="","",$H41-$I41) -> -441141.26 | L41: =IF($B41="","",IFERROR(SUMIFS(_MainTable!$K$2:$K$2001,_MainTable!$F$2:$F$2001,$B41,_MainTable!$G$2:$G$2001,">="&Controls!$C$12,_MainTable!$G$2:$G$2001,"<="&EOMONTH(Controls!$C$7,0))/MIN(Controls!$C$9,Controls!$C$10),0)) -> 147047.09 | M41: =IF($B41="","",$L41*Controls!$C$11) -> 294094.17 | N41: =IF($B41="","",$I41+$M41) -> 735235.43 | O41: =IF($B41="","",IFERROR($N41/$H41,0)) -> 0 | P41: =IF($B41="","",$H41-$N41) -> -735235.43 | Q41: =IF($B41="","",IF($L41<=0,"n/a",IFERROR($K41/$L41,"n/a"))) -> -3 | R41: =IF($B41="","",IF(AND($H41=0,$I41=0),"⚪ No Activity",IF(AND($H41=0,COUNTIFS('SC Change Orders'!$B$2:$B$501,$B41,'SC Change Orders'!$C$2:$C$501,">="&Controls!$C$5,'SC Change Orders'!$C$2:$C$501,"<="&Controls!$C$6)=0),"⚪ No Funding on File",IF($H41=0,"🔴 Unfunded Spend",IF($I41>=$H41,"🔴 Over Budget",IF($N41>$H41,"🔴 Projected Shortfall",IF($J41>=Controls!$C$8,"🟡 Watch","🟢 On Track"))))))) -> ⚪ No Funding on File
A42: =IF($B42="","",IF((IFERROR(INDEX(_RefTable!$A$2:$A$501,MATCH($B42,_RefTable!$C$2:$C$501,0)),IFERROR(INDEX(_MainTable!$A$2:$A$2001,MATCH($B42,_MainTable!$F$2:$F$2001,0)),IFERROR(INDEX('SC Change Orders'!$A$2:$A$501,MATCH($B42,'SC Change Orders'!$B$2:$B$501,0)),"(unknown vendor)"))))&""="","—",(IFERROR(INDEX(_RefTable!$A$2:$A$501,MATCH($B42,_RefTable!$C$2:$C$501,0)),IFERROR(INDEX(_MainTable!$A$2:$A$2001,MATCH($B42,_MainTable!$F$2:$F$2001,0)),IFERROR(INDEX('SC Change Orders'!$A$2:$A$501,MATCH($B42,'SC Change Orders'!$B$2:$B$501,0)),"(unknown vendor)")))))) -> GUIDEHOUSE INC | B42: =IFERROR(INDEX('PO Index'!$B$5:$B$84,38),"") -> 11587 | C42: =IF($B42="","",IF((IFERROR(INDEX(_RefTable!$B$2:$B$501,MATCH($B42,_RefTable!$C$2:$C$501,0))&IF(COUNTIF(_RefTable!$C$2:$C$501,$B42)>1," (+"&COUNTIF(_RefTable!$C$2:$C$501,$B42)-1&" more)",""),IFERROR(INDEX(_MainTable!$B$2:$B$2001,MATCH($B42,_MainTable!$F$2:$F$2001,0)),"")))&""="","—",(IFERROR(INDEX(_RefTable!$B$2:$B$501,MATCH($B42,_RefTable!$C$2:$C$501,0))&IF(COUNTIF(_RefTable!$C$2:$C$501,$B42)>1," (+"&COUNTIF(_RefTable!$C$2:$C$501,$B42)-1&" more)",""),IFERROR(INDEX(_MainTable!$B$2:$B$2001,MATCH($B42,_MainTable!$F$2:$F$2001,0)),""))))) -> CCC | D42: =IF($B42="","",IF((IFERROR(INDEX(_RefTable!$E$2:$E$501,MATCH($B42,_RefTable!$C$2:$C$501,0)),IFERROR(INDEX(_MainTable!$C$2:$C$2001,MATCH($B42,_MainTable!$F$2:$F$2001,0)),"")))&""="","—",(IFERROR(INDEX(_RefTable!$E$2:$E$501,MATCH($B42,_RefTable!$C$2:$C$501,0)),IFERROR(INDEX(_MainTable!$C$2:$C$2001,MATCH($B42,_MainTable!$F$2:$F$2001,0)),""))))) -> Anne Jensen | E42: =IF($B42="","",IF((IFERROR(INDEX(_RefTable!$F$2:$F$501,MATCH($B42,_RefTable!$C$2:$C$501,0)),IFERROR(INDEX(_MainTable!$D$2:$D$2001,MATCH($B42,_MainTable!$F$2:$F$2001,0)),"")))&""="","—",(IFERROR(INDEX(_RefTable!$F$2:$F$501,MATCH($B42,_RefTable!$C$2:$C$501,0)),IFERROR(INDEX(_MainTable!$D$2:$D$2001,MATCH($B42,_MainTable!$F$2:$F$2001,0)),""))))) -> Laney Rivera | F42: =IF($B42="","",IFERROR(_xlfn.MINIFS('SC Change Orders'!$E$2:$E$501,'SC Change Orders'!$B$2:$B$501,$B42,'SC Change Orders'!$C$2:$C$501,">="&Controls!$C$5,'SC Change Orders'!$C$2:$C$501,"<="&Controls!$C$6),0)) -> 0 | G42: =IF($B42="","",SUMIFS('SC Change Orders'!$F$2:$F$501,'SC Change Orders'!$B$2:$B$501,$B42,'SC Change Orders'!$C$2:$C$501,">="&Controls!$C$5,'SC Change Orders'!$C$2:$C$501,"<="&Controls!$C$6)) -> 0 | H42: =IF($B42="","",$F42+$G42) -> 0 | I42: =IF($B42="","",SUMIFS(_MainTable!$K$2:$K$2001,_MainTable!$F$2:$F$2001,$B42,_MainTable!$G$2:$G$2001,">="&Controls!$C$5,_MainTable!$G$2:$G$2001,"<="&Controls!$C$6)) -> 64750 | J42: =IF($B42="","",IFERROR($I42/$H42,0)) -> 0 | K42: =IF($B42="","",$H42-$I42) -> -64750 | L42: =IF($B42="","",IFERROR(SUMIFS(_MainTable!$K$2:$K$2001,_MainTable!$F$2:$F$2001,$B42,_MainTable!$G$2:$G$2001,">="&Controls!$C$12,_MainTable!$G$2:$G$2001,"<="&EOMONTH(Controls!$C$7,0))/MIN(Controls!$C$9,Controls!$C$10),0)) -> 12950 | M42: =IF($B42="","",$L42*Controls!$C$11) -> 25900 | N42: =IF($B42="","",$I42+$M42) -> 90650 | O42: =IF($B42="","",IFERROR($N42/$H42,0)) -> 0 | P42: =IF($B42="","",$H42-$N42) -> -90650 | Q42: =IF($B42="","",IF($L42<=0,"n/a",IFERROR($K42/$L42,"n/a"))) -> -5 | R42: =IF($B42="","",IF(AND($H42=0,$I42=0),"⚪ No Activity",IF(AND($H42=0,COUNTIFS('SC Change Orders'!$B$2:$B$501,$B42,'SC Change Orders'!$C$2:$C$501,">="&Controls!$C$5,'SC Change Orders'!$C$2:$C$501,"<="&Controls!$C$6)=0),"⚪ No Funding on File",IF($H42=0,"🔴 Unfunded Spend",IF($I42>=$H42,"🔴 Over Budget",IF($N42>$H42,"🔴 Projected Shortfall",IF($J42>=Controls!$C$8,"🟡 Watch","🟢 On Track"))))))) -> ⚪ No Funding on File
A43: =IF($B43="","",IF((IFERROR(INDEX(_RefTable!$A$2:$A$501,MATCH($B43,_RefTable!$C$2:$C$501,0)),IFERROR(INDEX(_MainTable!$A$2:$A$2001,MATCH($B43,_MainTable!$F$2:$F$2001,0)),IFERROR(INDEX('SC Change Orders'!$A$2:$A$501,MATCH($B43,'SC Change Orders'!$B$2:$B$501,0)),"(unknown vendor)"))))&""="","—",(IFERROR(INDEX(_RefTable!$A$2:$A$501,MATCH($B43,_RefTable!$C$2:$C$501,0)),IFERROR(INDEX(_MainTable!$A$2:$A$2001,MATCH($B43,_MainTable!$F$2:$F$2001,0)),IFERROR(INDEX('SC Change Orders'!$A$2:$A$501,MATCH($B43,'SC Change Orders'!$B$2:$B$501,0)),"(unknown vendor)")))))) -> WAYSTAR HEALTH | B43: =IFERROR(INDEX('PO Index'!$B$5:$B$84,39),"") -> 11631 | C43: =IF($B43="","",IF((IFERROR(INDEX(_RefTable!$B$2:$B$501,MATCH($B43,_RefTable!$C$2:$C$501,0))&IF(COUNTIF(_RefTable!$C$2:$C$501,$B43)>1," (+"&COUNTIF(_RefTable!$C$2:$C$501,$B43)-1&" more)",""),IFERROR(INDEX(_MainTable!$B$2:$B$2001,MATCH($B43,_MainTable!$F$2:$F$2001,0)),"")))&""="","—",(IFERROR(INDEX(_RefTable!$B$2:$B$501,MATCH($B43,_RefTable!$C$2:$C$501,0))&IF(COUNTIF(_RefTable!$C$2:$C$501,$B43)>1," (+"&COUNTIF(_RefTable!$C$2:$C$501,$B43)-1&" more)",""),IFERROR(INDEX(_MainTable!$B$2:$B$2001,MATCH($B43,_MainTable!$F$2:$F$2001,0)),""))))) -> RTA Auth | D43: =IF($B43="","",IF((IFERROR(INDEX(_RefTable!$E$2:$E$501,MATCH($B43,_RefTable!$C$2:$C$501,0)),IFERROR(INDEX(_MainTable!$C$2:$C$2001,MATCH($B43,_MainTable!$F$2:$F$2001,0)),"")))&""="","—",(IFERROR(INDEX(_RefTable!$E$2:$E$501,MATCH($B43,_RefTable!$C$2:$C$501,0)),IFERROR(INDEX(_MainTable!$C$2:$C$2001,MATCH($B43,_MainTable!$F$2:$F$2001,0)),""))))) -> Rachel Seaman | E43: =IF($B43="","",IF((IFERROR(INDEX(_RefTable!$F$2:$F$501,MATCH($B43,_RefTable!$C$2:$C$501,0)),IFERROR(INDEX(_MainTable!$D$2:$D$2001,MATCH($B43,_MainTable!$F$2:$F$2001,0)),"")))&""="","—",(IFERROR(INDEX(_RefTable!$F$2:$F$501,MATCH($B43,_RefTable!$C$2:$C$501,0)),IFERROR(INDEX(_MainTable!$D$2:$D$2001,MATCH($B43,_MainTable!$F$2:$F$2001,0)),""))))) -> Becca Osmanagic | F43: =IF($B43="","",IFERROR(_xlfn.MINIFS('SC Change Orders'!$E$2:$E$501,'SC Change Orders'!$B$2:$B$501,$B43,'SC Change Orders'!$C$2:$C$501,">="&Controls!$C$5,'SC Change Orders'!$C$2:$C$501,"<="&Controls!$C$6),0)) -> 135960 | G43: =IF($B43="","",SUMIFS('SC Change Orders'!$F$2:$F$501,'SC Change Orders'!$B$2:$B$501,$B43,'SC Change Orders'!$C$2:$C$501,">="&Controls!$C$5,'SC Change Orders'!$C$2:$C$501,"<="&Controls!$C$6)) -> 132000 | H43: =IF($B43="","",$F43+$G43) -> 267960 | I43: =IF($B43="","",SUMIFS(_MainTable!$K$2:$K$2001,_MainTable!$F$2:$F$2001,$B43,_MainTable!$G$2:$G$2001,">="&Controls!$C$5,_MainTable!$G$2:$G$2001,"<="&Controls!$C$6)) -> 264000 | J43: =IF($B43="","",IFERROR($I43/$H43,0)) -> 0.98522167 | K43: =IF($B43="","",$H43-$I43) -> 3960 | L43: =IF($B43="","",IFERROR(SUMIFS(_MainTable!$K$2:$K$2001,_MainTable!$F$2:$F$2001,$B43,_MainTable!$G$2:$G$2001,">="&Controls!$C$12,_MainTable!$G$2:$G$2001,"<="&EOMONTH(Controls!$C$7,0))/MIN(Controls!$C$9,Controls!$C$10),0)) -> 0 | M43: =IF($B43="","",$L43*Controls!$C$11) -> 0 | N43: =IF($B43="","",$I43+$M43) -> 264000 | O43: =IF($B43="","",IFERROR($N43/$H43,0)) -> 0.98522167 | P43: =IF($B43="","",$H43-$N43) -> 3960 | Q43: =IF($B43="","",IF($L43<=0,"n/a",IFERROR($K43/$L43,"n/a"))) -> n/a | R43: =IF($B43="","",IF(AND($H43=0,$I43=0),"⚪ No Activity",IF(AND($H43=0,COUNTIFS('SC Change Orders'!$B$2:$B$501,$B43,'SC Change Orders'!$C$2:$C$501,">="&Controls!$C$5,'SC Change Orders'!$C$2:$C$501,"<="&Controls!$C$6)=0),"⚪ No Funding on File",IF($H43=0,"🔴 Unfunded Spend",IF($I43>=$H43,"🔴 Over Budget",IF($N43>$H43,"🔴 Projected Shortfall",IF($J43>=Controls!$C$8,"🟡 Watch","🟢 On Track"))))))) -> 🟡 Watch
A44: =IF($B44="","",IF((IFERROR(INDEX(_RefTable!$A$2:$A$501,MATCH($B44,_RefTable!$C$2:$C$501,0)),IFERROR(INDEX(_MainTable!$A$2:$A$2001,MATCH($B44,_MainTable!$F$2:$F$2001,0)),IFERROR(INDEX('SC Change Orders'!$A$2:$A$501,MATCH($B44,'SC Change Orders'!$B$2:$B$501,0)),"(unknown vendor)"))))&""="","—",(IFERROR(INDEX(_RefTable!$A$2:$A$501,MATCH($B44,_RefTable!$C$2:$C$501,0)),IFERROR(INDEX(_MainTable!$A$2:$A$2001,MATCH($B44,_MainTable!$F$2:$F$2001,0)),IFERROR(INDEX('SC Change Orders'!$A$2:$A$501,MATCH($B44,'SC Change Orders'!$B$2:$B$501,0)),"(unknown vendor)")))))) -> HEALTHSTREAM | B44: =IFERROR(INDEX('PO Index'!$B$5:$B$84,40),"") -> 11778 | C44: =IF($B44="","",IF((IFERROR(INDEX(_RefTable!$B$2:$B$501,MATCH($B44,_RefTable!$C$2:$C$501,0))&IF(COUNTIF(_RefTable!$C$2:$C$501,$B44)>1," (+"&COUNTIF(_RefTable!$C$2:$C$501,$B44)-1&" more)",""),IFERROR(INDEX(_MainTable!$B$2:$B$2001,MATCH($B44,_MainTable!$F$2:$F$2001,0)),"")))&""="","—",(IFERROR(INDEX(_RefTable!$B$2:$B$501,MATCH($B44,_RefTable!$C$2:$C$501,0))&IF(COUNTIF(_RefTable!$C$2:$C$501,$B44)>1," (+"&COUNTIF(_RefTable!$C$2:$C$501,$B44)-1&" more)",""),IFERROR(INDEX(_MainTable!$B$2:$B$2001,MATCH($B44,_MainTable!$F$2:$F$2001,0)),""))))) -> Education | D44: =IF($B44="","",IF((IFERROR(INDEX(_RefTable!$E$2:$E$501,MATCH($B44,_RefTable!$C$2:$C$501,0)),IFERROR(INDEX(_MainTable!$C$2:$C$2001,MATCH($B44,_MainTable!$F$2:$F$2001,0)),"")))&""="","—",(IFERROR(INDEX(_RefTable!$E$2:$E$501,MATCH($B44,_RefTable!$C$2:$C$501,0)),IFERROR(INDEX(_MainTable!$C$2:$C$2001,MATCH($B44,_MainTable!$F$2:$F$2001,0)),""))))) -> Adam Vardaman | E44: =IF($B44="","",IF((IFERROR(INDEX(_RefTable!$F$2:$F$501,MATCH($B44,_RefTable!$C$2:$C$501,0)),IFERROR(INDEX(_MainTable!$D$2:$D$2001,MATCH($B44,_MainTable!$F$2:$F$2001,0)),"")))&""="","—",(IFERROR(INDEX(_RefTable!$F$2:$F$501,MATCH($B44,_RefTable!$C$2:$C$501,0)),IFERROR(INDEX(_MainTable!$D$2:$D$2001,MATCH($B44,_MainTable!$F$2:$F$2001,0)),""))))) -> Heather Geile | F44: =IF($B44="","",IFERROR(_xlfn.MINIFS('SC Change Orders'!$E$2:$E$501,'SC Change Orders'!$B$2:$B$501,$B44,'SC Change Orders'!$C$2:$C$501,">="&Controls!$C$5,'SC Change Orders'!$C$2:$C$501,"<="&Controls!$C$6),0)) -> 0 | G44: =IF($B44="","",SUMIFS('SC Change Orders'!$F$2:$F$501,'SC Change Orders'!$B$2:$B$501,$B44,'SC Change Orders'!$C$2:$C$501,">="&Controls!$C$5,'SC Change Orders'!$C$2:$C$501,"<="&Controls!$C$6)) -> 0 | H44: =IF($B44="","",$F44+$G44) -> 0 | I44: =IF($B44="","",SUMIFS(_MainTable!$K$2:$K$2001,_MainTable!$F$2:$F$2001,$B44,_MainTable!$G$2:$G$2001,">="&Controls!$C$5,_MainTable!$G$2:$G$2001,"<="&Controls!$C$6)) -> 194937.93 | J44: =IF($B44="","",IFERROR($I44/$H44,0)) -> 0 | K44: =IF($B44="","",$H44-$I44) -> -194937.93 | L44: =IF($B44="","",IFERROR(SUMIFS(_MainTable!$K$2:$K$2001,_MainTable!$F$2:$F$2001,$B44,_MainTable!$G$2:$G$2001,">="&Controls!$C$12,_MainTable!$G$2:$G$2001,"<="&EOMONTH(Controls!$C$7,0))/MIN(Controls!$C$9,Controls!$C$10),0)) -> 0 | M44: =IF($B44="","",$L44*Controls!$C$11) -> 0 | N44: =IF($B44="","",$I44+$M44) -> 194937.93 | O44: =IF($B44="","",IFERROR($N44/$H44,0)) -> 0 | P44: =IF($B44="","",$H44-$N44) -> -194937.93 | Q44: =IF($B44="","",IF($L44<=0,"n/a",IFERROR($K44/$L44,"n/a"))) -> n/a | R44: =IF($B44="","",IF(AND($H44=0,$I44=0),"⚪ No Activity",IF(AND($H44=0,COUNTIFS('SC Change Orders'!$B$2:$B$501,$B44,'SC Change Orders'!$C$2:$C$501,">="&Controls!$C$5,'SC Change Orders'!$C$2:$C$501,"<="&Controls!$C$6)=0),"⚪ No Funding on File",IF($H44=0,"🔴 Unfunded Spend",IF($I44>=$H44,"🔴 Over Budget",IF($N44>$H44,"🔴 Projected Shortfall",IF($J44>=Controls!$C$8,"🟡 Watch","🟢 On Track"))))))) -> ⚪ No Funding on File
A45: =IF($B45="","",IF((IFERROR(INDEX(_RefTable!$A$2:$A$501,MATCH($B45,_RefTable!$C$2:$C$501,0)),IFERROR(INDEX(_MainTable!$A$2:$A$2001,MATCH($B45,_MainTable!$F$2:$F$2001,0)),IFERROR(INDEX('SC Change Orders'!$A$2:$A$501,MATCH($B45,'SC Change Orders'!$B$2:$B$501,0)),"(unknown vendor)"))))&""="","—",(IFERROR(INDEX(_RefTable!$A$2:$A$501,MATCH($B45,_RefTable!$C$2:$C$501,0)),IFERROR(INDEX(_MainTable!$A$2:$A$2001,MATCH($B45,_MainTable!$F$2:$F$2001,0)),IFERROR(INDEX('SC Change Orders'!$A$2:$A$501,MATCH($B45,'SC Change Orders'!$B$2:$B$501,0)),"(unknown vendor)")))))) -> MEDLYTIX LLC | B45: =IFERROR(INDEX('PO Index'!$B$5:$B$84,41),"") -> 12088 | C45: =IF($B45="","",IF((IFERROR(INDEX(_RefTable!$B$2:$B$501,MATCH($B45,_RefTable!$C$2:$C$501,0))&IF(COUNTIF(_RefTable!$C$2:$C$501,$B45)>1," (+"&COUNTIF(_RefTable!$C$2:$C$501,$B45)-1&" more)",""),IFERROR(INDEX(_MainTable!$B$2:$B$2001,MATCH($B45,_MainTable!$F$2:$F$2001,0)),"")))&""="","—",(IFERROR(INDEX(_RefTable!$B$2:$B$501,MATCH($B45,_RefTable!$C$2:$C$501,0))&IF(COUNTIF(_RefTable!$C$2:$C$501,$B45)>1," (+"&COUNTIF(_RefTable!$C$2:$C$501,$B45)-1&" more)",""),IFERROR(INDEX(_MainTable!$B$2:$B$2001,MATCH($B45,_MainTable!$F$2:$F$2001,0)),""))))) -> Coverage Detection | D45: =IF($B45="","",IF((IFERROR(INDEX(_RefTable!$E$2:$E$501,MATCH($B45,_RefTable!$C$2:$C$501,0)),IFERROR(INDEX(_MainTable!$C$2:$C$2001,MATCH($B45,_MainTable!$F$2:$F$2001,0)),"")))&""="","—",(IFERROR(INDEX(_RefTable!$E$2:$E$501,MATCH($B45,_RefTable!$C$2:$C$501,0)),IFERROR(INDEX(_MainTable!$C$2:$C$2001,MATCH($B45,_MainTable!$F$2:$F$2001,0)),""))))) -> Anne Jensen | E45: =IF($B45="","",IF((IFERROR(INDEX(_RefTable!$F$2:$F$501,MATCH($B45,_RefTable!$C$2:$C$501,0)),IFERROR(INDEX(_MainTable!$D$2:$D$2001,MATCH($B45,_MainTable!$F$2:$F$2001,0)),"")))&""="","—",(IFERROR(INDEX(_RefTable!$F$2:$F$501,MATCH($B45,_RefTable!$C$2:$C$501,0)),IFERROR(INDEX(_MainTable!$D$2:$D$2001,MATCH($B45,_MainTable!$F$2:$F$2001,0)),""))))) -> Laney Rivera | F45: =IF($B45="","",IFERROR(_xlfn.MINIFS('SC Change Orders'!$E$2:$E$501,'SC Change Orders'!$B$2:$B$501,$B45,'SC Change Orders'!$C$2:$C$501,">="&Controls!$C$5,'SC Change Orders'!$C$2:$C$501,"<="&Controls!$C$6),0)) -> 0 | G45: =IF($B45="","",SUMIFS('SC Change Orders'!$F$2:$F$501,'SC Change Orders'!$B$2:$B$501,$B45,'SC Change Orders'!$C$2:$C$501,">="&Controls!$C$5,'SC Change Orders'!$C$2:$C$501,"<="&Controls!$C$6)) -> 0 | H45: =IF($B45="","",$F45+$G45) -> 0 | I45: =IF($B45="","",SUMIFS(_MainTable!$K$2:$K$2001,_MainTable!$F$2:$F$2001,$B45,_MainTable!$G$2:$G$2001,">="&Controls!$C$5,_MainTable!$G$2:$G$2001,"<="&Controls!$C$6)) -> 66407.26 | J45: =IF($B45="","",IFERROR($I45/$H45,0)) -> 0 | K45: =IF($B45="","",$H45-$I45) -> -66407.26 | L45: =IF($B45="","",IFERROR(SUMIFS(_MainTable!$K$2:$K$2001,_MainTable!$F$2:$F$2001,$B45,_MainTable!$G$2:$G$2001,">="&Controls!$C$12,_MainTable!$G$2:$G$2001,"<="&EOMONTH(Controls!$C$7,0))/MIN(Controls!$C$9,Controls!$C$10),0)) -> 22135.753 | M45: =IF($B45="","",$L45*Controls!$C$11) -> 44271.507 | N45: =IF($B45="","",$I45+$M45) -> 110678.77 | O45: =IF($B45="","",IFERROR($N45/$H45,0)) -> 0 | P45: =IF($B45="","",$H45-$N45) -> -110678.77 | Q45: =IF($B45="","",IF($L45<=0,"n/a",IFERROR($K45/$L45,"n/a"))) -> -3 | R45: =IF($B45="","",IF(AND($H45=0,$I45=0),"⚪ No Activity",IF(AND($H45=0,COUNTIFS('SC Change Orders'!$B$2:$B$501,$B45,'SC Change Orders'!$C$2:$C$501,">="&Controls!$C$5,'SC Change Orders'!$C$2:$C$501,"<="&Controls!$C$6)=0),"⚪ No Funding on File",IF($H45=0,"🔴 Unfunded Spend",IF($I45>=$H45,"🔴 Over Budget",IF($N45>$H45,"🔴 Projected Shortfall",IF($J45>=Controls!$C$8,"🟡 Watch","🟢 On Track"))))))) -> 🔴 Unfunded Spend
A46: =IF($B46="","",IF((IFERROR(INDEX(_RefTable!$A$2:$A$501,MATCH($B46,_RefTable!$C$2:$C$501,0)),IFERROR(INDEX(_MainTable!$A$2:$A$2001,MATCH($B46,_MainTable!$F$2:$F$2001,0)),IFERROR(INDEX('SC Change Orders'!$A$2:$A$501,MATCH($B46,'SC Change Orders'!$B$2:$B$501,0)),"(unknown vendor)"))))&""="","—",(IFERROR(INDEX(_RefTable!$A$2:$A$501,MATCH($B46,_RefTable!$C$2:$C$501,0)),IFERROR(INDEX(_MainTable!$A$2:$A$2001,MATCH($B46,_MainTable!$F$2:$F$2001,0)),IFERROR(INDEX('SC Change Orders'!$A$2:$A$501,MATCH($B46,'SC Change Orders'!$B$2:$B$501,0)),"(unknown vendor)")))))) -> HYVE HEALTHCARE | B46: =IFERROR(INDEX('PO Index'!$B$5:$B$84,42),"") -> 12263 | C46: =IF($B46="","",IF((IFERROR(INDEX(_RefTable!$B$2:$B$501,MATCH($B46,_RefTable!$C$2:$C$501,0))&IF(COUNTIF(_RefTable!$C$2:$C$501,$B46)>1," (+"&COUNTIF(_RefTable!$C$2:$C$501,$B46)-1&" more)",""),IFERROR(INDEX(_MainTable!$B$2:$B$2001,MATCH($B46,_MainTable!$F$2:$F$2001,0)),"")))&""="","—",(IFERROR(INDEX(_RefTable!$B$2:$B$501,MATCH($B46,_RefTable!$C$2:$C$501,0))&IF(COUNTIF(_RefTable!$C$2:$C$501,$B46)>1," (+"&COUNTIF(_RefTable!$C$2:$C$501,$B46)-1&" more)",""),IFERROR(INDEX(_MainTable!$B$2:$B$2001,MATCH($B46,_MainTable!$F$2:$F$2001,0)),""))))) -> Price Transparency | D46: =IF($B46="","",IF((IFERROR(INDEX(_RefTable!$E$2:$E$501,MATCH($B46,_RefTable!$C$2:$C$501,0)),IFERROR(INDEX(_MainTable!$C$2:$C$2001,MATCH($B46,_MainTable!$F$2:$F$2001,0)),"")))&""="","—",(IFERROR(INDEX(_RefTable!$E$2:$E$501,MATCH($B46,_RefTable!$C$2:$C$501,0)),IFERROR(INDEX(_MainTable!$C$2:$C$2001,MATCH($B46,_MainTable!$F$2:$F$2001,0)),""))))) -> Matthew Morishita | E46: =IF($B46="","",IF((IFERROR(INDEX(_RefTable!$F$2:$F$501,MATCH($B46,_RefTable!$C$2:$C$501,0)),IFERROR(INDEX(_MainTable!$D$2:$D$2001,MATCH($B46,_MainTable!$F$2:$F$2001,0)),"")))&""="","—",(IFERROR(INDEX(_RefTable!$F$2:$F$501,MATCH($B46,_RefTable!$C$2:$C$501,0)),IFERROR(INDEX(_MainTable!$D$2:$D$2001,MATCH($B46,_MainTable!$F$2:$F$2001,0)),""))))) -> Amanda Leroue | F46: =IF($B46="","",IFERROR(_xlfn.MINIFS('SC Change Orders'!$E$2:$E$501,'SC Change Orders'!$B$2:$B$501,$B46,'SC Change Orders'!$C$2:$C$501,">="&Controls!$C$5,'SC Change Orders'!$C$2:$C$501,"<="&Controls!$C$6),0)) -> 96000 | G46: =IF($B46="","",SUMIFS('SC Change Orders'!$F$2:$F$501,'SC Change Orders'!$B$2:$B$501,$B46,'SC Change Orders'!$C$2:$C$501,">="&Controls!$C$5,'SC Change Orders'!$C$2:$C$501,"<="&Controls!$C$6)) -> 0 | H46: =IF($B46="","",$F46+$G46) -> 96000 | I46: =IF($B46="","",SUMIFS(_MainTable!$K$2:$K$2001,_MainTable!$F$2:$F$2001,$B46,_MainTable!$G$2:$G$2001,">="&Controls!$C$5,_MainTable!$G$2:$G$2001,"<="&Controls!$C$6)) -> 0 | J46: =IF($B46="","",IFERROR($I46/$H46,0)) -> 0 | K46: =IF($B46="","",$H46-$I46) -> 96000 | L46: =IF($B46="","",IFERROR(SUMIFS(_MainTable!$K$2:$K$2001,_MainTable!$F$2:$F$2001,$B46,_MainTable!$G$2:$G$2001,">="&Controls!$C$12,_MainTable!$G$2:$G$2001,"<="&EOMONTH(Controls!$C$7,0))/MIN(Controls!$C$9,Controls!$C$10),0)) -> 0 | M46: =IF($B46="","",$L46*Controls!$C$11) -> 0 | N46: =IF($B46="","",$I46+$M46) -> 0 | O46: =IF($B46="","",IFERROR($N46/$H46,0)) -> 0 | P46: =IF($B46="","",$H46-$N46) -> 96000 | Q46: =IF($B46="","",IF($L46<=0,"n/a",IFERROR($K46/$L46,"n/a"))) -> n/a | R46: =IF($B46="","",IF(AND($H46=0,$I46=0),"⚪ No Activity",IF(AND($H46=0,COUNTIFS('SC Change Orders'!$B$2:$B$501,$B46,'SC Change Orders'!$C$2:$C$501,">="&Controls!$C$5,'SC Change Orders'!$C$2:$C$501,"<="&Controls!$C$6)=0),"⚪ No Funding on File",IF($H46=0,"🔴 Unfunded Spend",IF($I46>=$H46,"🔴 Over Budget",IF($N46>$H46,"🔴 Projected Shortfall",IF($J46>=Controls!$C$8,"🟡 Watch","🟢 On Track"))))))) -> 🟢 On Track
A47: =IF($B47="","",IF((IFERROR(INDEX(_RefTable!$A$2:$A$501,MATCH($B47,_RefTable!$C$2:$C$501,0)),IFERROR(INDEX(_MainTable!$A$2:$A$2001,MATCH($B47,_MainTable!$F$2:$F$2001,0)),IFERROR(INDEX('SC Change Orders'!$A$2:$A$501,MATCH($B47,'SC Change Orders'!$B$2:$B$501,0)),"(unknown vendor)"))))&""="","—",(IFERROR(INDEX(_RefTable!$A$2:$A$501,MATCH($B47,_RefTable!$C$2:$C$501,0)),IFERROR(INDEX(_MainTable!$A$2:$A$2001,MATCH($B47,_MainTable!$F$2:$F$2001,0)),IFERROR(INDEX('SC Change Orders'!$A$2:$A$501,MATCH($B47,'SC Change Orders'!$B$2:$B$501,0)),"(unknown vendor)")))))) -> UNITED AUDIT SYSTEMS INC | B47: =IFERROR(INDEX('PO Index'!$B$5:$B$84,43),"") -> 12584 | C47: =IF($B47="","",IF((IFERROR(INDEX(_RefTable!$B$2:$B$501,MATCH($B47,_RefTable!$C$2:$C$501,0))&IF(COUNTIF(_RefTable!$C$2:$C$501,$B47)>1," (+"&COUNTIF(_RefTable!$C$2:$C$501,$B47)-1&" more)",""),IFERROR(INDEX(_MainTable!$B$2:$B$2001,MATCH($B47,_MainTable!$F$2:$F$2001,0)),"")))&""="","—",(IFERROR(INDEX(_RefTable!$B$2:$B$501,MATCH($B47,_RefTable!$C$2:$C$501,0))&IF(COUNTIF(_RefTable!$C$2:$C$501,$B47)>1," (+"&COUNTIF(_RefTable!$C$2:$C$501,$B47)-1&" more)",""),IFERROR(INDEX(_MainTable!$B$2:$B$2001,MATCH($B47,_MainTable!$F$2:$F$2001,0)),""))))) -> Coding Audit | D47: =IF($B47="","",IF((IFERROR(INDEX(_RefTable!$E$2:$E$501,MATCH($B47,_RefTable!$C$2:$C$501,0)),IFERROR(INDEX(_MainTable!$C$2:$C$2001,MATCH($B47,_MainTable!$F$2:$F$2001,0)),"")))&""="","—",(IFERROR(INDEX(_RefTable!$E$2:$E$501,MATCH($B47,_RefTable!$C$2:$C$501,0)),IFERROR(INDEX(_MainTable!$C$2:$C$2001,MATCH($B47,_MainTable!$F$2:$F$2001,0)),""))))) -> Sona Buchanan | E47: =IF($B47="","",IF((IFERROR(INDEX(_RefTable!$F$2:$F$501,MATCH($B47,_RefTable!$C$2:$C$501,0)),IFERROR(INDEX(_MainTable!$D$2:$D$2001,MATCH($B47,_MainTable!$F$2:$F$2001,0)),"")))&""="","—",(IFERROR(INDEX(_RefTable!$F$2:$F$501,MATCH($B47,_RefTable!$C$2:$C$501,0)),IFERROR(INDEX(_MainTable!$D$2:$D$2001,MATCH($B47,_MainTable!$F$2:$F$2001,0)),""))))) -> Heather Geile | F47: =IF($B47="","",IFERROR(_xlfn.MINIFS('SC Change Orders'!$E$2:$E$501,'SC Change Orders'!$B$2:$B$501,$B47,'SC Change Orders'!$C$2:$C$501,">="&Controls!$C$5,'SC Change Orders'!$C$2:$C$501,"<="&Controls!$C$6),0)) -> 500000 | G47: =IF($B47="","",SUMIFS('SC Change Orders'!$F$2:$F$501,'SC Change Orders'!$B$2:$B$501,$B47,'SC Change Orders'!$C$2:$C$501,">="&Controls!$C$5,'SC Change Orders'!$C$2:$C$501,"<="&Controls!$C$6)) -> 500000 | H47: =IF($B47="","",$F47+$G47) -> 1000000 | I47: =IF($B47="","",SUMIFS(_MainTable!$K$2:$K$2001,_MainTable!$F$2:$F$2001,$B47,_MainTable!$G$2:$G$2001,">="&Controls!$C$5,_MainTable!$G$2:$G$2001,"<="&Controls!$C$6)) -> 3822.5 | J47: =IF($B47="","",IFERROR($I47/$H47,0)) -> 0.0038225 | K47: =IF($B47="","",$H47-$I47) -> 996177.5 | L47: =IF($B47="","",IFERROR(SUMIFS(_MainTable!$K$2:$K$2001,_MainTable!$F$2:$F$2001,$B47,_MainTable!$G$2:$G$2001,">="&Controls!$C$12,_MainTable!$G$2:$G$2001,"<="&EOMONTH(Controls!$C$7,0))/MIN(Controls!$C$9,Controls!$C$10),0)) -> 1274.1667 | M47: =IF($B47="","",$L47*Controls!$C$11) -> 2548.3333 | N47: =IF($B47="","",$I47+$M47) -> 6370.8333 | O47: =IF($B47="","",IFERROR($N47/$H47,0)) -> 0.0063708333 | P47: =IF($B47="","",$H47-$N47) -> 993629.17 | Q47: =IF($B47="","",IF($L47<=0,"n/a",IFERROR($K47/$L47,"n/a"))) -> 781.82668 | R47: =IF($B47="","",IF(AND($H47=0,$I47=0),"⚪ No Activity",IF(AND($H47=0,COUNTIFS('SC Change Orders'!$B$2:$B$501,$B47,'SC Change Orders'!$C$2:$C$501,">="&Controls!$C$5,'SC Change Orders'!$C$2:$C$501,"<="&Controls!$C$6)=0),"⚪ No Funding on File",IF($H47=0,"🔴 Unfunded Spend",IF($I47>=$H47,"🔴 Over Budget",IF($N47>$H47,"🔴 Projected Shortfall",IF($J47>=Controls!$C$8,"🟡 Watch","🟢 On Track"))))))) -> 🟢 On Track
A48: =IF($B48="","",IF((IFERROR(INDEX(_RefTable!$A$2:$A$501,MATCH($B48,_RefTable!$C$2:$C$501,0)),IFERROR(INDEX(_MainTable!$A$2:$A$2001,MATCH($B48,_MainTable!$F$2:$F$2001,0)),IFERROR(INDEX('SC Change Orders'!$A$2:$A$501,MATCH($B48,'SC Change Orders'!$B$2:$B$501,0)),"(unknown vendor)"))))&""="","—",(IFERROR(INDEX(_RefTable!$A$2:$A$501,MATCH($B48,_RefTable!$C$2:$C$501,0)),IFERROR(INDEX(_MainTable!$A$2:$A$2001,MATCH($B48,_MainTable!$F$2:$F$2001,0)),IFERROR(INDEX('SC Change Orders'!$A$2:$A$501,MATCH($B48,'SC Change Orders'!$B$2:$B$501,0)),"(unknown vendor)")))))) | B48: =IFERROR(INDEX('PO Index'!$B$5:$B$84,44),"") | C48: =IF($B48="","",IF((IFERROR(INDEX(_RefTable!$B$2:$B$501,MATCH($B48,_RefTable!$C$2:$C$501,0))&IF(COUNTIF(_RefTable!$C$2:$C$501,$B48)>1," (+"&COUNTIF(_RefTable!$C$2:$C$501,$B48)-1&" more)",""),IFERROR(INDEX(_MainTable!$B$2:$B$2001,MATCH($B48,_MainTable!$F$2:$F$2001,0)),"")))&""="","—",(IFERROR(INDEX(_RefTable!$B$2:$B$501,MATCH($B48,_RefTable!$C$2:$C$501,0))&IF(COUNTIF(_RefTable!$C$2:$C$501,$B48)>1," (+"&COUNTIF(_RefTable!$C$2:$C$501,$B48)-1&" more)",""),IFERROR(INDEX(_MainTable!$B$2:$B$2001,MATCH($B48,_MainTable!$F$2:$F$2001,0)),""))))) | D48: =IF($B48="","",IF((IFERROR(INDEX(_RefTable!$E$2:$E$501,MATCH($B48,_RefTable!$C$2:$C$501,0)),IFERROR(INDEX(_MainTable!$C$2:$C$2001,MATCH($B48,_MainTable!$F$2:$F$2001,0)),"")))&""="","—",(IFERROR(INDEX(_RefTable!$E$2:$E$501,MATCH($B48,_RefTable!$C$2:$C$501,0)),IFERROR(INDEX(_MainTable!$C$2:$C$2001,MATCH($B48,_MainTable!$F$2:$F$2001,0)),""))))) | E48: =IF($B48="","",IF((IFERROR(INDEX(_RefTable!$F$2:$F$501,MATCH($B48,_RefTable!$C$2:$C$501,0)),IFERROR(INDEX(_MainTable!$D$2:$D$2001,MATCH($B48,_MainTable!$F$2:$F$2001,0)),"")))&""="","—",(IFERROR(INDEX(_RefTable!$F$2:$F$501,MATCH($B48,_RefTable!$C$2:$C$501,0)),IFERROR(INDEX(_MainTable!$D$2:$D$2001,MATCH($B48,_MainTable!$F$2:$F$2001,0)),""))))) | F48: =IF($B48="","",IFERROR(_xlfn.MINIFS('SC Change Orders'!$E$2:$E$501,'SC Change Orders'!$B$2:$B$501,$B48,'SC Change Orders'!$C$2:$C$501,">="&Controls!$C$5,'SC Change Orders'!$C$2:$C$501,"<="&Controls!$C$6),0)) | G48: =IF($B48="","",SUMIFS('SC Change Orders'!$F$2:$F$501,'SC Change Orders'!$B$2:$B$501,$B48,'SC Change Orders'!$C$2:$C$501,">="&Controls!$C$5,'SC Change Orders'!$C$2:$C$501,"<="&Controls!$C$6)) | H48: =IF($B48="","",$F48+$G48) | I48: =IF($B48="","",SUMIFS(_MainTable!$K$2:$K$2001,_MainTable!$F$2:$F$2001,$B48,_MainTable!$G$2:$G$2001,">="&Controls!$C$5,_MainTable!$G$2:$G$2001,"<="&Controls!$C$6)) | J48: =IF($B48="","",IFERROR($I48/$H48,0)) | K48: =IF($B48="","",$H48-$I48) | L48: =IF($B48="","",IFERROR(SUMIFS(_MainTable!$K$2:$K$2001,_MainTable!$F$2:$F$2001,$B48,_MainTable!$G$2:$G$2001,">="&Controls!$C$12,_MainTable!$G$2:$G$2001,"<="&EOMONTH(Controls!$C$7,0))/MIN(Controls!$C$9,Controls!$C$10),0)) | M48: =IF($B48="","",$L48*Controls!$C$11) | N48: =IF($B48="","",$I48+$M48) | O48: =IF($B48="","",IFERROR($N48/$H48,0)) | P48: =IF($B48="","",$H48-$N48) | Q48: =IF($B48="","",IF($L48<=0,"n/a",IFERROR($K48/$L48,"n/a"))) | R48: =IF($B48="","",IF(AND($H48=0,$I48=0),"⚪ No Activity",IF(AND($H48=0,COUNTIFS('SC Change Orders'!$B$2:$B$501,$B48,'SC Change Orders'!$C$2:$C$501,">="&Controls!$C$5,'SC Change Orders'!$C$2:$C$501,"<="&Controls!$C$6)=0),"⚪ No Funding on File",IF($H48=0,"🔴 Unfunded Spend",IF($I48>=$H48,"🔴 Over Budget",IF($N48>$H48,"🔴 Projected Shortfall",IF($J48>=Controls!$C$8,"🟡 Watch","🟢 On Track")))))))
A49: =IF($B49="","",IF((IFERROR(INDEX(_RefTable!$A$2:$A$501,MATCH($B49,_RefTable!$C$2:$C$501,0)),IFERROR(INDEX(_MainTable!$A$2:$A$2001,MATCH($B49,_MainTable!$F$2:$F$2001,0)),IFERROR(INDEX('SC Change Orders'!$A$2:$A$501,MATCH($B49,'SC Change Orders'!$B$2:$B$501,0)),"(unknown vendor)"))))&""="","—",(IFERROR(INDEX(_RefTable!$A$2:$A$501,MATCH($B49,_RefTable!$C$2:$C$501,0)),IFERROR(INDEX(_MainTable!$A$2:$A$2001,MATCH($B49,_MainTable!$F$2:$F$2001,0)),IFERROR(INDEX('SC Change Orders'!$A$2:$A$501,MATCH($B49,'SC Change Orders'!$B$2:$B$501,0)),"(unknown vendor)")))))) | B49: =IFERROR(INDEX('PO Index'!$B$5:$B$84,45),"") | C49: =IF($B49="","",IF((IFERROR(INDEX(_RefTable!$B$2:$B$501,MATCH($B49,_RefTable!$C$2:$C$501,0))&IF(COUNTIF(_RefTable!$C$2:$C$501,$B49)>1," (+"&COUNTIF(_RefTable!$C$2:$C$501,$B49)-1&" more)",""),IFERROR(INDEX(_MainTable!$B$2:$B$2001,MATCH($B49,_MainTable!$F$2:$F$2001,0)),"")))&""="","—",(IFERROR(INDEX(_RefTable!$B$2:$B$501,MATCH($B49,_RefTable!$C$2:$C$501,0))&IF(COUNTIF(_RefTable!$C$2:$C$501,$B49)>1," (+"&COUNTIF(_RefTable!$C$2:$C$501,$B49)-1&" more)",""),IFERROR(INDEX(_MainTable!$B$2:$B$2001,MATCH($B49,_MainTable!$F$2:$F$2001,0)),""))))) | D49: =IF($B49="","",IF((IFERROR(INDEX(_RefTable!$E$2:$E$501,MATCH($B49,_RefTable!$C$2:$C$501,0)),IFERROR(INDEX(_MainTable!$C$2:$C$2001,MATCH($B49,_MainTable!$F$2:$F$2001,0)),"")))&""="","—",(IFERROR(INDEX(_RefTable!$E$2:$E$501,MATCH($B49,_RefTable!$C$2:$C$501,0)),IFERROR(INDEX(_MainTable!$C$2:$C$2001,MATCH($B49,_MainTable!$F$2:$F$2001,0)),""))))) | E49: =IF($B49="","",IF((IFERROR(INDEX(_RefTable!$F$2:$F$501,MATCH($B49,_RefTable!$C$2:$C$501,0)),IFERROR(INDEX(_MainTable!$D$2:$D$2001,MATCH($B49,_MainTable!$F$2:$F$2001,0)),"")))&""="","—",(IFERROR(INDEX(_RefTable!$F$2:$F$501,MATCH($B49,_RefTable!$C$2:$C$501,0)),IFERROR(INDEX(_MainTable!$D$2:$D$2001,MATCH($B49,_MainTable!$F$2:$F$2001,0)),""))))) | F49: =IF($B49="","",IFERROR(_xlfn.MINIFS('SC Change Orders'!$E$2:$E$501,'SC Change Orders'!$B$2:$B$501,$B49,'SC Change Orders'!$C$2:$C$501,">="&Controls!$C$5,'SC Change Orders'!$C$2:$C$501,"<="&Controls!$C$6),0)) | G49: =IF($B49="","",SUMIFS('SC Change Orders'!$F$2:$F$501,'SC Change Orders'!$B$2:$B$501,$B49,'SC Change Orders'!$C$2:$C$501,">="&Controls!$C$5,'SC Change Orders'!$C$2:$C$501,"<="&Controls!$C$6)) | H49: =IF($B49="","",$F49+$G49) | I49: =IF($B49="","",SUMIFS(_MainTable!$K$2:$K$2001,_MainTable!$F$2:$F$2001,$B49,_MainTable!$G$2:$G$2001,">="&Controls!$C$5,_MainTable!$G$2:$G$2001,"<="&Controls!$C$6)) | J49: =IF($B49="","",IFERROR($I49/$H49,0)) | K49: =IF($B49="","",$H49-$I49) | L49: =IF($B49="","",IFERROR(SUMIFS(_MainTable!$K$2:$K$2001,_MainTable!$F$2:$F$2001,$B49,_MainTable!$G$2:$G$2001,">="&Controls!$C$12,_MainTable!$G$2:$G$2001,"<="&EOMONTH(Controls!$C$7,0))/MIN(Controls!$C$9,Controls!$C$10),0)) | M49: =IF($B49="","",$L49*Controls!$C$11) | N49: =IF($B49="","",$I49+$M49) | O49: =IF($B49="","",IFERROR($N49/$H49,0)) | P49: =IF($B49="","",$H49-$N49) | Q49: =IF($B49="","",IF($L49<=0,"n/a",IFERROR($K49/$L49,"n/a"))) | R49: =IF($B49="","",IF(AND($H49=0,$I49=0),"⚪ No Activity",IF(AND($H49=0,COUNTIFS('SC Change Orders'!$B$2:$B$501,$B49,'SC Change Orders'!$C$2:$C$501,">="&Controls!$C$5,'SC Change Orders'!$C$2:$C$501,"<="&Controls!$C$6)=0),"⚪ No Funding on File",IF($H49=0,"🔴 Unfunded Spend",IF($I49>=$H49,"🔴 Over Budget",IF($N49>$H49,"🔴 Projected Shortfall",IF($J49>=Controls!$C$8,"🟡 Watch","🟢 On Track")))))))
A50: =IF($B50="","",IF((IFERROR(INDEX(_RefTable!$A$2:$A$501,MATCH($B50,_RefTable!$C$2:$C$501,0)),IFERROR(INDEX(_MainTable!$A$2:$A$2001,MATCH($B50,_MainTable!$F$2:$F$2001,0)),IFERROR(INDEX('SC Change Orders'!$A$2:$A$501,MATCH($B50,'SC Change Orders'!$B$2:$B$501,0)),"(unknown vendor)"))))&""="","—",(IFERROR(INDEX(_RefTable!$A$2:$A$501,MATCH($B50,_RefTable!$C$2:$C$501,0)),IFERROR(INDEX(_MainTable!$A$2:$A$2001,MATCH($B50,_MainTable!$F$2:$F$2001,0)),IFERROR(INDEX('SC Change Orders'!$A$2:$A$501,MATCH($B50,'SC Change Orders'!$B$2:$B$501,0)),"(unknown vendor)")))))) | B50: =IFERROR(INDEX('PO Index'!$B$5:$B$84,46),"") | C50: =IF($B50="","",IF((IFERROR(INDEX(_RefTable!$B$2:$B$501,MATCH($B50,_RefTable!$C$2:$C$501,0))&IF(COUNTIF(_RefTable!$C$2:$C$501,$B50)>1," (+"&COUNTIF(_RefTable!$C$2:$C$501,$B50)-1&" more)",""),IFERROR(INDEX(_MainTable!$B$2:$B$2001,MATCH($B50,_MainTable!$F$2:$F$2001,0)),"")))&""="","—",(IFERROR(INDEX(_RefTable!$B$2:$B$501,MATCH($B50,_RefTable!$C$2:$C$501,0))&IF(COUNTIF(_RefTable!$C$2:$C$501,$B50)>1," (+"&COUNTIF(_RefTable!$C$2:$C$501,$B50)-1&" more)",""),IFERROR(INDEX(_MainTable!$B$2:$B$2001,MATCH($B50,_MainTable!$F$2:$F$2001,0)),""))))) | D50: =IF($B50="","",IF((IFERROR(INDEX(_RefTable!$E$2:$E$501,MATCH($B50,_RefTable!$C$2:$C$501,0)),IFERROR(INDEX(_MainTable!$C$2:$C$2001,MATCH($B50,_MainTable!$F$2:$F$2001,0)),"")))&""="","—",(IFERROR(INDEX(_RefTable!$E$2:$E$501,MATCH($B50,_RefTable!$C$2:$C$501,0)),IFERROR(INDEX(_MainTable!$C$2:$C$2001,MATCH($B50,_MainTable!$F$2:$F$2001,0)),""))))) | E50: =IF($B50="","",IF((IFERROR(INDEX(_RefTable!$F$2:$F$501,MATCH($B50,_RefTable!$C$2:$C$501,0)),IFERROR(INDEX(_MainTable!$D$2:$D$2001,MATCH($B50,_MainTable!$F$2:$F$2001,0)),"")))&""="","—",(IFERROR(INDEX(_RefTable!$F$2:$F$501,MATCH($B50,_RefTable!$C$2:$C$501,0)),IFERROR(INDEX(_MainTable!$D$2:$D$2001,MATCH($B50,_MainTable!$F$2:$F$2001,0)),""))))) | F50: =IF($B50="","",IFERROR(_xlfn.MINIFS('SC Change Orders'!$E$2:$E$501,'SC Change Orders'!$B$2:$B$501,$B50,'SC Change Orders'!$C$2:$C$501,">="&Controls!$C$5,'SC Change Orders'!$C$2:$C$501,"<="&Controls!$C$6),0)) | G50: =IF($B50="","",SUMIFS('SC Change Orders'!$F$2:$F$501,'SC Change Orders'!$B$2:$B$501,$B50,'SC Change Orders'!$C$2:$C$501,">="&Controls!$C$5,'SC Change Orders'!$C$2:$C$501,"<="&Controls!$C$6)) | H50: =IF($B50="","",$F50+$G50) | I50: =IF($B50="","",SUMIFS(_MainTable!$K$2:$K$2001,_MainTable!$F$2:$F$2001,$B50,_MainTable!$G$2:$G$2001,">="&Controls!$C$5,_MainTable!$G$2:$G$2001,"<="&Controls!$C$6)) | J50: =IF($B50="","",IFERROR($I50/$H50,0)) | K50: =IF($B50="","",$H50-$I50) | L50: =IF($B50="","",IFERROR(SUMIFS(_MainTable!$K$2:$K$2001,_MainTable!$F$2:$F$2001,$B50,_MainTable!$G$2:$G$2001,">="&Controls!$C$12,_MainTable!$G$2:$G$2001,"<="&EOMONTH(Controls!$C$7,0))/MIN(Controls!$C$9,Controls!$C$10),0)) | M50: =IF($B50="","",$L50*Controls!$C$11) | N50: =IF($B50="","",$I50+$M50) | O50: =IF($B50="","",IFERROR($N50/$H50,0)) | P50: =IF($B50="","",$H50-$N50) | Q50: =IF($B50="","",IF($L50<=0,"n/a",IFERROR($K50/$L50,"n/a"))) | R50: =IF($B50="","",IF(AND($H50=0,$I50=0),"⚪ No Activity",IF(AND($H50=0,COUNTIFS('SC Change Orders'!$B$2:$B$501,$B50,'SC Change Orders'!$C$2:$C$501,">="&Controls!$C$5,'SC Change Orders'!$C$2:$C$501,"<="&Controls!$C$6)=0),"⚪ No Funding on File",IF($H50=0,"🔴 Unfunded Spend",IF($I50>=$H50,"🔴 Over Budget",IF($N50>$H50,"🔴 Projected Shortfall",IF($J50>=Controls!$C$8,"🟡 Watch","🟢 On Track")))))))
A51: =IF($B51="","",IF((IFERROR(INDEX(_RefTable!$A$2:$A$501,MATCH($B51,_RefTable!$C$2:$C$501,0)),IFERROR(INDEX(_MainTable!$A$2:$A$2001,MATCH($B51,_MainTable!$F$2:$F$2001,0)),IFERROR(INDEX('SC Change Orders'!$A$2:$A$501,MATCH($B51,'SC Change Orders'!$B$2:$B$501,0)),"(unknown vendor)"))))&""="","—",(IFERROR(INDEX(_RefTable!$A$2:$A$501,MATCH($B51,_RefTable!$C$2:$C$501,0)),IFERROR(INDEX(_MainTable!$A$2:$A$2001,MATCH($B51,_MainTable!$F$2:$F$2001,0)),IFERROR(INDEX('SC Change Orders'!$A$2:$A$501,MATCH($B51,'SC Change Orders'!$B$2:$B$501,0)),"(unknown vendor)")))))) | B51: =IFERROR(INDEX('PO Index'!$B$5:$B$84,47),"") | C51: =IF($B51="","",IF((IFERROR(INDEX(_RefTable!$B$2:$B$501,MATCH($B51,_RefTable!$C$2:$C$501,0))&IF(COUNTIF(_RefTable!$C$2:$C$501,$B51)>1," (+"&COUNTIF(_RefTable!$C$2:$C$501,$B51)-1&" more)",""),IFERROR(INDEX(_MainTable!$B$2:$B$2001,MATCH($B51,_MainTable!$F$2:$F$2001,0)),"")))&""="","—",(IFERROR(INDEX(_RefTable!$B$2:$B$501,MATCH($B51,_RefTable!$C$2:$C$501,0))&IF(COUNTIF(_RefTable!$C$2:$C$501,$B51)>1," (+"&COUNTIF(_RefTable!$C$2:$C$501,$B51)-1&" more)",""),IFERROR(INDEX(_MainTable!$B$2:$B$2001,MATCH($B51,_MainTable!$F$2:$F$2001,0)),""))))) | D51: =IF($B51="","",IF((IFERROR(INDEX(_RefTable!$E$2:$E$501,MATCH($B51,_RefTable!$C$2:$C$501,0)),IFERROR(INDEX(_MainTable!$C$2:$C$2001,MATCH($B51,_MainTable!$F$2:$F$2001,0)),"")))&""="","—",(IFERROR(INDEX(_RefTable!$E$2:$E$501,MATCH($B51,_RefTable!$C$2:$C$501,0)),IFERROR(INDEX(_MainTable!$C$2:$C$2001,MATCH($B51,_MainTable!$F$2:$F$2001,0)),""))))) | E51: =IF($B51="","",IF((IFERROR(INDEX(_RefTable!$F$2:$F$501,MATCH($B51,_RefTable!$C$2:$C$501,0)),IFERROR(INDEX(_MainTable!$D$2:$D$2001,MATCH($B51,_MainTable!$F$2:$F$2001,0)),"")))&""="","—",(IFERROR(INDEX(_RefTable!$F$2:$F$501,MATCH($B51,_RefTable!$C$2:$C$501,0)),IFERROR(INDEX(_MainTable!$D$2:$D$2001,MATCH($B51,_MainTable!$F$2:$F$2001,0)),""))))) | F51: =IF($B51="","",IFERROR(_xlfn.MINIFS('SC Change Orders'!$E$2:$E$501,'SC Change Orders'!$B$2:$B$501,$B51,'SC Change Orders'!$C$2:$C$501,">="&Controls!$C$5,'SC Change Orders'!$C$2:$C$501,"<="&Controls!$C$6),0)) | G51: =IF($B51="","",SUMIFS('SC Change Orders'!$F$2:$F$501,'SC Change Orders'!$B$2:$B$501,$B51,'SC Change Orders'!$C$2:$C$501,">="&Controls!$C$5,'SC Change Orders'!$C$2:$C$501,"<="&Controls!$C$6)) | H51: =IF($B51="","",$F51+$G51) | I51: =IF($B51="","",SUMIFS(_MainTable!$K$2:$K$2001,_MainTable!$F$2:$F$2001,$B51,_MainTable!$G$2:$G$2001,">="&Controls!$C$5,_MainTable!$G$2:$G$2001,"<="&Controls!$C$6)) | J51: =IF($B51="","",IFERROR($I51/$H51,0)) | K51: =IF($B51="","",$H51-$I51) | L51: =IF($B51="","",IFERROR(SUMIFS(_MainTable!$K$2:$K$2001,_MainTable!$F$2:$F$2001,$B51,_MainTable!$G$2:$G$2001,">="&Controls!$C$12,_MainTable!$G$2:$G$2001,"<="&EOMONTH(Controls!$C$7,0))/MIN(Controls!$C$9,Controls!$C$10),0)) | M51: =IF($B51="","",$L51*Controls!$C$11) | N51: =IF($B51="","",$I51+$M51) | O51: =IF($B51="","",IFERROR($N51/$H51,0)) | P51: =IF($B51="","",$H51-$N51) | Q51: =IF($B51="","",IF($L51<=0,"n/a",IFERROR($K51/$L51,"n/a"))) | R51: =IF($B51="","",IF(AND($H51=0,$I51=0),"⚪ No Activity",IF(AND($H51=0,COUNTIFS('SC Change Orders'!$B$2:$B$501,$B51,'SC Change Orders'!$C$2:$C$501,">="&Controls!$C$5,'SC Change Orders'!$C$2:$C$501,"<="&Controls!$C$6)=0),"⚪ No Funding on File",IF($H51=0,"🔴 Unfunded Spend",IF($I51>=$H51,"🔴 Over Budget",IF($N51>$H51,"🔴 Projected Shortfall",IF($J51>=Controls!$C$8,"🟡 Watch","🟢 On Track")))))))
A52: =IF($B52="","",IF((IFERROR(INDEX(_RefTable!$A$2:$A$501,MATCH($B52,_RefTable!$C$2:$C$501,0)),IFERROR(INDEX(_MainTable!$A$2:$A$2001,MATCH($B52,_MainTable!$F$2:$F$2001,0)),IFERROR(INDEX('SC Change Orders'!$A$2:$A$501,MATCH($B52,'SC Change Orders'!$B$2:$B$501,0)),"(unknown vendor)"))))&""="","—",(IFERROR(INDEX(_RefTable!$A$2:$A$501,MATCH($B52,_RefTable!$C$2:$C$501,0)),IFERROR(INDEX(_MainTable!$A$2:$A$2001,MATCH($B52,_MainTable!$F$2:$F$2001,0)),IFERROR(INDEX('SC Change Orders'!$A$2:$A$501,MATCH($B52,'SC Change Orders'!$B$2:$B$501,0)),"(unknown vendor)")))))) | B52: =IFERROR(INDEX('PO Index'!$B$5:$B$84,48),"") | C52: =IF($B52="","",IF((IFERROR(INDEX(_RefTable!$B$2:$B$501,MATCH($B52,_RefTable!$C$2:$C$501,0))&IF(COUNTIF(_RefTable!$C$2:$C$501,$B52)>1," (+"&COUNTIF(_RefTable!$C$2:$C$501,$B52)-1&" more)",""),IFERROR(INDEX(_MainTable!$B$2:$B$2001,MATCH($B52,_MainTable!$F$2:$F$2001,0)),"")))&""="","—",(IFERROR(INDEX(_RefTable!$B$2:$B$501,MATCH($B52,_RefTable!$C$2:$C$501,0))&IF(COUNTIF(_RefTable!$C$2:$C$501,$B52)>1," (+"&COUNTIF(_RefTable!$C$2:$C$501,$B52)-1&" more)",""),IFERROR(INDEX(_MainTable!$B$2:$B$2001,MATCH($B52,_MainTable!$F$2:$F$2001,0)),""))))) | D52: =IF($B52="","",IF((IFERROR(INDEX(_RefTable!$E$2:$E$501,MATCH($B52,_RefTable!$C$2:$C$501,0)),IFERROR(INDEX(_MainTable!$C$2:$C$2001,MATCH($B52,_MainTable!$F$2:$F$2001,0)),"")))&""="","—",(IFERROR(INDEX(_RefTable!$E$2:$E$501,MATCH($B52,_RefTable!$C$2:$C$501,0)),IFERROR(INDEX(_MainTable!$C$2:$C$2001,MATCH($B52,_MainTable!$F$2:$F$2001,0)),""))))) | E52: =IF($B52="","",IF((IFERROR(INDEX(_RefTable!$F$2:$F$501,MATCH($B52,_RefTable!$C$2:$C$501,0)),IFERROR(INDEX(_MainTable!$D$2:$D$2001,MATCH($B52,_MainTable!$F$2:$F$2001,0)),"")))&""="","—",(IFERROR(INDEX(_RefTable!$F$2:$F$501,MATCH($B52,_RefTable!$C$2:$C$501,0)),IFERROR(INDEX(_MainTable!$D$2:$D$2001,MATCH($B52,_MainTable!$F$2:$F$2001,0)),""))))) | F52: =IF($B52="","",IFERROR(_xlfn.MINIFS('SC Change Orders'!$E$2:$E$501,'SC Change Orders'!$B$2:$B$501,$B52,'SC Change Orders'!$C$2:$C$501,">="&Controls!$C$5,'SC Change Orders'!$C$2:$C$501,"<="&Controls!$C$6),0)) | G52: =IF($B52="","",SUMIFS('SC Change Orders'!$F$2:$F$501,'SC Change Orders'!$B$2:$B$501,$B52,'SC Change Orders'!$C$2:$C$501,">="&Controls!$C$5,'SC Change Orders'!$C$2:$C$501,"<="&Controls!$C$6)) | H52: =IF($B52="","",$F52+$G52) | I52: =IF($B52="","",SUMIFS(_MainTable!$K$2:$K$2001,_MainTable!$F$2:$F$2001,$B52,_MainTable!$G$2:$G$2001,">="&Controls!$C$5,_MainTable!$G$2:$G$2001,"<="&Controls!$C$6)) | J52: =IF($B52="","",IFERROR($I52/$H52,0)) | K52: =IF($B52="","",$H52-$I52) | L52: =IF($B52="","",IFERROR(SUMIFS(_MainTable!$K$2:$K$2001,_MainTable!$F$2:$F$2001,$B52,_MainTable!$G$2:$G$2001,">="&Controls!$C$12,_MainTable!$G$2:$G$2001,"<="&EOMONTH(Controls!$C$7,0))/MIN(Controls!$C$9,Controls!$C$10),0)) | M52: =IF($B52="","",$L52*Controls!$C$11) | N52: =IF($B52="","",$I52+$M52) | O52: =IF($B52="","",IFERROR($N52/$H52,0)) | P52: =IF($B52="","",$H52-$N52) | Q52: =IF($B52="","",IF($L52<=0,"n/a",IFERROR($K52/$L52,"n/a"))) | R52: =IF($B52="","",IF(AND($H52=0,$I52=0),"⚪ No Activity",IF(AND($H52=0,COUNTIFS('SC Change Orders'!$B$2:$B$501,$B52,'SC Change Orders'!$C$2:$C$501,">="&Controls!$C$5,'SC Change Orders'!$C$2:$C$501,"<="&Controls!$C$6)=0),"⚪ No Funding on File",IF($H52=0,"🔴 Unfunded Spend",IF($I52>=$H52,"🔴 Over Budget",IF($N52>$H52,"🔴 Projected Shortfall",IF($J52>=Controls!$C$8,"🟡 Watch","🟢 On Track")))))))
A53: =IF($B53="","",IF((IFERROR(INDEX(_RefTable!$A$2:$A$501,MATCH($B53,_RefTable!$C$2:$C$501,0)),IFERROR(INDEX(_MainTable!$A$2:$A$2001,MATCH($B53,_MainTable!$F$2:$F$2001,0)),IFERROR(INDEX('SC Change Orders'!$A$2:$A$501,MATCH($B53,'SC Change Orders'!$B$2:$B$501,0)),"(unknown vendor)"))))&""="","—",(IFERROR(INDEX(_RefTable!$A$2:$A$501,MATCH($B53,_RefTable!$C$2:$C$501,0)),IFERROR(INDEX(_MainTable!$A$2:$A$2001,MATCH($B53,_MainTable!$F$2:$F$2001,0)),IFERROR(INDEX('SC Change Orders'!$A$2:$A$501,MATCH($B53,'SC Change Orders'!$B$2:$B$501,0)),"(unknown vendor)")))))) | B53: =IFERROR(INDEX('PO Index'!$B$5:$B$84,49),"") | C53: =IF($B53="","",IF((IFERROR(INDEX(_RefTable!$B$2:$B$501,MATCH($B53,_RefTable!$C$2:$C$501,0))&IF(COUNTIF(_RefTable!$C$2:$C$501,$B53)>1," (+"&COUNTIF(_RefTable!$C$2:$C$501,$B53)-1&" more)",""),IFERROR(INDEX(_MainTable!$B$2:$B$2001,MATCH($B53,_MainTable!$F$2:$F$2001,0)),"")))&""="","—",(IFERROR(INDEX(_RefTable!$B$2:$B$501,MATCH($B53,_RefTable!$C$2:$C$501,0))&IF(COUNTIF(_RefTable!$C$2:$C$501,$B53)>1," (+"&COUNTIF(_RefTable!$C$2:$C$501,$B53)-1&" more)",""),IFERROR(INDEX(_MainTable!$B$2:$B$2001,MATCH($B53,_MainTable!$F$2:$F$2001,0)),""))))) | D53: =IF($B53="","",IF((IFERROR(INDEX(_RefTable!$E$2:$E$501,MATCH($B53,_RefTable!$C$2:$C$501,0)),IFERROR(INDEX(_MainTable!$C$2:$C$2001,MATCH($B53,_MainTable!$F$2:$F$2001,0)),"")))&""="","—",(IFERROR(INDEX(_RefTable!$E$2:$E$501,MATCH($B53,_RefTable!$C$2:$C$501,0)),IFERROR(INDEX(_MainTable!$C$2:$C$2001,MATCH($B53,_MainTable!$F$2:$F$2001,0)),""))))) | E53: =IF($B53="","",IF((IFERROR(INDEX(_RefTable!$F$2:$F$501,MATCH($B53,_RefTable!$C$2:$C$501,0)),IFERROR(INDEX(_MainTable!$D$2:$D$2001,MATCH($B53,_MainTable!$F$2:$F$2001,0)),"")))&""="","—",(IFERROR(INDEX(_RefTable!$F$2:$F$501,MATCH($B53,_RefTable!$C$2:$C$501,0)),IFERROR(INDEX(_MainTable!$D$2:$D$2001,MATCH($B53,_MainTable!$F$2:$F$2001,0)),""))))) | F53: =IF($B53="","",IFERROR(_xlfn.MINIFS('SC Change Orders'!$E$2:$E$501,'SC Change Orders'!$B$2:$B$501,$B53,'SC Change Orders'!$C$2:$C$501,">="&Controls!$C$5,'SC Change Orders'!$C$2:$C$501,"<="&Controls!$C$6),0)) | G53: =IF($B53="","",SUMIFS('SC Change Orders'!$F$2:$F$501,'SC Change Orders'!$B$2:$B$501,$B53,'SC Change Orders'!$C$2:$C$501,">="&Controls!$C$5,'SC Change Orders'!$C$2:$C$501,"<="&Controls!$C$6)) | H53: =IF($B53="","",$F53+$G53) | I53: =IF($B53="","",SUMIFS(_MainTable!$K$2:$K$2001,_MainTable!$F$2:$F$2001,$B53,_MainTable!$G$2:$G$2001,">="&Controls!$C$5,_MainTable!$G$2:$G$2001,"<="&Controls!$C$6)) | J53: =IF($B53="","",IFERROR($I53/$H53,0)) | K53: =IF($B53="","",$H53-$I53) | L53: =IF($B53="","",IFERROR(SUMIFS(_MainTable!$K$2:$K$2001,_MainTable!$F$2:$F$2001,$B53,_MainTable!$G$2:$G$2001,">="&Controls!$C$12,_MainTable!$G$2:$G$2001,"<="&EOMONTH(Controls!$C$7,0))/MIN(Controls!$C$9,Controls!$C$10),0)) | M53: =IF($B53="","",$L53*Controls!$C$11) | N53: =IF($B53="","",$I53+$M53) | O53: =IF($B53="","",IFERROR($N53/$H53,0)) | P53: =IF($B53="","",$H53-$N53) | Q53: =IF($B53="","",IF($L53<=0,"n/a",IFERROR($K53/$L53,"n/a"))) | R53: =IF($B53="","",IF(AND($H53=0,$I53=0),"⚪ No Activity",IF(AND($H53=0,COUNTIFS('SC Change Orders'!$B$2:$B$501,$B53,'SC Change Orders'!$C$2:$C$501,">="&Controls!$C$5,'SC Change Orders'!$C$2:$C$501,"<="&Controls!$C$6)=0),"⚪ No Funding on File",IF($H53=0,"🔴 Unfunded Spend",IF($I53>=$H53,"🔴 Over Budget",IF($N53>$H53,"🔴 Projected Shortfall",IF($J53>=Controls!$C$8,"🟡 Watch","🟢 On Track")))))))
A54: =IF($B54="","",IF((IFERROR(INDEX(_RefTable!$A$2:$A$501,MATCH($B54,_RefTable!$C$2:$C$501,0)),IFERROR(INDEX(_MainTable!$A$2:$A$2001,MATCH($B54,_MainTable!$F$2:$F$2001,0)),IFERROR(INDEX('SC Change Orders'!$A$2:$A$501,MATCH($B54,'SC Change Orders'!$B$2:$B$501,0)),"(unknown vendor)"))))&""="","—",(IFERROR(INDEX(_RefTable!$A$2:$A$501,MATCH($B54,_RefTable!$C$2:$C$501,0)),IFERROR(INDEX(_MainTable!$A$2:$A$2001,MATCH($B54,_MainTable!$F$2:$F$2001,0)),IFERROR(INDEX('SC Change Orders'!$A$2:$A$501,MATCH($B54,'SC Change Orders'!$B$2:$B$501,0)),"(unknown vendor)")))))) | B54: =IFERROR(INDEX('PO Index'!$B$5:$B$84,50),"") | C54: =IF($B54="","",IF((IFERROR(INDEX(_RefTable!$B$2:$B$501,MATCH($B54,_RefTable!$C$2:$C$501,0))&IF(COUNTIF(_RefTable!$C$2:$C$501,$B54)>1," (+"&COUNTIF(_RefTable!$C$2:$C$501,$B54)-1&" more)",""),IFERROR(INDEX(_MainTable!$B$2:$B$2001,MATCH($B54,_MainTable!$F$2:$F$2001,0)),"")))&""="","—",(IFERROR(INDEX(_RefTable!$B$2:$B$501,MATCH($B54,_RefTable!$C$2:$C$501,0))&IF(COUNTIF(_RefTable!$C$2:$C$501,$B54)>1," (+"&COUNTIF(_RefTable!$C$2:$C$501,$B54)-1&" more)",""),IFERROR(INDEX(_MainTable!$B$2:$B$2001,MATCH($B54,_MainTable!$F$2:$F$2001,0)),""))))) | D54: =IF($B54="","",IF((IFERROR(INDEX(_RefTable!$E$2:$E$501,MATCH($B54,_RefTable!$C$2:$C$501,0)),IFERROR(INDEX(_MainTable!$C$2:$C$2001,MATCH($B54,_MainTable!$F$2:$F$2001,0)),"")))&""="","—",(IFERROR(INDEX(_RefTable!$E$2:$E$501,MATCH($B54,_RefTable!$C$2:$C$501,0)),IFERROR(INDEX(_MainTable!$C$2:$C$2001,MATCH($B54,_MainTable!$F$2:$F$2001,0)),""))))) | E54: =IF($B54="","",IF((IFERROR(INDEX(_RefTable!$F$2:$F$501,MATCH($B54,_RefTable!$C$2:$C$501,0)),IFERROR(INDEX(_MainTable!$D$2:$D$2001,MATCH($B54,_MainTable!$F$2:$F$2001,0)),"")))&""="","—",(IFERROR(INDEX(_RefTable!$F$2:$F$501,MATCH($B54,_RefTable!$C$2:$C$501,0)),IFERROR(INDEX(_MainTable!$D$2:$D$2001,MATCH($B54,_MainTable!$F$2:$F$2001,0)),""))))) | F54: =IF($B54="","",IFERROR(_xlfn.MINIFS('SC Change Orders'!$E$2:$E$501,'SC Change Orders'!$B$2:$B$501,$B54,'SC Change Orders'!$C$2:$C$501,">="&Controls!$C$5,'SC Change Orders'!$C$2:$C$501,"<="&Controls!$C$6),0)) | G54: =IF($B54="","",SUMIFS('SC Change Orders'!$F$2:$F$501,'SC Change Orders'!$B$2:$B$501,$B54,'SC Change Orders'!$C$2:$C$501,">="&Controls!$C$5,'SC Change Orders'!$C$2:$C$501,"<="&Controls!$C$6)) | H54: =IF($B54="","",$F54+$G54) | I54: =IF($B54="","",SUMIFS(_MainTable!$K$2:$K$2001,_MainTable!$F$2:$F$2001,$B54,_MainTable!$G$2:$G$2001,">="&Controls!$C$5,_MainTable!$G$2:$G$2001,"<="&Controls!$C$6)) | J54: =IF($B54="","",IFERROR($I54/$H54,0)) | K54: =IF($B54="","",$H54-$I54) | L54: =IF($B54="","",IFERROR(SUMIFS(_MainTable!$K$2:$K$2001,_MainTable!$F$2:$F$2001,$B54,_MainTable!$G$2:$G$2001,">="&Controls!$C$12,_MainTable!$G$2:$G$2001,"<="&EOMONTH(Controls!$C$7,0))/MIN(Controls!$C$9,Controls!$C$10),0)) | M54: =IF($B54="","",$L54*Controls!$C$11) | N54: =IF($B54="","",$I54+$M54) | O54: =IF($B54="","",IFERROR($N54/$H54,0)) | P54: =IF($B54="","",$H54-$N54) | Q54: =IF($B54="","",IF($L54<=0,"n/a",IFERROR($K54/$L54,"n/a"))) | R54: =IF($B54="","",IF(AND($H54=0,$I54=0),"⚪ No Activity",IF(AND($H54=0,COUNTIFS('SC Change Orders'!$B$2:$B$501,$B54,'SC Change Orders'!$C$2:$C$501,">="&Controls!$C$5,'SC Change Orders'!$C$2:$C$501,"<="&Controls!$C$6)=0),"⚪ No Funding on File",IF($H54=0,"🔴 Unfunded Spend",IF($I54>=$H54,"🔴 Over Budget",IF($N54>$H54,"🔴 Projected Shortfall",IF($J54>=Controls!$C$8,"🟡 Watch","🟢 On Track")))))))
A55: =IF($B55="","",IF((IFERROR(INDEX(_RefTable!$A$2:$A$501,MATCH($B55,_RefTable!$C$2:$C$501,0)),IFERROR(INDEX(_MainTable!$A$2:$A$2001,MATCH($B55,_MainTable!$F$2:$F$2001,0)),IFERROR(INDEX('SC Change Orders'!$A$2:$A$501,MATCH($B55,'SC Change Orders'!$B$2:$B$501,0)),"(unknown vendor)"))))&""="","—",(IFERROR(INDEX(_RefTable!$A$2:$A$501,MATCH($B55,_RefTable!$C$2:$C$501,0)),IFERROR(INDEX(_MainTable!$A$2:$A$2001,MATCH($B55,_MainTable!$F$2:$F$2001,0)),IFERROR(INDEX('SC Change Orders'!$A$2:$A$501,MATCH($B55,'SC Change Orders'!$B$2:$B$501,0)),"(unknown vendor)")))))) | B55: =IFERROR(INDEX('PO Index'!$B$5:$B$84,51),"") | C55: =IF($B55="","",IF((IFERROR(INDEX(_RefTable!$B$2:$B$501,MATCH($B55,_RefTable!$C$2:$C$501,0))&IF(COUNTIF(_RefTable!$C$2:$C$501,$B55)>1," (+"&COUNTIF(_RefTable!$C$2:$C$501,$B55)-1&" more)",""),IFERROR(INDEX(_MainTable!$B$2:$B$2001,MATCH($B55,_MainTable!$F$2:$F$2001,0)),"")))&""="","—",(IFERROR(INDEX(_RefTable!$B$2:$B$501,MATCH($B55,_RefTable!$C$2:$C$501,0))&IF(COUNTIF(_RefTable!$C$2:$C$501,$B55)>1," (+"&COUNTIF(_RefTable!$C$2:$C$501,$B55)-1&" more)",""),IFERROR(INDEX(_MainTable!$B$2:$B$2001,MATCH($B55,_MainTable!$F$2:$F$2001,0)),""))))) | D55: =IF($B55="","",IF((IFERROR(INDEX(_RefTable!$E$2:$E$501,MATCH($B55,_RefTable!$C$2:$C$501,0)),IFERROR(INDEX(_MainTable!$C$2:$C$2001,MATCH($B55,_MainTable!$F$2:$F$2001,0)),"")))&""="","—",(IFERROR(INDEX(_RefTable!$E$2:$E$501,MATCH($B55,_RefTable!$C$2:$C$501,0)),IFERROR(INDEX(_MainTable!$C$2:$C$2001,MATCH($B55,_MainTable!$F$2:$F$2001,0)),""))))) | E55: =IF($B55="","",IF((IFERROR(INDEX(_RefTable!$F$2:$F$501,MATCH($B55,_RefTable!$C$2:$C$501,0)),IFERROR(INDEX(_MainTable!$D$2:$D$2001,MATCH($B55,_MainTable!$F$2:$F$2001,0)),"")))&""="","—",(IFERROR(INDEX(_RefTable!$F$2:$F$501,MATCH($B55,_RefTable!$C$2:$C$501,0)),IFERROR(INDEX(_MainTable!$D$2:$D$2001,MATCH($B55,_MainTable!$F$2:$F$2001,0)),""))))) | F55: =IF($B55="","",IFERROR(_xlfn.MINIFS('SC Change Orders'!$E$2:$E$501,'SC Change Orders'!$B$2:$B$501,$B55,'SC Change Orders'!$C$2:$C$501,">="&Controls!$C$5,'SC Change Orders'!$C$2:$C$501,"<="&Controls!$C$6),0)) | G55: =IF($B55="","",SUMIFS('SC Change Orders'!$F$2:$F$501,'SC Change Orders'!$B$2:$B$501,$B55,'SC Change Orders'!$C$2:$C$501,">="&Controls!$C$5,'SC Change Orders'!$C$2:$C$501,"<="&Controls!$C$6)) | H55: =IF($B55="","",$F55+$G55) | I55: =IF($B55="","",SUMIFS(_MainTable!$K$2:$K$2001,_MainTable!$F$2:$F$2001,$B55,_MainTable!$G$2:$G$2001,">="&Controls!$C$5,_MainTable!$G$2:$G$2001,"<="&Controls!$C$6)) | J55: =IF($B55="","",IFERROR($I55/$H55,0)) | K55: =IF($B55="","",$H55-$I55) | L55: =IF($B55="","",IFERROR(SUMIFS(_MainTable!$K$2:$K$2001,_MainTable!$F$2:$F$2001,$B55,_MainTable!$G$2:$G$2001,">="&Controls!$C$12,_MainTable!$G$2:$G$2001,"<="&EOMONTH(Controls!$C$7,0))/MIN(Controls!$C$9,Controls!$C$10),0)) | M55: =IF($B55="","",$L55*Controls!$C$11) | N55: =IF($B55="","",$I55+$M55) | O55: =IF($B55="","",IFERROR($N55/$H55,0)) | P55: =IF($B55="","",$H55-$N55) | Q55: =IF($B55="","",IF($L55<=0,"n/a",IFERROR($K55/$L55,"n/a"))) | R55: =IF($B55="","",IF(AND($H55=0,$I55=0),"⚪ No Activity",IF(AND($H55=0,COUNTIFS('SC Change Orders'!$B$2:$B$501,$B55,'SC Change Orders'!$C$2:$C$501,">="&Controls!$C$5,'SC Change Orders'!$C$2:$C$501,"<="&Controls!$C$6)=0),"⚪ No Funding on File",IF($H55=0,"🔴 Unfunded Spend",IF($I55>=$H55,"🔴 Over Budget",IF($N55>$H55,"🔴 Projected Shortfall",IF($J55>=Controls!$C$8,"🟡 Watch","🟢 On Track")))))))
A56: =IF($B56="","",IF((IFERROR(INDEX(_RefTable!$A$2:$A$501,MATCH($B56,_RefTable!$C$2:$C$501,0)),IFERROR(INDEX(_MainTable!$A$2:$A$2001,MATCH($B56,_MainTable!$F$2:$F$2001,0)),IFERROR(INDEX('SC Change Orders'!$A$2:$A$501,MATCH($B56,'SC Change Orders'!$B$2:$B$501,0)),"(unknown vendor)"))))&""="","—",(IFERROR(INDEX(_RefTable!$A$2:$A$501,MATCH($B56,_RefTable!$C$2:$C$501,0)),IFERROR(INDEX(_MainTable!$A$2:$A$2001,MATCH($B56,_MainTable!$F$2:$F$2001,0)),IFERROR(INDEX('SC Change Orders'!$A$2:$A$501,MATCH($B56,'SC Change Orders'!$B$2:$B$501,0)),"(unknown vendor)")))))) | B56: =IFERROR(INDEX('PO Index'!$B$5:$B$84,52),"") | C56: =IF($B56="","",IF((IFERROR(INDEX(_RefTable!$B$2:$B$501,MATCH($B56,_RefTable!$C$2:$C$501,0))&IF(COUNTIF(_RefTable!$C$2:$C$501,$B56)>1," (+"&COUNTIF(_RefTable!$C$2:$C$501,$B56)-1&" more)",""),IFERROR(INDEX(_MainTable!$B$2:$B$2001,MATCH($B56,_MainTable!$F$2:$F$2001,0)),"")))&""="","—",(IFERROR(INDEX(_RefTable!$B$2:$B$501,MATCH($B56,_RefTable!$C$2:$C$501,0))&IF(COUNTIF(_RefTable!$C$2:$C$501,$B56)>1," (+"&COUNTIF(_RefTable!$C$2:$C$501,$B56)-1&" more)",""),IFERROR(INDEX(_MainTable!$B$2:$B$2001,MATCH($B56,_MainTable!$F$2:$F$2001,0)),""))))) | D56: =IF($B56="","",IF((IFERROR(INDEX(_RefTable!$E$2:$E$501,MATCH($B56,_RefTable!$C$2:$C$501,0)),IFERROR(INDEX(_MainTable!$C$2:$C$2001,MATCH($B56,_MainTable!$F$2:$F$2001,0)),"")))&""="","—",(IFERROR(INDEX(_RefTable!$E$2:$E$501,MATCH($B56,_RefTable!$C$2:$C$501,0)),IFERROR(INDEX(_MainTable!$C$2:$C$2001,MATCH($B56,_MainTable!$F$2:$F$2001,0)),""))))) | E56: =IF($B56="","",IF((IFERROR(INDEX(_RefTable!$F$2:$F$501,MATCH($B56,_RefTable!$C$2:$C$501,0)),IFERROR(INDEX(_MainTable!$D$2:$D$2001,MATCH($B56,_MainTable!$F$2:$F$2001,0)),"")))&""="","—",(IFERROR(INDEX(_RefTable!$F$2:$F$501,MATCH($B56,_RefTable!$C$2:$C$501,0)),IFERROR(INDEX(_MainTable!$D$2:$D$2001,MATCH($B56,_MainTable!$F$2:$F$2001,0)),""))))) | F56: =IF($B56="","",IFERROR(_xlfn.MINIFS('SC Change Orders'!$E$2:$E$501,'SC Change Orders'!$B$2:$B$501,$B56,'SC Change Orders'!$C$2:$C$501,">="&Controls!$C$5,'SC Change Orders'!$C$2:$C$501,"<="&Controls!$C$6),0)) | G56: =IF($B56="","",SUMIFS('SC Change Orders'!$F$2:$F$501,'SC Change Orders'!$B$2:$B$501,$B56,'SC Change Orders'!$C$2:$C$501,">="&Controls!$C$5,'SC Change Orders'!$C$2:$C$501,"<="&Controls!$C$6)) | H56: =IF($B56="","",$F56+$G56) | I56: =IF($B56="","",SUMIFS(_MainTable!$K$2:$K$2001,_MainTable!$F$2:$F$2001,$B56,_MainTable!$G$2:$G$2001,">="&Controls!$C$5,_MainTable!$G$2:$G$2001,"<="&Controls!$C$6)) | J56: =IF($B56="","",IFERROR($I56/$H56,0)) | K56: =IF($B56="","",$H56-$I56) | L56: =IF($B56="","",IFERROR(SUMIFS(_MainTable!$K$2:$K$2001,_MainTable!$F$2:$F$2001,$B56,_MainTable!$G$2:$G$2001,">="&Controls!$C$12,_MainTable!$G$2:$G$2001,"<="&EOMONTH(Controls!$C$7,0))/MIN(Controls!$C$9,Controls!$C$10),0)) | M56: =IF($B56="","",$L56*Controls!$C$11) | N56: =IF($B56="","",$I56+$M56) | O56: =IF($B56="","",IFERROR($N56/$H56,0)) | P56: =IF($B56="","",$H56-$N56) | Q56: =IF($B56="","",IF($L56<=0,"n/a",IFERROR($K56/$L56,"n/a"))) | R56: =IF($B56="","",IF(AND($H56=0,$I56=0),"⚪ No Activity",IF(AND($H56=0,COUNTIFS('SC Change Orders'!$B$2:$B$501,$B56,'SC Change Orders'!$C$2:$C$501,">="&Controls!$C$5,'SC Change Orders'!$C$2:$C$501,"<="&Controls!$C$6)=0),"⚪ No Funding on File",IF($H56=0,"🔴 Unfunded Spend",IF($I56>=$H56,"🔴 Over Budget",IF($N56>$H56,"🔴 Projected Shortfall",IF($J56>=Controls!$C$8,"🟡 Watch","🟢 On Track")))))))
A57: =IF($B57="","",IF((IFERROR(INDEX(_RefTable!$A$2:$A$501,MATCH($B57,_RefTable!$C$2:$C$501,0)),IFERROR(INDEX(_MainTable!$A$2:$A$2001,MATCH($B57,_MainTable!$F$2:$F$2001,0)),IFERROR(INDEX('SC Change Orders'!$A$2:$A$501,MATCH($B57,'SC Change Orders'!$B$2:$B$501,0)),"(unknown vendor)"))))&""="","—",(IFERROR(INDEX(_RefTable!$A$2:$A$501,MATCH($B57,_RefTable!$C$2:$C$501,0)),IFERROR(INDEX(_MainTable!$A$2:$A$2001,MATCH($B57,_MainTable!$F$2:$F$2001,0)),IFERROR(INDEX('SC Change Orders'!$A$2:$A$501,MATCH($B57,'SC Change Orders'!$B$2:$B$501,0)),"(unknown vendor)")))))) | B57: =IFERROR(INDEX('PO Index'!$B$5:$B$84,53),"") | C57: =IF($B57="","",IF((IFERROR(INDEX(_RefTable!$B$2:$B$501,MATCH($B57,_RefTable!$C$2:$C$501,0))&IF(COUNTIF(_RefTable!$C$2:$C$501,$B57)>1," (+"&COUNTIF(_RefTable!$C$2:$C$501,$B57)-1&" more)",""),IFERROR(INDEX(_MainTable!$B$2:$B$2001,MATCH($B57,_MainTable!$F$2:$F$2001,0)),"")))&""="","—",(IFERROR(INDEX(_RefTable!$B$2:$B$501,MATCH($B57,_RefTable!$C$2:$C$501,0))&IF(COUNTIF(_RefTable!$C$2:$C$501,$B57)>1," (+"&COUNTIF(_RefTable!$C$2:$C$501,$B57)-1&" more)",""),IFERROR(INDEX(_MainTable!$B$2:$B$2001,MATCH($B57,_MainTable!$F$2:$F$2001,0)),""))))) | D57: =IF($B57="","",IF((IFERROR(INDEX(_RefTable!$E$2:$E$501,MATCH($B57,_RefTable!$C$2:$C$501,0)),IFERROR(INDEX(_MainTable!$C$2:$C$2001,MATCH($B57,_MainTable!$F$2:$F$2001,0)),"")))&""="","—",(IFERROR(INDEX(_RefTable!$E$2:$E$501,MATCH($B57,_RefTable!$C$2:$C$501,0)),IFERROR(INDEX(_MainTable!$C$2:$C$2001,MATCH($B57,_MainTable!$F$2:$F$2001,0)),""))))) | E57: =IF($B57="","",IF((IFERROR(INDEX(_RefTable!$F$2:$F$501,MATCH($B57,_RefTable!$C$2:$C$501,0)),IFERROR(INDEX(_MainTable!$D$2:$D$2001,MATCH($B57,_MainTable!$F$2:$F$2001,0)),"")))&""="","—",(IFERROR(INDEX(_RefTable!$F$2:$F$501,MATCH($B57,_RefTable!$C$2:$C$501,0)),IFERROR(INDEX(_MainTable!$D$2:$D$2001,MATCH($B57,_MainTable!$F$2:$F$2001,0)),""))))) | F57: =IF($B57="","",IFERROR(_xlfn.MINIFS('SC Change Orders'!$E$2:$E$501,'SC Change Orders'!$B$2:$B$501,$B57,'SC Change Orders'!$C$2:$C$501,">="&Controls!$C$5,'SC Change Orders'!$C$2:$C$501,"<="&Controls!$C$6),0)) | G57: =IF($B57="","",SUMIFS('SC Change Orders'!$F$2:$F$501,'SC Change Orders'!$B$2:$B$501,$B57,'SC Change Orders'!$C$2:$C$501,">="&Controls!$C$5,'SC Change Orders'!$C$2:$C$501,"<="&Controls!$C$6)) | H57: =IF($B57="","",$F57+$G57) | I57: =IF($B57="","",SUMIFS(_MainTable!$K$2:$K$2001,_MainTable!$F$2:$F$2001,$B57,_MainTable!$G$2:$G$2001,">="&Controls!$C$5,_MainTable!$G$2:$G$2001,"<="&Controls!$C$6)) | J57: =IF($B57="","",IFERROR($I57/$H57,0)) | K57: =IF($B57="","",$H57-$I57) | L57: =IF($B57="","",IFERROR(SUMIFS(_MainTable!$K$2:$K$2001,_MainTable!$F$2:$F$2001,$B57,_MainTable!$G$2:$G$2001,">="&Controls!$C$12,_MainTable!$G$2:$G$2001,"<="&EOMONTH(Controls!$C$7,0))/MIN(Controls!$C$9,Controls!$C$10),0)) | M57: =IF($B57="","",$L57*Controls!$C$11) | N57: =IF($B57="","",$I57+$M57) | O57: =IF($B57="","",IFERROR($N57/$H57,0)) | P57: =IF($B57="","",$H57-$N57) | Q57: =IF($B57="","",IF($L57<=0,"n/a",IFERROR($K57/$L57,"n/a"))) | R57: =IF($B57="","",IF(AND($H57=0,$I57=0),"⚪ No Activity",IF(AND($H57=0,COUNTIFS('SC Change Orders'!$B$2:$B$501,$B57,'SC Change Orders'!$C$2:$C$501,">="&Controls!$C$5,'SC Change Orders'!$C$2:$C$501,"<="&Controls!$C$6)=0),"⚪ No Funding on File",IF($H57=0,"🔴 Unfunded Spend",IF($I57>=$H57,"🔴 Over Budget",IF($N57>$H57,"🔴 Projected Shortfall",IF($J57>=Controls!$C$8,"🟡 Watch","🟢 On Track")))))))
A58: =IF($B58="","",IF((IFERROR(INDEX(_RefTable!$A$2:$A$501,MATCH($B58,_RefTable!$C$2:$C$501,0)),IFERROR(INDEX(_MainTable!$A$2:$A$2001,MATCH($B58,_MainTable!$F$2:$F$2001,0)),IFERROR(INDEX('SC Change Orders'!$A$2:$A$501,MATCH($B58,'SC Change Orders'!$B$2:$B$501,0)),"(unknown vendor)"))))&""="","—",(IFERROR(INDEX(_RefTable!$A$2:$A$501,MATCH($B58,_RefTable!$C$2:$C$501,0)),IFERROR(INDEX(_MainTable!$A$2:$A$2001,MATCH($B58,_MainTable!$F$2:$F$2001,0)),IFERROR(INDEX('SC Change Orders'!$A$2:$A$501,MATCH($B58,'SC Change Orders'!$B$2:$B$501,0)),"(unknown vendor)")))))) | B58: =IFERROR(INDEX('PO Index'!$B$5:$B$84,54),"") | C58: =IF($B58="","",IF((IFERROR(INDEX(_RefTable!$B$2:$B$501,MATCH($B58,_RefTable!$C$2:$C$501,0))&IF(COUNTIF(_RefTable!$C$2:$C$501,$B58)>1," (+"&COUNTIF(_RefTable!$C$2:$C$501,$B58)-1&" more)",""),IFERROR(INDEX(_MainTable!$B$2:$B$2001,MATCH($B58,_MainTable!$F$2:$F$2001,0)),"")))&""="","—",(IFERROR(INDEX(_RefTable!$B$2:$B$501,MATCH($B58,_RefTable!$C$2:$C$501,0))&IF(COUNTIF(_RefTable!$C$2:$C$501,$B58)>1," (+"&COUNTIF(_RefTable!$C$2:$C$501,$B58)-1&" more)",""),IFERROR(INDEX(_MainTable!$B$2:$B$2001,MATCH($B58,_MainTable!$F$2:$F$2001,0)),""))))) | D58: =IF($B58="","",IF((IFERROR(INDEX(_RefTable!$E$2:$E$501,MATCH($B58,_RefTable!$C$2:$C$501,0)),IFERROR(INDEX(_MainTable!$C$2:$C$2001,MATCH($B58,_MainTable!$F$2:$F$2001,0)),"")))&""="","—",(IFERROR(INDEX(_RefTable!$E$2:$E$501,MATCH($B58,_RefTable!$C$2:$C$501,0)),IFERROR(INDEX(_MainTable!$C$2:$C$2001,MATCH($B58,_MainTable!$F$2:$F$2001,0)),""))))) | E58: =IF($B58="","",IF((IFERROR(INDEX(_RefTable!$F$2:$F$501,MATCH($B58,_RefTable!$C$2:$C$501,0)),IFERROR(INDEX(_MainTable!$D$2:$D$2001,MATCH($B58,_MainTable!$F$2:$F$2001,0)),"")))&""="","—",(IFERROR(INDEX(_RefTable!$F$2:$F$501,MATCH($B58,_RefTable!$C$2:$C$501,0)),IFERROR(INDEX(_MainTable!$D$2:$D$2001,MATCH($B58,_MainTable!$F$2:$F$2001,0)),""))))) | F58: =IF($B58="","",IFERROR(_xlfn.MINIFS('SC Change Orders'!$E$2:$E$501,'SC Change Orders'!$B$2:$B$501,$B58,'SC Change Orders'!$C$2:$C$501,">="&Controls!$C$5,'SC Change Orders'!$C$2:$C$501,"<="&Controls!$C$6),0)) | G58: =IF($B58="","",SUMIFS('SC Change Orders'!$F$2:$F$501,'SC Change Orders'!$B$2:$B$501,$B58,'SC Change Orders'!$C$2:$C$501,">="&Controls!$C$5,'SC Change Orders'!$C$2:$C$501,"<="&Controls!$C$6)) | H58: =IF($B58="","",$F58+$G58) | I58: =IF($B58="","",SUMIFS(_MainTable!$K$2:$K$2001,_MainTable!$F$2:$F$2001,$B58,_MainTable!$G$2:$G$2001,">="&Controls!$C$5,_MainTable!$G$2:$G$2001,"<="&Controls!$C$6)) | J58: =IF($B58="","",IFERROR($I58/$H58,0)) | K58: =IF($B58="","",$H58-$I58) | L58: =IF($B58="","",IFERROR(SUMIFS(_MainTable!$K$2:$K$2001,_MainTable!$F$2:$F$2001,$B58,_MainTable!$G$2:$G$2001,">="&Controls!$C$12,_MainTable!$G$2:$G$2001,"<="&EOMONTH(Controls!$C$7,0))/MIN(Controls!$C$9,Controls!$C$10),0)) | M58: =IF($B58="","",$L58*Controls!$C$11) | N58: =IF($B58="","",$I58+$M58) | O58: =IF($B58="","",IFERROR($N58/$H58,0)) | P58: =IF($B58="","",$H58-$N58) | Q58: =IF($B58="","",IF($L58<=0,"n/a",IFERROR($K58/$L58,"n/a"))) | R58: =IF($B58="","",IF(AND($H58=0,$I58=0),"⚪ No Activity",IF(AND($H58=0,COUNTIFS('SC Change Orders'!$B$2:$B$501,$B58,'SC Change Orders'!$C$2:$C$501,">="&Controls!$C$5,'SC Change Orders'!$C$2:$C$501,"<="&Controls!$C$6)=0),"⚪ No Funding on File",IF($H58=0,"🔴 Unfunded Spend",IF($I58>=$H58,"🔴 Over Budget",IF($N58>$H58,"🔴 Projected Shortfall",IF($J58>=Controls!$C$8,"🟡 Watch","🟢 On Track")))))))
A59: =IF($B59="","",IF((IFERROR(INDEX(_RefTable!$A$2:$A$501,MATCH($B59,_RefTable!$C$2:$C$501,0)),IFERROR(INDEX(_MainTable!$A$2:$A$2001,MATCH($B59,_MainTable!$F$2:$F$2001,0)),IFERROR(INDEX('SC Change Orders'!$A$2:$A$501,MATCH($B59,'SC Change Orders'!$B$2:$B$501,0)),"(unknown vendor)"))))&""="","—",(IFERROR(INDEX(_RefTable!$A$2:$A$501,MATCH($B59,_RefTable!$C$2:$C$501,0)),IFERROR(INDEX(_MainTable!$A$2:$A$2001,MATCH($B59,_MainTable!$F$2:$F$2001,0)),IFERROR(INDEX('SC Change Orders'!$A$2:$A$501,MATCH($B59,'SC Change Orders'!$B$2:$B$501,0)),"(unknown vendor)")))))) | B59: =IFERROR(INDEX('PO Index'!$B$5:$B$84,55),"") | C59: =IF($B59="","",IF((IFERROR(INDEX(_RefTable!$B$2:$B$501,MATCH($B59,_RefTable!$C$2:$C$501,0))&IF(COUNTIF(_RefTable!$C$2:$C$501,$B59)>1," (+"&COUNTIF(_RefTable!$C$2:$C$501,$B59)-1&" more)",""),IFERROR(INDEX(_MainTable!$B$2:$B$2001,MATCH($B59,_MainTable!$F$2:$F$2001,0)),"")))&""="","—",(IFERROR(INDEX(_RefTable!$B$2:$B$501,MATCH($B59,_RefTable!$C$2:$C$501,0))&IF(COUNTIF(_RefTable!$C$2:$C$501,$B59)>1," (+"&COUNTIF(_RefTable!$C$2:$C$501,$B59)-1&" more)",""),IFERROR(INDEX(_MainTable!$B$2:$B$2001,MATCH($B59,_MainTable!$F$2:$F$2001,0)),""))))) | D59: =IF($B59="","",IF((IFERROR(INDEX(_RefTable!$E$2:$E$501,MATCH($B59,_RefTable!$C$2:$C$501,0)),IFERROR(INDEX(_MainTable!$C$2:$C$2001,MATCH($B59,_MainTable!$F$2:$F$2001,0)),"")))&""="","—",(IFERROR(INDEX(_RefTable!$E$2:$E$501,MATCH($B59,_RefTable!$C$2:$C$501,0)),IFERROR(INDEX(_MainTable!$C$2:$C$2001,MATCH($B59,_MainTable!$F$2:$F$2001,0)),""))))) | E59: =IF($B59="","",IF((IFERROR(INDEX(_RefTable!$F$2:$F$501,MATCH($B59,_RefTable!$C$2:$C$501,0)),IFERROR(INDEX(_MainTable!$D$2:$D$2001,MATCH($B59,_MainTable!$F$2:$F$2001,0)),"")))&""="","—",(IFERROR(INDEX(_RefTable!$F$2:$F$501,MATCH($B59,_RefTable!$C$2:$C$501,0)),IFERROR(INDEX(_MainTable!$D$2:$D$2001,MATCH($B59,_MainTable!$F$2:$F$2001,0)),""))))) | F59: =IF($B59="","",IFERROR(_xlfn.MINIFS('SC Change Orders'!$E$2:$E$501,'SC Change Orders'!$B$2:$B$501,$B59,'SC Change Orders'!$C$2:$C$501,">="&Controls!$C$5,'SC Change Orders'!$C$2:$C$501,"<="&Controls!$C$6),0)) | G59: =IF($B59="","",SUMIFS('SC Change Orders'!$F$2:$F$501,'SC Change Orders'!$B$2:$B$501,$B59,'SC Change Orders'!$C$2:$C$501,">="&Controls!$C$5,'SC Change Orders'!$C$2:$C$501,"<="&Controls!$C$6)) | H59: =IF($B59="","",$F59+$G59) | I59: =IF($B59="","",SUMIFS(_MainTable!$K$2:$K$2001,_MainTable!$F$2:$F$2001,$B59,_MainTable!$G$2:$G$2001,">="&Controls!$C$5,_MainTable!$G$2:$G$2001,"<="&Controls!$C$6)) | J59: =IF($B59="","",IFERROR($I59/$H59,0)) | K59: =IF($B59="","",$H59-$I59) | L59: =IF($B59="","",IFERROR(SUMIFS(_MainTable!$K$2:$K$2001,_MainTable!$F$2:$F$2001,$B59,_MainTable!$G$2:$G$2001,">="&Controls!$C$12,_MainTable!$G$2:$G$2001,"<="&EOMONTH(Controls!$C$7,0))/MIN(Controls!$C$9,Controls!$C$10),0)) | M59: =IF($B59="","",$L59*Controls!$C$11) | N59: =IF($B59="","",$I59+$M59) | O59: =IF($B59="","",IFERROR($N59/$H59,0)) | P59: =IF($B59="","",$H59-$N59) | Q59: =IF($B59="","",IF($L59<=0,"n/a",IFERROR($K59/$L59,"n/a"))) | R59: =IF($B59="","",IF(AND($H59=0,$I59=0),"⚪ No Activity",IF(AND($H59=0,COUNTIFS('SC Change Orders'!$B$2:$B$501,$B59,'SC Change Orders'!$C$2:$C$501,">="&Controls!$C$5,'SC Change Orders'!$C$2:$C$501,"<="&Controls!$C$6)=0),"⚪ No Funding on File",IF($H59=0,"🔴 Unfunded Spend",IF($I59>=$H59,"🔴 Over Budget",IF($N59>$H59,"🔴 Projected Shortfall",IF($J59>=Controls!$C$8,"🟡 Watch","🟢 On Track")))))))
